Workbook
Name acq: 'A&R'!$D$13
Name Cir: 'A&R'!$I$9
Name exit: 'A&R'!$D$16
Name period: 'A&R'!$D$17
Name py: 'A&R'!$D$11
Name start: 'A&R'!$D$14
Name unit: 'A&R'!$D$10

Sheet A&R
B2: Team LAVEL | AF2: 변수입력 | AG2: 합계1 | AH2: 제목
B3: KBC타워 재무모델 | AF3: 적정성확인 | AG3: 합계2 | AH3: 표제목
AF4: 오류확인 | AG4: 합계3 | AH4: 작성자참고
A6: 단위: 백만원 | AH6: 45611
A7: Assumption & Result
B8: 기본가정 | U8: 운영비용 및 기타수입 가정
B9: •투자 Vehicle: | D9: 부동산펀드(REF) | G9: •Circulation Switch | I9: 1 | U9: 운영비용 가정 | AC9: Leasing비용 가정
B10: •화폐단위: | D10: 1000000 | E10: 원 | U10: 구분 | V10: 주요가정 | Z10: 비고 | AC10: 구분 | AD10: 주요가정
B11: •1㎡ = | D11: 0.3025 | E11: 평 | U11: PM Fee | V11: 평단가/월 | W11: 900 | X11: 연 상승률 | Y11: 0.025 | AC11: 재계약시 | AD11: 실질 월 임대료의 | AF11: 0.7
B12: •날짜입력: | D12: 월말기준 | U12: FM Fee | V12: 평단가/월 | W12: 11000 | X12: 연 상승률 | Y12: 0.025 | AC12: 신규계약시 | AD12: 실질 월 임대료의 | AF12: 2.1 | AG12: 최초 1기 6개월 지급이연
B13: •자산취득월: | D13: 45688 | U13: 수도광열비 | V13: 평단가/월 | W13: 8000 | X13: 연 상승률 | Y13: 0.025 | AG13: 대신 10%p 상향계약
B14: •자산운용시작월: | D14: =EOMONTH(D13,1) -> 45716 | U14: 유지관리비 | V14: 평단가/월 | W14: 3500 | X14: 연 상승률 | Y14: 0.025 | Z14: 매입 1달 후 30% 감소 | AC14: 기타수입 가정
B15: •자산운용기간: | D15: 5 | U15: 보험료 | V15: 평단가/월 | W15: 200 | X15: 연 상승률 | Y15: 0.025 | AC15: 구분 | AE15: 주요가정
B16: •자산매각월: | D16: =EOMONTH(D13,12*D15) -> 47514 | U16: 제세공과금 | V16: 매입가의 | W16: 0.005 | X16: 연 상승률 | Y16: 0.025 | AC16: 주차수입 | AE16: 40 | AF16: 백만원/월 | AG16: 연 상승률 | AH16: 0.025
B17: •회계기간: | D17: 6 | AC17: 기타수입 | AE17: 평단가/월 | AF17: 2000 | AG17: 연 상승률 | AH17: 0.025
B18: 자산개요 | U18: 펀드 및 기타비용 가정 | AC18: 전광판수입 | AE18: 240 | AF18: 백만원/월 | AG18: 연 상승률 | AH18: 0.025
B19: •자산명: | D19: KBC타워 | I19: •타입: | K19: 오피스(중대형, B Grade) | U19: 구분 | X19: 주요가정 | AC19: 옥외전광판 공사기간 1개월
B20: •위치: | D20: 서울시 중구 남대문로 125 | I20: •연면적: | K20: 25076 | L20: ㎡ ➔ | M20: =K20*py -> 7585.49 | N20: 평 | U20: 집합투자업자 운용보수 | X20: 400 | Y20: 백만원/년
B21: •용도지역: | D21: 일반상업지역 | I21: •준공연도: | K21: 40209 | L21: 년 | U21: 신탁업자 자산수탁 보수 | X21: 60 | Y21: 백만원/년
B22: •대지면적: | D22: 2115 | E22: ㎡ | F22: =D22*py -> 639.7875 | G22: 평 | I22: •건물규모: | K22: 지하5층 / 지상17층 | U22: 투자매매/중개업자 판매보수 | X22: 40 | Y22: 백만원/년
B23: •공시지가: | D23: 65430000 | E23: 원/㎡ ➔ | F23: =D22*D23/unit -> 138384.45 | G23: 백만원 | I23: •매입가 적정성: | K23: Stb Initial Cap | M23: =$G$27 -> 0.047656366 | U23: 일반사무관리회사 업무보수 | X23: 25 | Y23: 백만원/년
B24: •기존 Rentroll 공실률: | D24: =SUM(Rentroll!F23:F26)/Rentroll!F32 -> 0.22099455 | K24: 연면적당 매입가 | M24: =E27/M20 -> 31.112031 | N24: 백만원/평 | U24: Other Fees (Acc./Tax/etc.) | X24: 45 | Y24: 백만원/년
B25: 투자비 산정 | U25: 자산매각 가정
B26: 구분 | E26: 금액 | F26: 산정근거 | I26: 비율 | J26: 비고 | U26: 1. 연차별 NOI산정
B27: 매입가격 | E27: 236000 | F27: Stb Initial Cap | G27: =$AF$44/($E$27-$E$54) -> 0.047656366 | I27: =E27/$E$43 -> 0.91291074 | K27: Going-in Cap | M27: =$AH$44/($E$27-$E$54) -> 0.036638203 | U27: 연차 | X27: 합게 | Y27: 1 | Z27: 2 | AA27: 3 | AB27: 4 | AC27: 5 | AD27: 6 | AE27: 7 | AF27: 8 | AG27: 9 | AH27: 10
B28: 부대비용 | E28: =SUM(E29:E31) -> 13480 | I28: =E28/$E$43 -> 0.052144224 | L28: =I28+I32 -> 0.054397022 | M28: =E28+E32 -> 14062.379 | U28: 운영수입 | X28: =SUM(Y28:AH28) -> 81962.918 | Y28: =SUM(Y29:Y33) -> 14253.082 | Z28: =SUM(Z29:Z33) -> 15959.019 | AA28: =SUM(AA29:AA33) -> 16464.692 | AB28: =SUM(AB29:AB33) -> 17274.609 | AC28: =SUM(AC29:AC33) -> 18011.516 | AD28: =SUM(AD29:AD33) -> 0 | AE28: =SUM(AE29:AE33) -> 0 | AF28: =SUM(AF29:AF33) -> 0 | ... AH28: =SUM(AH29:AH33) -> 0
C29: AMC 매입보수 | E29: =E27*G29 -> 1652 | F29: 매입가의 | G29: 0.007 | V29: 임대료 수입 | W29: =ABS(X29-운영수입!Q18)<0.001 -> TRUE | X29: =SUM(Y29:AH29) -> 42367.537 | Y29: =SUMIF(운영수입!$S$16:$DM$16,Y$27,운영수입!$S$18:$DM$18) -> 7028.616 | Z29: =SUMIF(운영수입!$S$16:$DM$16,Z$27,운영수입!$S$18:$DM$18) -> 8216.2367 | AA29: =SUMIF(운영수입!$S$16:$DM$16,AA$27,운영수입!$S$18:$DM$18) -> 8467.0596 | AB29: =SUMIF(운영수입!$S$16:$DM$16,AB$27,운영수입!$S$18:$DM$18) -> 9065.4481 | AC29: =SUMIF(운영수입!$S$16:$DM$16,AC$27,운영수입!$S$18:$DM$18) -> 9590.1767 | AD29: =SUMIF(운영수입!$S$16:$DM$16,AD$27,운영수입!$S$18:$DM$18) -> 0 | AE29: =SUMIF(운영수입!$S$16:$DM$16,AE$27,운영수입!$S$18:$DM$18) -> 0 | AF29: =SUMIF(운영수입!$S$16:$DM$16,AF$27,운영수입!$S$18:$DM$18) -> 0 | ... AH29: =SUMIF(운영수입!$S$16:$DM$16,AH$27,운영수입!$S$18:$DM$18) -> 0
C30: 소유권 이전비용 | E30: =E27*G30 -> 11328 | F30: 매입가의 | G30: 0.048 | J30: 취득세, 담보설정비용 포함 | V30: 관리비 수입 | W30: =ABS(X30-운영수입!Q65)<0.001 -> TRUE | X30: =SUM(Y30:AH30) -> 21242.108 | Y30: =SUMIF(운영수입!$S$16:$DM$16,Y$27,운영수입!$S$65:$DM$65) -> 3922.4142 | Z30: =SUMIF(운영수입!$S$16:$DM$16,Z$27,운영수입!$S$65:$DM$65) -> 4118.1793 | AA30: =SUMIF(운영수입!$S$16:$DM$16,AA$27,운영수입!$S$65:$DM$65) -> 4282.414 | AB30: =SUMIF(운영수입!$S$16:$DM$16,AB$27,운영수입!$S$65:$DM$65) -> 4401.0627 | AC30: =SUMIF(운영수입!$S$16:$DM$16,AC$27,운영수입!$S$65:$DM$65) -> 4518.038 | AD30: =SUMIF(운영수입!$S$16:$DM$16,AD$27,운영수입!$S$65:$DM$65) -> 0 | AE30: =SUMIF(운영수입!$S$16:$DM$16,AE$27,운영수입!$S$65:$DM$65) -> 0 | AF30: =SUMIF(운영수입!$S$16:$DM$16,AF$27,운영수입!$S$65:$DM$65) -> 0 | ... AH30: =SUMIF(운영수입!$S$16:$DM$16,AH$27,운영수입!$S$65:$DM$65) -> 0
C31: 실사비용 | E31: 500 | F31: 기본가정사항 | V31: 주차수입 | W31: =ABS(X31-운영수입!Q170)<0.001 -> TRUE | X31: =SUM(Y31:AH31) -> 2523.0377 | Y31: =SUMIF(운영수입!$S$16:$DM$16,Y$27,운영수입!$S$170:$DM$170) -> 480 | Z31: =SUMIF(운영수입!$S$16:$DM$16,Z$27,운영수입!$S$170:$DM$170) -> 492 | AA31: =SUMIF(운영수입!$S$16:$DM$16,AA$27,운영수입!$S$170:$DM$170) -> 504.3 | AB31: =SUMIF(운영수입!$S$16:$DM$16,AB$27,운영수입!$S$170:$DM$170) -> 516.9075 | AC31: =SUMIF(운영수입!$S$16:$DM$16,AC$27,운영수입!$S$170:$DM$170) -> 529.83019 | AD31: =SUMIF(운영수입!$S$16:$DM$16,AD$27,운영수입!$S$170:$DM$170) -> 0 | AE31: =SUMIF(운영수입!$S$16:$DM$16,AE$27,운영수입!$S$170:$DM$170) -> 0 | AF31: =SUMIF(운영수입!$S$16:$DM$16,AF$27,운영수입!$S$170:$DM$170) -> 0 | ... AH31: =SUMIF(운영수입!$S$16:$DM$16,AH$27,운영수입!$S$170:$DM$170) -> 0
B32: 금융비용 | E32: =E33 -> 582.37934 | I32: =E32/$E$43 -> 0.0022527981 | V32: 기타수입 | W32: =ABS(X32-운영수입!Q175)<0.001 -> TRUE | X32: =SUM(Y32:AH32) -> 956.92386 | Y32: =SUMIF(운영수입!$S$16:$DM$16,Y$27,운영수입!$S$175:$DM$175) -> 182.05176 | Z32: =SUMIF(운영수입!$S$16:$DM$16,Z$27,운영수입!$S$175:$DM$175) -> 186.60305 | AA32: =SUMIF(운영수입!$S$16:$DM$16,AA$27,운영수입!$S$175:$DM$175) -> 191.26813 | AB32: =SUMIF(운영수입!$S$16:$DM$16,AB$27,운영수입!$S$175:$DM$175) -> 196.04983 | AC32: =SUMIF(운영수입!$S$16:$DM$16,AC$27,운영수입!$S$175:$DM$175) -> 200.95108 | AD32: =SUMIF(운영수입!$S$16:$DM$16,AD$27,운영수입!$S$175:$DM$175) -> 0 | AE32: =SUMIF(운영수입!$S$16:$DM$16,AE$27,운영수입!$S$175:$DM$175) -> 0 | AF32: =SUMIF(운영수입!$S$16:$DM$16,AF$27,운영수입!$S$175:$DM$175) -> 0 | ... AH32: =SUMIF(운영수입!$S$16:$DM$16,AH$27,운영수입!$S$175:$DM$175) -> 0
C33: 대출취급수수료 | E33: =(E52*J52)+(E53*J53) -> 582.37934 | F33: 재원조달계획 참조 | V33: 전광판 수입 | W33: =ABS(X33-운영수입!Q180)<0.001 -> TRUE | X33: =SUM(Y33:AH33) -> 14873.311 | Y33: =SUMIF(운영수입!$16:$16,'A&R'!Y27,운영수입!$180:$180) -> 2640 | Z33: =SUMIF(운영수입!$16:$16,'A&R'!Z27,운영수입!$180:$180) -> 2946 | AA33: =SUMIF(운영수입!$16:$16,'A&R'!AA27,운영수입!$180:$180) -> 3019.65 | AB33: =SUMIF(운영수입!$16:$16,'A&R'!AB27,운영수입!$180:$180) -> 3095.1413 | AC33: =SUMIF(운영수입!$16:$16,'A&R'!AC27,운영수입!$180:$180) -> 3172.5198 | AD33: =SUMIF(운영수입!$16:$16,'A&R'!AD27,운영수입!$180:$180) -> 0 | AE33: =SUMIF(운영수입!$16:$16,'A&R'!AE27,운영수입!$180:$180) -> 0 | AF33: =SUMIF(운영수입!$16:$16,'A&R'!AF27,운영수입!$180:$180) -> 0 | ... AH33: =SUMIF(운영수입!$16:$16,'A&R'!AH27,운영수입!$180:$180) -> 0
B34: 공사비용 | E34: =SUM(E35:E39) -> 6600 | I34: =E34/$E$43 -> 0.025530555 | U34: (-)운영비용 | X34: =SUM(Y34:AH34) -> 18020.536 | Y34: =SUM(Y35:Y41) -> 3779.6703 | Z34: =SUM(Z35:Z41) -> 3345.5488 | AA34: =SUM(AA35:AA41) -> 3692.7884 | AB34: =SUM(AB35:AB41) -> 3634.3059 | AC34: =SUM(AC35:AC41) -> 3568.2226 | AD34: =SUM(AD35:AD41) -> 0 | AE34: =SUM(AE35:AE41) -> 0 | AF34: =SUM(AF35:AF41) -> 0 | ... AH34: =SUM(AH35:AH41) -> 0
C35: 로비환경개선공사 | E35: 3000 | F35: 기본가정사항 | V35: =U11 -> PM Fee | X35: =SUM(Y35:AH35) -> 430.61574 | Y35: =SUMIF(운영비용!$H$16:$DB$16,'A&R'!Y$27,운영비용!$H$20:$DB$20) -> 81.923292 | Z35: =SUMIF(운영비용!$H$16:$DB$16,'A&R'!Z$27,운영비용!$H$20:$DB$20) -> 83.971374 | AA35: =SUMIF(운영비용!$H$16:$DB$16,'A&R'!AA$27,운영비용!$H$20:$DB$20) -> 86.070659 | AB35: =SUMIF(운영비용!$H$16:$DB$16,'A&R'!AB$27,운영비용!$H$20:$DB$20) -> 88.222425 | AC35: =SUMIF(운영비용!$H$16:$DB$16,'A&R'!AC$27,운영비용!$H$20:$DB$20) -> 90.427986 | AD35: =SUMIF(운영비용!$H$16:$DB$16,'A&R'!AD$27,운영비용!$H$20:$DB$20) -> 0 | AE35: =SUMIF(운영비용!$H$16:$DB$16,'A&R'!AE$27,운영비용!$H$20:$DB$20) -> 0 | AF35: =SUMIF(운영비용!$H$16:$DB$16,'A&R'!AF$27,운영비용!$H$20:$DB$20) -> 0 | ... AH35: =SUMIF(운영비용!$H$16:$DB$16,'A&R'!AH$27,운영비용!$H$20:$DB$20) -> 0
C36: 용도변경공사 | E36: 300 | F36: 기본가정사항 | V36: =U12 -> FM Fee | X36: =SUM(Y36:AH36) -> 5263.0812 | Y36: =SUMIF(운영비용!$H$16:$DB$16,'A&R'!Y$27,운영비용!$H$25:$DB$25) -> 1001.2847 | Z36: =SUMIF(운영비용!$H$16:$DB$16,'A&R'!Z$27,운영비용!$H$25:$DB$25) -> 1026.3168 | AA36: =SUMIF(운영비용!$H$16:$DB$16,'A&R'!AA$27,운영비용!$H$25:$DB$25) -> 1051.9747 | AB36: =SUMIF(운영비용!$H$16:$DB$16,'A&R'!AB$27,운영비용!$H$25:$DB$25) -> 1078.2741 | AC36: =SUMIF(운영비용!$H$16:$DB$16,'A&R'!AC$27,운영비용!$H$25:$DB$25) -> 1105.2309 | AD36: =SUMIF(운영비용!$H$16:$DB$16,'A&R'!AD$27,운영비용!$H$25:$DB$25) -> 0 | AE36: =SUMIF(운영비용!$H$16:$DB$16,'A&R'!AE$27,운영비용!$H$25:$DB$25) -> 0 | AF36: =SUMIF(운영비용!$H$16:$DB$16,'A&R'!AF$27,운영비용!$H$25:$DB$25) -> 0 | ... AH36: =SUMIF(운영비용!$H$16:$DB$16,'A&R'!AH$27,운영비용!$H$25:$DB$25) -> 0
C37: 에스컬레이터 증설 | E37: 100 | F37: 기본가정사항 | V37: =U13 -> 수도광열비 | X37: =SUM(Y37:AH37) -> 3827.6954 | Y37: =SUMIF(운영비용!$H$16:$DB$16,'A&R'!Y$27,운영비용!$H$30:$DB$30) -> 728.20704 | Z37: =SUMIF(운영비용!$H$16:$DB$16,'A&R'!Z$27,운영비용!$H$30:$DB$30) -> 746.41222 | AA37: =SUMIF(운영비용!$H$16:$DB$16,'A&R'!AA$27,운영비용!$H$30:$DB$30) -> 765.07252 | AB37: =SUMIF(운영비용!$H$16:$DB$16,'A&R'!AB$27,운영비용!$H$30:$DB$30) -> 784.19933 | AC37: =SUMIF(운영비용!$H$16:$DB$16,'A&R'!AC$27,운영비용!$H$30:$DB$30) -> 803.80432 | AD37: =SUMIF(운영비용!$H$16:$DB$16,'A&R'!AD$27,운영비용!$H$30:$DB$30) -> 0 | AE37: =SUMIF(운영비용!$H$16:$DB$16,'A&R'!AE$27,운영비용!$H$30:$DB$30) -> 0 | AF37: =SUMIF(운영비용!$H$16:$DB$16,'A&R'!AF$27,운영비용!$H$30:$DB$30) -> 0 | ... AH37: =SUMIF(운영비용!$H$16:$DB$16,'A&R'!AH$27,운영비용!$H$30:$DB$30) -> 0
C38: 기계/설비 교체 | E38: 2000 | F38: 기본가정사항 | V38: =U14 -> 유지관리비 | X38: =SUM(Y38:AH38) -> 1180.1965 | Y38: =SUMIF(운영비용!$H$16:$DB$16,'A&R'!Y$27,운영비용!$H$35:$DB$35) -> 230.97817 | Z38: =SUMIF(운영비용!$H$16:$DB$16,'A&R'!Z$27,운영비용!$H$35:$DB$35) -> 228.58874 | AA38: =SUMIF(운영비용!$H$16:$DB$16,'A&R'!AA$27,운영비용!$H$35:$DB$35) -> 234.30346 | AB38: =SUMIF(운영비용!$H$16:$DB$16,'A&R'!AB$27,운영비용!$H$35:$DB$35) -> 240.16105 | AC38: =SUMIF(운영비용!$H$16:$DB$16,'A&R'!AC$27,운영비용!$H$35:$DB$35) -> 246.16507 | AD38: =SUMIF(운영비용!$H$16:$DB$16,'A&R'!AD$27,운영비용!$H$35:$DB$35) -> 0 | AE38: =SUMIF(운영비용!$H$16:$DB$16,'A&R'!AE$27,운영비용!$H$35:$DB$35) -> 0 | AF38: =SUMIF(운영비용!$H$16:$DB$16,'A&R'!AF$27,운영비용!$H$35:$DB$35) -> 0 | ... AH38: =SUMIF(운영비용!$H$16:$DB$16,'A&R'!AH$27,운영비용!$H$35:$DB$35) -> 0
C39: 기타 공사비 | E39: 1200 | J39: 커튼월, 테라스공사, 옥외전광판 설치 등 | V39: =U15 -> 보험료 | X39: =SUM(Y39:AH39) -> 95.692386 | Y39: =SUMIF(운영비용!$H$16:$DB$16,'A&R'!Y$27,운영비용!$H$40:$DB$40) -> 18.205176 | Z39: =SUMIF(운영비용!$H$16:$DB$16,'A&R'!Z$27,운영비용!$H$40:$DB$40) -> 18.660305 | AA39: =SUMIF(운영비용!$H$16:$DB$16,'A&R'!AA$27,운영비용!$H$40:$DB$40) -> 19.126813 | AB39: =SUMIF(운영비용!$H$16:$DB$16,'A&R'!AB$27,운영비용!$H$40:$DB$40) -> 19.604983 | AC39: =SUMIF(운영비용!$H$16:$DB$16,'A&R'!AC$27,운영비용!$H$40:$DB$40) -> 20.095108 | AD39: =SUMIF(운영비용!$H$16:$DB$16,'A&R'!AD$27,운영비용!$H$40:$DB$40) -> 0 | AE39: =SUMIF(운영비용!$H$16:$DB$16,'A&R'!AE$27,운영비용!$H$40:$DB$40) -> 0 | AF39: =SUMIF(운영비용!$H$16:$DB$16,'A&R'!AF$27,운영비용!$H$40:$DB$40) -> 0 | ... AH39: =SUMIF(운영비용!$H$16:$DB$16,'A&R'!AH$27,운영비용!$H$40:$DB$40) -> 0
B40: 기타예비비 | E40: =SUM(E41:E42) -> 1851.3938 | I40: =E40/$E$43 -> 0.0071616835 | V40: =U16 -> 제세공과금 | X40: =SUM(Y40:AH40) -> 6202.4676 | Y40: =SUMIF(운영비용!$H$16:$DB$16,'A&R'!Y$27,운영비용!$H$45:$DB$45) -> 1180 | Z40: =SUMIF(운영비용!$H$16:$DB$16,'A&R'!Z$27,운영비용!$H$45:$DB$45) -> 1209.5 | AA40: =SUMIF(운영비용!$H$16:$DB$16,'A&R'!AA$27,운영비용!$H$45:$DB$45) -> 1239.7375 | AB40: =SUMIF(운영비용!$H$16:$DB$16,'A&R'!AB$27,운영비용!$H$45:$DB$45) -> 1270.7309 | AC40: =SUMIF(운영비용!$H$16:$DB$16,'A&R'!AC$27,운영비용!$H$45:$DB$45) -> 1302.4992 | AD40: =SUMIF(운영비용!$H$16:$DB$16,'A&R'!AD$27,운영비용!$H$45:$DB$45) -> 0 | AE40: =SUMIF(운영비용!$H$16:$DB$16,'A&R'!AE$27,운영비용!$H$45:$DB$45) -> 0 | AF40: =SUMIF(운영비용!$H$16:$DB$16,'A&R'!AF$27,운영비용!$H$45:$DB$45) -> 0 | ... AH40: =SUMIF(운영비용!$H$16:$DB$16,'A&R'!AH$27,운영비용!$H$45:$DB$45) -> 0
C41: 임차인유치비용(TI) | E41: =Rentroll!AC63 -> 251.39383 | F41: Rentroll 참조 | V41: Leasing 비용 | X41: =SUM(Y41:AH41) -> 1020.7871 | Y41: =SUMIF(운영비용!$H$16:$DB$16,'A&R'!Y$27,운영비용!$H$73:$DB$73) -> 539.07189 | Z41: =SUMIF(운영비용!$H$16:$DB$16,'A&R'!Z$27,운영비용!$H$73:$DB$73) -> 32.09936 | AA41: =SUMIF(운영비용!$H$16:$DB$16,'A&R'!AA$27,운영비용!$H$73:$DB$73) -> 296.50276 | AB41: =SUMIF(운영비용!$H$16:$DB$16,'A&R'!AB$27,운영비용!$H$73:$DB$73) -> 153.11307 | AC41: =SUMIF(운영비용!$H$16:$DB$16,'A&R'!AC$27,운영비용!$H$73:$DB$73) -> 0 | AD41: =SUMIF(운영비용!$H$16:$DB$16,'A&R'!AD$27,운영비용!$H$73:$DB$73) -> 0 | AE41: =SUMIF(운영비용!$H$16:$DB$16,'A&R'!AE$27,운영비용!$H$73:$DB$73) -> 0 | AF41: =SUMIF(운영비용!$H$16:$DB$16,'A&R'!AF$27,운영비용!$H$73:$DB$73) -> 0 | ... AH41: =SUMIF(운영비용!$H$16:$DB$16,'A&R'!AH$27,운영비용!$H$73:$DB$73) -> 0
C42: 순수 예비비 | E42: 1600 | U42: NOI | X42: =SUM(Y42:AH42) -> 63942.382 | Y42: =Y28-Y34 -> 10473.412 | Z42: =Z28-Z34 -> 12613.47 | AA42: =AA28-AA34 -> 12771.903 | AB42: =AB28-AB34 -> 13640.304 | AC42: =AC28-AC34 -> 14443.293 | AD42: =AD28-AD34 -> 0 | AE42: =AE28-AE34 -> 0 | AF42: =AF28-AF34 -> 0 | ... AH42: =AH28-AH34 -> 0
B43: 합계 | E43: =E27+E28+E32+E34+E40 -> 258513.77 | I43: =SUM(I27:I42) -> 1 | V43: NOI Margin | Y43: =IFERROR(Y42/Y28," ") -> 0.73481734 | Z43: =IFERROR(Z42/Z28," ") -> 0.79036626 | AA43: =IFERROR(AA42/AA28," ") -> 0.77571469 | AB43: =IFERROR(AB42/AB28," ") -> 0.78961574 | AC43: =IFERROR(AC42/AC28," ") -> 0.80189215 | AD43: =IFERROR(AD42/AD28," ") | AE43: =IFERROR(AE42/AE28," ") | AF43: =IFERROR(AF42/AF28," ") | ... AH43: =IFERROR(AH42/AH28," ")
B44: 재원조달계획 | U44: 2. N+1년차 Normalized NOI 추정 | Y44: =Y34-Y41 -> 3240.5984 | AD44: Normalized | AE44: 공실 미반영 | AF44: =Y28-Y44 -> 11012.484 | AG44: 공실 반영 | AH44: =Rentroll!$Z$32+X31+X32-$Y$44 -> 8466.3948
B45: 조달필요액 | E45: =E43 -> 258513.77 | U45: 1) 자산매각일 | X45: =exit -> 47514 | Y45: =D15 -> 5
B46: 재원조달액 | U46: 2) N+1년차 Normalized 운영수입
B47: 자기자본 | E47: 합계 | F47: 발행일 | G47: 누적배당률 | H47: 매각차익분배 | I47: 비고 | O47: 전체비율 | U47: 구분 | V47: 임대면적(평) | W47: 신규계약일 | X47: 계약조건 | AC47: N+1년차
C48: 제1종수익증권 | E48: 51500 | F48: =acq -> 45688 | G48: 0.065 | H48: 0.1 | I48: 에코생명 | M48: =E48/E50 -> 0.5255102 | O48: =E48/E56 -> 0.19921569 | X48: 임대료단가 | Y48: 관리비단가 | Z48: 임대료상승률 | AA48: 관리비상승률 | AB48: Rentfree | AC48: 경과년수 | AD48: 임대료단가 | AE48: 관리비단가 | AF48: 임대료수입 | AG48: 관리비수입 | AH48: 연 운영수입
C49: 제2종수익증권 | E49: 46500 | F49: =acq -> 45688 | G49: N/A | H49: =1-H48 -> 0.9 | I49: 타이거로켓(395억), KT에스테이트(70억) | M49: =E49/E50 -> 0.4744898 | O49: =E49/E56 -> 0.17987436 | U49: =Rentroll!$C37 -> 17 | V49: =VLOOKUP($U49,Rentroll!$C$37:$AC$60,6,FALSE) -> 418.98972 | W49: =VLOOKUP($U49,Rentroll!$C$37:$AC$60,9,FALSE) -> 47149 | X49: =VLOOKUP($U49,Rentroll!$C$37:$AC$60,13,FALSE) -> 115927.41 | Y49: =VLOOKUP($U49,Rentroll!$C$37:$AC$60,15,FALSE) -> 50647.896 | Z49: =VLOOKUP($U49,Rentroll!$C$37:$AC$60,19,FALSE) -> 0.03 | AA49: =VLOOKUP($U49,Rentroll!$C$37:$AC$60,20,FALSE) -> 0.03 | AB49: =VLOOKUP($U49,Rentroll!$C$37:$AC$60,18,FALSE) -> 1 | AC49: =IFERROR(DATEDIF($W49,$X$45,"y"),0) -> 1 | AD49: =$X49*(1+$Z49)^$AC49 -> 119405.23 | AE49: =$Y49*(1+$AA49)^$AC49 -> 52167.333 | AF49: =$V49*$AD49*(12-$AB49)/unit -> 550.32521 | AG49: =$V49*$AE49*(12-$AB49)/unit -> 240.43334 | AH49: =SUM(AF49:AG49) -> 790.75855
C50: 소계 | E50: =SUM(E48:E49) -> 98000 | O50: =E50/E56 -> 0.37909005 | U50: =Rentroll!$C38 -> 16 | V50: =VLOOKUP($U50,Rentroll!$C$37:$AC$60,6,FALSE) -> 418.98972 | W50: =VLOOKUP($U50,Rentroll!$C$37:$AC$60,9,FALSE) -> 47149 | X50: =VLOOKUP($U50,Rentroll!$C$37:$AC$60,13,FALSE) -> 115927.41 | Y50: =VLOOKUP($U50,Rentroll!$C$37:$AC$60,15,FALSE) -> 50647.896 | Z50: =VLOOKUP($U50,Rentroll!$C$37:$AC$60,19,FALSE) -> 0.03 | AA50: =VLOOKUP($U50,Rentroll!$C$37:$AC$60,20,FALSE) -> 0.03 | AB50: =VLOOKUP($U50,Rentroll!$C$37:$AC$60,18,FALSE) -> 1 | AC50: =IFERROR(DATEDIF($W50,$X$45,"y"),0) -> 1 | AD50: =$X50*(1+$Z50)^$AC50 -> 119405.23 | AE50: =$Y50*(1+$AA50)^$AC50 -> 52167.333 | AF50: =$V50*$AD50*(12-$AB50)/unit -> 550.32521 | AG50: =$V50*$AE50*(12-$AB50)/unit -> 240.43334 | AH50: =SUM(AF50:AG50) -> 790.75855
B51: 타인자본 | E51: 합계 | F51: 인출일 | G51: 상환일 | H51: 대출기간 | I51: 연 이자율 | J51: 대출취급수수료 | K51: 이자지급 | L51: All-in이자율 | M51: LTV | N51: 비고 | U51: =Rentroll!$C39 -> 15 | V51: =VLOOKUP($U51,Rentroll!$C$37:$AC$60,6,FALSE) -> 418.98972 | W51: =VLOOKUP($U51,Rentroll!$C$37:$AC$60,9,FALSE) -> 45869 | X51: =VLOOKUP($U51,Rentroll!$C$37:$AC$60,13,FALSE) -> 103000 | Y51: =VLOOKUP($U51,Rentroll!$C$37:$AC$60,15,FALSE) -> 45000 | Z51: =VLOOKUP($U51,Rentroll!$C$37:$AC$60,19,FALSE) -> 0.03 | AA51: =VLOOKUP($U51,Rentroll!$C$37:$AC$60,20,FALSE) -> 0.03 | AB51: =VLOOKUP($U51,Rentroll!$C$37:$AC$60,18,FALSE) -> 1 | AC51: =IFERROR(DATEDIF($W51,$X$45,"y"),0) -> 4 | AD51: =$X51*(1+$Z51)^$AC51 -> 115927.41 | AE51: =$Y51*(1+$AA51)^$AC51 -> 50647.896 | AF51: =$V51*$AD51*(12-$AB51)/unit -> 534.29632 | AG51: =$V51*$AE51*(12-$AB51)/unit -> 233.43043 | AH51: =SUM(AF51:AG51) -> 767.72675
C52: Tr.A 담보대출 | E52: =E45-E50-E54-E53 -> 145594.83 | F52: =acq -> 45688 | G52: =EOMONTH(F52,H52) -> 46783 | H52: 36 | I52: 0.045 | J52: 0.004 | K52: 6 | L52: =I52+J52/(H52/12) -> 0.046333333 | M52: =(E52+E54)/$E$27 -> 0.63777023 | N52: 찰리화재 | O52: =E52/E56 -> 0.56319953 | U52: =Rentroll!$C40 -> 14 | V52: =VLOOKUP($U52,Rentroll!$C$37:$AC$60,6,FALSE) -> 418.98972 | W52: =VLOOKUP($U52,Rentroll!$C$37:$AC$60,9,FALSE) -> 45869 | X52: =VLOOKUP($U52,Rentroll!$C$37:$AC$60,13,FALSE) -> 103000 | Y52: =VLOOKUP($U52,Rentroll!$C$37:$AC$60,15,FALSE) -> 45000 | Z52: =VLOOKUP($U52,Rentroll!$C$37:$AC$60,19,FALSE) -> 0.03 | AA52: =VLOOKUP($U52,Rentroll!$C$37:$AC$60,20,FALSE) -> 0.03 | AB52: =VLOOKUP($U52,Rentroll!$C$37:$AC$60,18,FALSE) -> 1 | AC52: =IFERROR(DATEDIF($W52,$X$45,"y"),0) -> 4 | AD52: =$X52*(1+$Z52)^$AC52 -> 115927.41 | AE52: =$Y52*(1+$AA52)^$AC52 -> 50647.896 | AF52: =$V52*$AD52*(12-$AB52)/unit -> 534.29632 | AG52: =$V52*$AE52*(12-$AB52)/unit -> 233.43043 | AH52: =SUM(AF52:AG52) -> 767.72675
C53: Tr.B 담보대출 | E53: 10000 | F53: =acq -> 45688 | G53: =EOMONTH(F53,H53) -> 46418 | H53: 24 | I53: 0.0643 | J53: 0 | K53: 6 | L53: =IFERROR((I53+J53/(H53/12)), " ") -> 0.0643 | M53: =IF(E53=0,0,(E52+E54+E53)/$E$27) -> 0.68014311 | N53: 브라보은행 | O53: =E53/E56 -> 0.038682658 | U53: =Rentroll!$C41 -> 13 | V53: =VLOOKUP($U53,Rentroll!$C$37:$AC$60,6,FALSE) -> 418.98972 | W53: =VLOOKUP($U53,Rentroll!$C$37:$AC$60,9,FALSE) -> 45869 | X53: =VLOOKUP($U53,Rentroll!$C$37:$AC$60,13,FALSE) -> 103000 | Y53: =VLOOKUP($U53,Rentroll!$C$37:$AC$60,15,FALSE) -> 45000 | Z53: =VLOOKUP($U53,Rentroll!$C$37:$AC$60,19,FALSE) -> 0.03 | AA53: =VLOOKUP($U53,Rentroll!$C$37:$AC$60,20,FALSE) -> 0.03 | AB53: =VLOOKUP($U53,Rentroll!$C$37:$AC$60,18,FALSE) -> 1 | AC53: =IFERROR(DATEDIF($W53,$X$45,"y"),0) -> 4 | AD53: =$X53*(1+$Z53)^$AC53 -> 115927.41 | AE53: =$Y53*(1+$AA53)^$AC53 -> 50647.896 | AF53: =$V53*$AD53*(12-$AB53)/unit -> 534.29632 | AG53: =$V53*$AE53*(12-$AB53)/unit -> 233.43043 | AH53: =SUM(AF53:AG53) -> 767.72675
C54: 보증금 | E54: =Rentroll!Y32 -> 4918.9383 | F54: =acq -> 45688 | G54: =exit -> 47514 | H54: N/A | I54: N/A | J54: N/A | K54: N/A | O54: =E54/E56 -> 0.019027761 | U54: =Rentroll!$C42 -> 12 | V54: =VLOOKUP($U54,Rentroll!$C$37:$AC$60,6,FALSE) -> 418.98972 | W54: =VLOOKUP($U54,Rentroll!$C$37:$AC$60,9,FALSE) -> 45869 | X54: =VLOOKUP($U54,Rentroll!$C$37:$AC$60,13,FALSE) -> 103000 | Y54: =VLOOKUP($U54,Rentroll!$C$37:$AC$60,15,FALSE) -> 45000 | Z54: =VLOOKUP($U54,Rentroll!$C$37:$AC$60,19,FALSE) -> 0.03 | AA54: =VLOOKUP($U54,Rentroll!$C$37:$AC$60,20,FALSE) -> 0.03 | AB54: =VLOOKUP($U54,Rentroll!$C$37:$AC$60,18,FALSE) -> 1 | AC54: =IFERROR(DATEDIF($W54,$X$45,"y"),0) -> 4 | AD54: =$X54*(1+$Z54)^$AC54 -> 115927.41 | AE54: =$Y54*(1+$AA54)^$AC54 -> 50647.896 | AF54: =$V54*$AD54*(12-$AB54)/unit -> 534.29632 | AG54: =$V54*$AE54*(12-$AB54)/unit -> 233.43043 | AH54: =SUM(AF54:AG54) -> 767.72675
C55: 소계 | E55: =SUM(E52:E54) -> 160513.77 | O55: =E55/E56 -> 0.62090995 | U55: =Rentroll!$C43 -> 11 | V55: =VLOOKUP($U55,Rentroll!$C$37:$AC$60,6,FALSE) -> 418.98972 | W55: =VLOOKUP($U55,Rentroll!$C$37:$AC$60,9,FALSE) -> 46904 | X55: =VLOOKUP($U55,Rentroll!$C$37:$AC$60,13,FALSE) -> 112550.88 | Y55: =VLOOKUP($U55,Rentroll!$C$37:$AC$60,15,FALSE) -> 49172.715 | Z55: =VLOOKUP($U55,Rentroll!$C$37:$AC$60,19,FALSE) -> 0.03 | AA55: =VLOOKUP($U55,Rentroll!$C$37:$AC$60,20,FALSE) -> 0.03 | AB55: =VLOOKUP($U55,Rentroll!$C$37:$AC$60,18,FALSE) -> 1 | AC55: =IFERROR(DATEDIF($W55,$X$45,"y"),0) -> 1 | AD55: =$X55*(1+$Z55)^$AC55 -> 115927.41 | AE55: =$Y55*(1+$AA55)^$AC55 -> 50647.896 | AF55: =$V55*$AD55*(12-$AB55)/unit -> 534.29632 | AG55: =$V55*$AE55*(12-$AB55)/unit -> 233.43043 | AH55: =SUM(AF55:AG55) -> 767.72675
B56: 합계 | E56: =E50+E55 -> 258513.77 | U56: =Rentroll!$C44 -> 10 | V56: =VLOOKUP($U56,Rentroll!$C$37:$AC$60,6,FALSE) -> 418.98972 | W56: =VLOOKUP($U56,Rentroll!$C$37:$AC$60,9,FALSE) -> 46904 | X56: =VLOOKUP($U56,Rentroll!$C$37:$AC$60,13,FALSE) -> 112550.88 | Y56: =VLOOKUP($U56,Rentroll!$C$37:$AC$60,15,FALSE) -> 49172.715 | Z56: =VLOOKUP($U56,Rentroll!$C$37:$AC$60,19,FALSE) -> 0.03 | AA56: =VLOOKUP($U56,Rentroll!$C$37:$AC$60,20,FALSE) -> 0.03 | AB56: =VLOOKUP($U56,Rentroll!$C$37:$AC$60,18,FALSE) -> 1 | AC56: =IFERROR(DATEDIF($W56,$X$45,"y"),0) -> 1 | AD56: =$X56*(1+$Z56)^$AC56 -> 115927.41 | AE56: =$Y56*(1+$AA56)^$AC56 -> 50647.896 | AF56: =$V56*$AD56*(12-$AB56)/unit -> 534.29632 | AG56: =$V56*$AE56*(12-$AB56)/unit -> 233.43043 | AH56: =SUM(AF56:AG56) -> 767.72675
B57: 운영기간 중 재원조달 | E57: 합계 | F57: 인출일 | G57: 상환일 | H57: 대출기간 | I57: 연 이자율 | J57: 대출취급수수료 | K57: 이자지급 | L57: All-in이자율 | M57: LTV | N57: 비고 | U57: =Rentroll!$C45 -> 9 | V57: =VLOOKUP($U57,Rentroll!$C$37:$AC$60,6,FALSE) -> 418.98972 | W57: =VLOOKUP($U57,Rentroll!$C$37:$AC$60,9,FALSE) -> 46904 | X57: =VLOOKUP($U57,Rentroll!$C$37:$AC$60,13,FALSE) -> 112550.88 | Y57: =VLOOKUP($U57,Rentroll!$C$37:$AC$60,15,FALSE) -> 49172.715 | Z57: =VLOOKUP($U57,Rentroll!$C$37:$AC$60,19,FALSE) -> 0.03 | AA57: =VLOOKUP($U57,Rentroll!$C$37:$AC$60,20,FALSE) -> 0.03 | AB57: =VLOOKUP($U57,Rentroll!$C$37:$AC$60,18,FALSE) -> 1 | AC57: =IFERROR(DATEDIF($W57,$X$45,"y"),0) -> 1 | AD57: =$X57*(1+$Z57)^$AC57 -> 115927.41 | AE57: =$Y57*(1+$AA57)^$AC57 -> 50647.896 | AF57: =$V57*$AD57*(12-$AB57)/unit -> 534.29632 | AG57: =$V57*$AE57*(12-$AB57)/unit -> 233.43043 | AH57: =SUM(AF57:AG57) -> 767.72675
C58: Tr.A 리파이낸싱 | E58: =IF(H58=0,0,E52) -> 145594.83 | F58: =G52 -> 46783 | G58: =exit -> 47514 | H58: =DATEDIF(F58,G58,"m") -> 24 | I58: =AG111 -> 0.0418 | J58: 0.004 | K58: 6 | L58: =IFERROR(I58+J58/(H58/12)," ") -> 0.0438 | M58: =IF(E58=0,0,(E58+R64)/R65) -> 0.55527506 | N58: 찰리화재 | U58: =Rentroll!$C46 -> 8 | V58: =VLOOKUP($U58,Rentroll!$C$37:$AC$60,6,FALSE) -> 418.98972 | W58: =VLOOKUP($U58,Rentroll!$C$37:$AC$60,9,FALSE) -> 46477 | X58: =VLOOKUP($U58,Rentroll!$C$37:$AC$60,13,FALSE) -> 109272.7 | Y58: =VLOOKUP($U58,Rentroll!$C$37:$AC$60,15,FALSE) -> 47740.5 | Z58: =VLOOKUP($U58,Rentroll!$C$37:$AC$60,19,FALSE) -> 0.03 | AA58: =VLOOKUP($U58,Rentroll!$C$37:$AC$60,20,FALSE) -> 0.03 | AB58: =VLOOKUP($U58,Rentroll!$C$37:$AC$60,18,FALSE) -> 1 | AC58: =IFERROR(DATEDIF($W58,$X$45,"y"),0) -> 2 | AD58: =$X58*(1+$Z58)^$AC58 -> 115927.41 | AE58: =$Y58*(1+$AA58)^$AC58 -> 50647.896 | AF58: =$V58*$AD58*(12-$AB58)/unit -> 534.29632 | AG58: =$V58*$AE58*(12-$AB58)/unit -> 233.43043 | AH58: =SUM(AF58:AG58) -> 767.72675
C59: Tr.B 리파이낸싱 | E59: =IF(H59=0,0,E53) -> 10000 | F59: =G53 -> 46418 | G59: =exit -> 47514 | H59: =IF(H53=0,0,DATEDIF(F59,G59,"m")) -> 36 | I59: =AG111+1.87% -> 0.0605 | J59: 0.004 | K59: 6 | L59: =IFERROR(I59+J59/(H59/12)," ") -> 0.061833333 | M59: =IF(E59=0,0,(E59+R64+E52)/R65) -> 0.59149726 | N59: 찰리화재 | U59: =Rentroll!$C47 -> 7 | V59: =VLOOKUP($U59,Rentroll!$C$37:$AC$60,6,FALSE) -> 418.98972 | W59: =VLOOKUP($U59,Rentroll!$C$37:$AC$60,9,FALSE) -> 46477 | X59: =VLOOKUP($U59,Rentroll!$C$37:$AC$60,13,FALSE) -> 109272.7 | Y59: =VLOOKUP($U59,Rentroll!$C$37:$AC$60,15,FALSE) -> 47740.5 | Z59: =VLOOKUP($U59,Rentroll!$C$37:$AC$60,19,FALSE) -> 0.03 | AA59: =VLOOKUP($U59,Rentroll!$C$37:$AC$60,20,FALSE) -> 0.03 | AB59: =VLOOKUP($U59,Rentroll!$C$37:$AC$60,18,FALSE) -> 1 | AC59: =IFERROR(DATEDIF($W59,$X$45,"y"),0) -> 2 | AD59: =$X59*(1+$Z59)^$AC59 -> 115927.41 | AE59: =$Y59*(1+$AA59)^$AC59 -> 50647.896 | AF59: =$V59*$AD59*(12-$AB59)/unit -> 534.29632 | AG59: =$V59*$AE59*(12-$AB59)/unit -> 233.43043 | AH59: =SUM(AF59:AG59) -> 767.72675
C60: 한도대출 | I60: 0 | N60: 없음 | U60: =Rentroll!$C48 -> 6 | V60: =VLOOKUP($U60,Rentroll!$C$37:$AC$60,6,FALSE) -> 418.98972 | W60: =VLOOKUP($U60,Rentroll!$C$37:$AC$60,9,FALSE) -> 46477 | X60: =VLOOKUP($U60,Rentroll!$C$37:$AC$60,13,FALSE) -> 109272.7 | Y60: =VLOOKUP($U60,Rentroll!$C$37:$AC$60,15,FALSE) -> 47740.5 | Z60: =VLOOKUP($U60,Rentroll!$C$37:$AC$60,19,FALSE) -> 0.03 | AA60: =VLOOKUP($U60,Rentroll!$C$37:$AC$60,20,FALSE) -> 0.03 | AB60: =VLOOKUP($U60,Rentroll!$C$37:$AC$60,18,FALSE) -> 1 | AC60: =IFERROR(DATEDIF($W60,$X$45,"y"),0) -> 2 | AD60: =$X60*(1+$Z60)^$AC60 -> 115927.41 | AE60: =$Y60*(1+$AA60)^$AC60 -> 50647.896 | AF60: =$V60*$AD60*(12-$AB60)/unit -> 534.29632 | AG60: =$V60*$AE60*(12-$AB60)/unit -> 233.43043 | AH60: =SUM(AF60:AG60) -> 767.72675
N61: 리파이낸싱 LTV 산정 | U61: =Rentroll!$C49 -> 5 | V61: =VLOOKUP($U61,Rentroll!$C$37:$AC$60,6,FALSE) -> 418.98972 | W61: =VLOOKUP($U61,Rentroll!$C$37:$AC$60,9,FALSE) -> 45688 | X61: =VLOOKUP($U61,Rentroll!$C$37:$AC$60,13,FALSE) -> 103000 | Y61: =VLOOKUP($U61,Rentroll!$C$37:$AC$60,15,FALSE) -> 45000 | Z61: =VLOOKUP($U61,Rentroll!$C$37:$AC$60,19,FALSE) -> 0.03 | AA61: =VLOOKUP($U61,Rentroll!$C$37:$AC$60,20,FALSE) -> 0.03 | AB61: =VLOOKUP($U61,Rentroll!$C$37:$AC$60,18,FALSE) -> 1.5 | AC61: =IFERROR(DATEDIF($W61,$X$45,"y"),0) -> 5 | AD61: =$X61*(1+$Z61)^$AC61 -> 119405.23 | AE61: =$Y61*(1+$AA61)^$AC61 -> 52167.333 | AF61: =$V61*$AD61*(12-$AB61)/unit -> 525.31043 | AG61: =$V61*$AE61*(12-$AB61)/unit -> 229.50455 | AH61: =SUM(AF61:AG61) -> 754.81498
N62: 1) 인출일 기준 NOI 산정 | P62: 2 | Q62: NOI = | R62: =HLOOKUP(P62,U27:AH42,16,FALSE) -> 12613.47 | S62: 백만원 | U62: =Rentroll!$C50 -> 4 | V62: =VLOOKUP($U62,Rentroll!$C$37:$AC$60,6,FALSE) -> 418.98972 | W62: =VLOOKUP($U62,Rentroll!$C$37:$AC$60,9,FALSE) -> 45688 | X62: =VLOOKUP($U62,Rentroll!$C$37:$AC$60,13,FALSE) -> 103000 | Y62: =VLOOKUP($U62,Rentroll!$C$37:$AC$60,15,FALSE) -> 45000 | Z62: =VLOOKUP($U62,Rentroll!$C$37:$AC$60,19,FALSE) -> 0.03 | AA62: =VLOOKUP($U62,Rentroll!$C$37:$AC$60,20,FALSE) -> 0.03 | AB62: =VLOOKUP($U62,Rentroll!$C$37:$AC$60,18,FALSE) -> 1.5 | AC62: =IFERROR(DATEDIF($W62,$X$45,"y"),0) -> 5 | AD62: =$X62*(1+$Z62)^$AC62 -> 119405.23 | AE62: =$Y62*(1+$AA62)^$AC62 -> 52167.333 | AF62: =$V62*$AD62*(12-$AB62)/unit -> 525.31043 | AG62: =$V62*$AE62*(12-$AB62)/unit -> 229.50455 | AH62: =SUM(AF62:AG62) -> 754.81498
N63: 2) 인출일 기준 Cap rate 가정 | R63: 0.047 | U63: =Rentroll!$C51 -> 3 | V63: =VLOOKUP($U63,Rentroll!$C$37:$AC$60,6,FALSE) -> 418.98972 | W63: =VLOOKUP($U63,Rentroll!$C$37:$AC$60,9,FALSE) -> 45688 | X63: =VLOOKUP($U63,Rentroll!$C$37:$AC$60,13,FALSE) -> 103000 | Y63: =VLOOKUP($U63,Rentroll!$C$37:$AC$60,15,FALSE) -> 45000 | Z63: =VLOOKUP($U63,Rentroll!$C$37:$AC$60,19,FALSE) -> 0.03 | AA63: =VLOOKUP($U63,Rentroll!$C$37:$AC$60,20,FALSE) -> 0.03 | AB63: =VLOOKUP($U63,Rentroll!$C$37:$AC$60,18,FALSE) -> 1.5 | AC63: =IFERROR(DATEDIF($W63,$X$45,"y"),0) -> 5 | AD63: =$X63*(1+$Z63)^$AC63 -> 119405.23 | AE63: =$Y63*(1+$AA63)^$AC63 -> 52167.333 | AF63: =$V63*$AD63*(12-$AB63)/unit -> 525.31043 | AG63: =$V63*$AE63*(12-$AB63)/unit -> 229.50455 | AH63: =SUM(AF63:AG63) -> 754.81498
N64: 3) 인출일 기준 임차보증금 | R64: =HLOOKUP($F$58,운영수입!$S$14:$DM$157,99,FALSE) -> 7702.0181 | U64: =Rentroll!$C52 -> 201호 | V64: =VLOOKUP($U64,Rentroll!$C$37:$AC$60,6,FALSE) -> 104.74743 | W64: =VLOOKUP($U64,Rentroll!$C$37:$AC$60,9,FALSE) -> 45747 | X64: =VLOOKUP($U64,Rentroll!$C$37:$AC$60,13,FALSE) -> 130000 | Y64: =VLOOKUP($U64,Rentroll!$C$37:$AC$60,15,FALSE) -> 45000 | Z64: =VLOOKUP($U64,Rentroll!$C$37:$AC$60,19,FALSE) -> 0.03 | AA64: =VLOOKUP($U64,Rentroll!$C$37:$AC$60,20,FALSE) -> 0.03 | AB64: =VLOOKUP($U64,Rentroll!$C$37:$AC$60,18,FALSE) -> 0 | AC64: =IFERROR(DATEDIF($W64,$X$45,"y"),0) -> 4 | AD64: =$X64*(1+$Z64)^$AC64 -> 146316.15 | AE64: =$Y64*(1+$AA64)^$AC64 -> 50647.896 | AF64: =$V64*$AD64*(12-$AB64)/unit -> 183.91488 | AG64: =$V64*$AE64*(12-$AB64)/unit -> 63.662845 | AH64: =SUM(AF64:AG64) -> 247.57773
N65: 4) 인출일 기준 자산가치 산정 | R65: =R62/R63+R64 -> 276073.73 | S65: 백만원 | U65: =Rentroll!$C53 -> 202호 | V65: =VLOOKUP($U65,Rentroll!$C$37:$AC$60,6,FALSE) -> 104.74743 | W65: =VLOOKUP($U65,Rentroll!$C$37:$AC$60,9,FALSE) -> 45747 | X65: =VLOOKUP($U65,Rentroll!$C$37:$AC$60,13,FALSE) -> 130000 | Y65: =VLOOKUP($U65,Rentroll!$C$37:$AC$60,15,FALSE) -> 45000 | Z65: =VLOOKUP($U65,Rentroll!$C$37:$AC$60,19,FALSE) -> 0.03 | AA65: =VLOOKUP($U65,Rentroll!$C$37:$AC$60,20,FALSE) -> 0.03 | AB65: =VLOOKUP($U65,Rentroll!$C$37:$AC$60,18,FALSE) -> 0 | AC65: =IFERROR(DATEDIF($W65,$X$45,"y"),0) -> 4 | AD65: =$X65*(1+$Z65)^$AC65 -> 146316.15 | AE65: =$Y65*(1+$AA65)^$AC65 -> 50647.896 | AF65: =$V65*$AD65*(12-$AB65)/unit -> 183.91488 | AG65: =$V65*$AE65*(12-$AB65)/unit -> 63.662845 | AH65: =SUM(AF65:AG65) -> 247.57773
U66: =Rentroll!$C54 -> 203호 | V66: =VLOOKUP($U66,Rentroll!$C$37:$AC$60,6,FALSE) -> 104.74743 | W66: =VLOOKUP($U66,Rentroll!$C$37:$AC$60,9,FALSE) -> 45747 | X66: =VLOOKUP($U66,Rentroll!$C$37:$AC$60,13,FALSE) -> 130000 | Y66: =VLOOKUP($U66,Rentroll!$C$37:$AC$60,15,FALSE) -> 45000 | Z66: =VLOOKUP($U66,Rentroll!$C$37:$AC$60,19,FALSE) -> 0.03 | AA66: =VLOOKUP($U66,Rentroll!$C$37:$AC$60,20,FALSE) -> 0.03 | AB66: =VLOOKUP($U66,Rentroll!$C$37:$AC$60,18,FALSE) -> 0 | AC66: =IFERROR(DATEDIF($W66,$X$45,"y"),0) -> 4 | AD66: =$X66*(1+$Z66)^$AC66 -> 146316.15 | AE66: =$Y66*(1+$AA66)^$AC66 -> 50647.896 | AF66: =$V66*$AD66*(12-$AB66)/unit -> 183.91488 | AG66: =$V66*$AE66*(12-$AB66)/unit -> 63.662845 | AH66: =SUM(AF66:AG66) -> 247.57773
B67: 사업기간별 현금흐름 | U67: =Rentroll!$C55 -> 204호 | V67: =VLOOKUP($U67,Rentroll!$C$37:$AC$60,6,FALSE) -> 104.74743 | W67: =VLOOKUP($U67,Rentroll!$C$37:$AC$60,9,FALSE) -> 45747 | X67: =VLOOKUP($U67,Rentroll!$C$37:$AC$60,13,FALSE) -> 130000 | Y67: =VLOOKUP($U67,Rentroll!$C$37:$AC$60,15,FALSE) -> 45000 | Z67: =VLOOKUP($U67,Rentroll!$C$37:$AC$60,19,FALSE) -> 0.03 | AA67: =VLOOKUP($U67,Rentroll!$C$37:$AC$60,20,FALSE) -> 0.03 | AB67: =VLOOKUP($U67,Rentroll!$C$37:$AC$60,18,FALSE) -> 0 | AC67: =IFERROR(DATEDIF($W67,$X$45,"y"),0) -> 4 | AD67: =$X67*(1+$Z67)^$AC67 -> 146316.15 | AE67: =$Y67*(1+$AA67)^$AC67 -> 50647.896 | AF67: =$V67*$AD67*(12-$AB67)/unit -> 183.91488 | AG67: =$V67*$AE67*(12-$AB67)/unit -> 63.662845 | AH67: =SUM(AF67:AG67) -> 247.57773
D68: 사업연도(회계기간) | F68: =운영수입!T8 -> 1 | G68: =운영수입!U8 -> 2 | H68: =운영수입!V8 -> 3 | I68: =운영수입!W8 -> 4 | J68: =운영수입!X8 -> 5 | K68: =운영수입!Y8 -> 6 | L68: =운영수입!Z8 -> 7 | M68: =운영수입!AA8 -> 8 | ... S68: =운영수입!AG8 -> 14 | U68: =Rentroll!$C56 -> 101호 | V68: =VLOOKUP($U68,Rentroll!$C$37:$AC$60,6,FALSE) -> 146.64595 | W68: =VLOOKUP($U68,Rentroll!$C$37:$AC$60,9,FALSE) -> 45838 | X68: =VLOOKUP($U68,Rentroll!$C$37:$AC$60,13,FALSE) -> 150000 | Y68: =VLOOKUP($U68,Rentroll!$C$37:$AC$60,15,FALSE) -> 45000 | Z68: =VLOOKUP($U68,Rentroll!$C$37:$AC$60,19,FALSE) -> 0.03 | AA68: =VLOOKUP($U68,Rentroll!$C$37:$AC$60,20,FALSE) -> 0.03 | AB68: =VLOOKUP($U68,Rentroll!$C$37:$AC$60,18,FALSE) -> 0 | AC68: =IFERROR(DATEDIF($W68,$X$45,"y"),0) -> 4 | AD68: =$X68*(1+$Z68)^$AC68 -> 168826.32 | AE68: =$Y68*(1+$AA68)^$AC68 -> 50647.896 | AF68: =$V68*$AD68*(12-$AB68)/unit -> 297.09236 | AG68: =$V68*$AE68*(12-$AB68)/unit -> 89.127707 | AH68: =SUM(AF68:AG68) -> 386.22006
D69: 시작월 | F69: =운영수입!T9 -> 45716 | G69: =운영수입!U9 -> 45900 | H69: =운영수입!V9 -> 46081 | I69: =운영수입!W9 -> 46265 | J69: =운영수입!X9 -> 46446 | K69: =운영수입!Y9 -> 46630 | L69: =운영수입!Z9 -> 46812 | M69: =운영수입!AA9 -> 46996 | ... S69: =운영수입!AG9 -> 48091 | U69: =Rentroll!$C57 -> 102호 | V69: =VLOOKUP($U69,Rentroll!$C$37:$AC$60,6,FALSE) -> 146.64595 | W69: =VLOOKUP($U69,Rentroll!$C$37:$AC$60,9,FALSE) -> 45838 | X69: =VLOOKUP($U69,Rentroll!$C$37:$AC$60,13,FALSE) -> 150000 | Y69: =VLOOKUP($U69,Rentroll!$C$37:$AC$60,15,FALSE) -> 45000 | Z69: =VLOOKUP($U69,Rentroll!$C$37:$AC$60,19,FALSE) -> 0.03 | AA69: =VLOOKUP($U69,Rentroll!$C$37:$AC$60,20,FALSE) -> 0.03 | AB69: =VLOOKUP($U69,Rentroll!$C$37:$AC$60,18,FALSE) -> 0 | AC69: =IFERROR(DATEDIF($W69,$X$45,"y"),0) -> 4 | AD69: =$X69*(1+$Z69)^$AC69 -> 168826.32 | AE69: =$Y69*(1+$AA69)^$AC69 -> 50647.896 | AF69: =$V69*$AD69*(12-$AB69)/unit -> 297.09236 | AG69: =$V69*$AE69*(12-$AB69)/unit -> 89.127707 | AH69: =SUM(AF69:AG69) -> 386.22006
D70: 종료월 | E70: =acq -> 45688 | F70: =운영수입!T10 -> 45869 | G70: =운영수입!U10 -> 46053 | H70: =운영수입!V10 -> 46234 | I70: =운영수입!W10 -> 46418 | J70: =운영수입!X10 -> 46599 | K70: =운영수입!Y10 -> 46783 | L70: =운영수입!Z10 -> 46965 | M70: =운영수입!AA10 -> 47149 | ... S70: =운영수입!AG10 -> 48244 | U70: =Rentroll!$C58 -> B101호 | V70: =VLOOKUP($U70,Rentroll!$C$37:$AC$60,6,FALSE) -> 293.2919 | W70: =VLOOKUP($U70,Rentroll!$C$37:$AC$60,9,FALSE) -> 46752 | X70: =VLOOKUP($U70,Rentroll!$C$37:$AC$60,13,FALSE) -> 52116.712 | Y70: =VLOOKUP($U70,Rentroll!$C$37:$AC$60,15,FALSE) -> 40000 | Z70: =VLOOKUP($U70,Rentroll!$C$37:$AC$60,19,FALSE) -> 0.03 | AA70: =VLOOKUP($U70,Rentroll!$C$37:$AC$60,20,FALSE) -> 0.03 | AB70: =VLOOKUP($U70,Rentroll!$C$37:$AC$60,18,FALSE) -> 0 | AC70: =IFERROR(DATEDIF($W70,$X$45,"y"),0) -> 2 | AD70: =$X70*(1+$Z70)^$AC70 -> 55290.62 | AE70: =$Y70*(1+$AA70)^$AC70 -> 42436 | AF70: =$V70*$AD70*(12-$AB70)/unit -> 194.59549 | AG70: =$V70*$AE70*(12-$AB70)/unit -> 149.35362 | AH70: =SUM(AF70:AG70) -> 343.94911
B71: =현금흐름!B17 -> 영업현금흐름 | U71: =Rentroll!$C59 -> B102호 | V71: =VLOOKUP($U71,Rentroll!$C$37:$AC$60,6,FALSE) -> 293.2919 | W71: =VLOOKUP($U71,Rentroll!$C$37:$AC$60,9,FALSE) -> 46418 | X71: =VLOOKUP($U71,Rentroll!$C$37:$AC$60,13,FALSE) -> 52116.712 | Y71: =VLOOKUP($U71,Rentroll!$C$37:$AC$60,15,FALSE) -> 40000 | Z71: =VLOOKUP($U71,Rentroll!$C$37:$AC$60,19,FALSE) -> 0.03 | AA71: =VLOOKUP($U71,Rentroll!$C$37:$AC$60,20,FALSE) -> 0.03 | AB71: =VLOOKUP($U71,Rentroll!$C$37:$AC$60,18,FALSE) -> 0 | AC71: =IFERROR(DATEDIF($W71,$X$45,"y"),0) -> 3 | AD71: =$X71*(1+$Z71)^$AC71 -> 56949.339 | AE71: =$Y71*(1+$AA71)^$AC71 -> 43709.08 | AF71: =$V71*$AD71*(12-$AB71)/unit -> 200.43336 | AG71: =$V71*$AE71*(12-$AB71)/unit -> 153.83423 | AH71: =SUM(AF71:AG71) -> 354.26759
B72: =현금흐름!C18 -> 운영수입 | E72: =SUMIF(현금흐름!$15:$15,'A&R'!E$68,현금흐름!18:18) -> 0 | F72: =SUMIF(현금흐름!$15:$15,'A&R'!F$68,현금흐름!18:18) -> 6610.9098 | G72: =SUMIF(현금흐름!$15:$15,'A&R'!G$68,현금흐름!18:18) -> 7642.1722 | H72: =SUMIF(현금흐름!$15:$15,'A&R'!H$68,현금흐름!18:18) -> 7933.4512 | I72: =SUMIF(현금흐름!$15:$15,'A&R'!I$68,현금흐름!18:18) -> 8025.5678 | J72: =SUMIF(현금흐름!$15:$15,'A&R'!J$68,현금흐름!18:18) -> 8108.9813 | K72: =SUMIF(현금흐름!$15:$15,'A&R'!K$68,현금흐름!18:18) -> 8355.7103 | L72: =SUMIF(현금흐름!$15:$15,'A&R'!L$68,현금흐름!18:18) -> 8579.1058 | ... S72: =SUMIF(현금흐름!$15:$15,'A&R'!S$68,현금흐름!18:18) -> 0
B73: =현금흐름!C19 -> 운영비용 | E73: =SUMIF(현금흐름!$15:$15,'A&R'!E$68,현금흐름!19:19) -> 0 | F73: =SUMIF(현금흐름!$15:$15,'A&R'!F$68,현금흐름!19:19) -> -1624.2816 | G73: =SUMIF(현금흐름!$15:$15,'A&R'!G$68,현금흐름!19:19) -> -2155.3887 | H73: =SUMIF(현금흐름!$15:$15,'A&R'!H$68,현금흐름!19:19) -> -1656.7247 | I73: =SUMIF(현금흐름!$15:$15,'A&R'!I$68,현금흐름!19:19) -> -1688.8241 | J73: =SUMIF(현금흐름!$15:$15,'A&R'!J$68,현금흐름!19:19) -> -1962.5462 | K73: =SUMIF(현금흐름!$15:$15,'A&R'!K$68,현금흐름!19:19) -> -1730.2422 | L73: =SUMIF(현금흐름!$15:$15,'A&R'!L$68,현금흐름!19:19) -> -1831.3749 | ... S73: =SUMIF(현금흐름!$15:$15,'A&R'!S$68,현금흐름!19:19) -> 0 | U73: 합계 | V73: =SUM(V49:V72) -> 7583.7113 | AH73: =SUM(AH49:AH72) -> 13984.197
B74: =현금흐름!C20 -> 펀드비용 | E74: =SUMIF(현금흐름!$15:$15,'A&R'!E$68,현금흐름!20:20) -> 0 | F74: =SUMIF(현금흐름!$15:$15,'A&R'!F$68,현금흐름!20:20) -> -285 | G74: =SUMIF(현금흐름!$15:$15,'A&R'!G$68,현금흐름!20:20) -> -285 | H74: =SUMIF(현금흐름!$15:$15,'A&R'!H$68,현금흐름!20:20) -> -285 | I74: =SUMIF(현금흐름!$15:$15,'A&R'!I$68,현금흐름!20:20) -> -285 | J74: =SUMIF(현금흐름!$15:$15,'A&R'!J$68,현금흐름!20:20) -> -285 | K74: =SUMIF(현금흐름!$15:$15,'A&R'!K$68,현금흐름!20:20) -> -285 | L74: =SUMIF(현금흐름!$15:$15,'A&R'!L$68,현금흐름!20:20) -> -285 | ... S74: =SUMIF(현금흐름!$15:$15,'A&R'!S$68,현금흐름!20:20) -> 0
B75: =현금흐름!C21 -> 이자비용 | E75: =SUMIF(현금흐름!$15:$15,'A&R'!E$68,현금흐름!21:21) -> 0 | F75: =SUMIF(현금흐름!$15:$15,'A&R'!F$68,현금흐름!21:21) -> -3624.1755 | G75: =SUMIF(현금흐름!$15:$15,'A&R'!G$68,현금흐름!21:21) -> -3597.3838 | H75: =SUMIF(현금흐름!$15:$15,'A&R'!H$68,현금흐름!21:21) -> -3597.3838 | I75: =SUMIF(현금흐름!$15:$15,'A&R'!I$68,현금흐름!21:21) -> -3570.5921 | J75: =SUMIF(현금흐름!$15:$15,'A&R'!J$68,현금흐름!21:21) -> -3603.5921 | K75: =SUMIF(현금흐름!$15:$15,'A&R'!K$68,현금흐름!21:21) -> -3578.3838 | L75: =SUMIF(현금흐름!$15:$15,'A&R'!L$68,현금흐름!21:21) -> -3345.432 | ... S75: =SUMIF(현금흐름!$15:$15,'A&R'!S$68,현금흐름!21:21) -> 0 | U75: 2-2) N+1년차 임대 외 수입
B76: =현금흐름!C22 -> 영업현금흐름 합계 | E76: =SUM(E72:E75) -> 0 | F76: =SUM(F72:F75) -> 1077.4528 | G76: =SUM(G72:G75) -> 1604.3997 | H76: =SUM(H72:H75) -> 2394.3427 | I76: =SUM(I72:I75) -> 2481.1516 | J76: =SUM(J72:J75) -> 2257.843 | K76: =SUM(K72:K75) -> 2762.0844 | L76: =SUM(L72:L75) -> 3117.2988 | ... S76: =SUM(S72:S75) -> 0 | U76: 구분 | V76: =Y45 -> 5 | W76: CAGR | X76: N+1년차
U77: =AC16 -> 주차수입 | V77: =SUMIF($Y$27:$AH$27,$V$76,$Y31:$AH31) -> 529.83019 | W77: =RATE($V$76-1,0,-$Y31,$V77) -> 0.025 | X77: =$V77*(1+$W77) -> 543.07594
B78: =현금흐름!B24 -> 투자현금흐름 | U78: =AC17 -> 기타수입 | V78: =SUMIF($Y$27:$AH$27,$V$76,$Y32:$AH32) -> 200.95108 | W78: =RATE($V$76-1,0,-$Y32,$V78) -> 0.025 | X78: =$V78*(1+$W78) -> 205.97486
B79: =현금흐름!C25 -> 자산취득 | E79: =SUMIF(현금흐름!$15:$15,'A&R'!E$68,현금흐름!25:25) -> -258513.77 | F79: =SUMIF(현금흐름!$15:$15,'A&R'!F$68,현금흐름!25:25) -> 0 | G79: =SUMIF(현금흐름!$15:$15,'A&R'!G$68,현금흐름!25:25) -> 0 | H79: =SUMIF(현금흐름!$15:$15,'A&R'!H$68,현금흐름!25:25) -> 0 | I79: =SUMIF(현금흐름!$15:$15,'A&R'!I$68,현금흐름!25:25) -> 0 | J79: =SUMIF(현금흐름!$15:$15,'A&R'!J$68,현금흐름!25:25) -> 0 | K79: =SUMIF(현금흐름!$15:$15,'A&R'!K$68,현금흐름!25:25) -> 0 | L79: =SUMIF(현금흐름!$15:$15,'A&R'!L$68,현금흐름!25:25) -> 0 | ... S79: =SUMIF(현금흐름!$15:$15,'A&R'!S$68,현금흐름!25:25) -> 0 | U79: =AC18 -> 전광판수입 | V79: =SUMIF($Y$27:$AH$27,$V$76,$Y33:$AH33) -> 3172.5198 | W79: =2.5% -> 0.025 | X79: =$V79*(1+$W79) -> 3251.8328
B80: =현금흐름!C26 -> 운영기간 Capex | E80: =SUMIF(현금흐름!$15:$15,'A&R'!E$68,현금흐름!26:26) -> 0 | F80: =SUMIF(현금흐름!$15:$15,'A&R'!F$68,현금흐름!26:26) -> 0 | G80: =SUMIF(현금흐름!$15:$15,'A&R'!G$68,현금흐름!26:26) -> 0 | H80: =SUMIF(현금흐름!$15:$15,'A&R'!H$68,현금흐름!26:26) -> 0 | I80: =SUMIF(현금흐름!$15:$15,'A&R'!I$68,현금흐름!26:26) -> 0 | J80: =SUMIF(현금흐름!$15:$15,'A&R'!J$68,현금흐름!26:26) -> 0 | K80: =SUMIF(현금흐름!$15:$15,'A&R'!K$68,현금흐름!26:26) -> 0 | L80: =SUMIF(현금흐름!$15:$15,'A&R'!L$68,현금흐름!26:26) -> 0 | ... S80: =SUMIF(현금흐름!$15:$15,'A&R'!S$68,현금흐름!26:26) -> 0 | U80: 합계 | V80: =SUM(V77:V79) -> 3903.301 | X80: =SUM(X77:X79) -> 4000.8836
B81: =현금흐름!C27 -> 자산매각 | E81: =SUMIF(현금흐름!$15:$15,'A&R'!E$68,현금흐름!27:27) -> 0 | F81: =SUMIF(현금흐름!$15:$15,'A&R'!F$68,현금흐름!27:27) -> 0 | G81: =SUMIF(현금흐름!$15:$15,'A&R'!G$68,현금흐름!27:27) -> 0 | H81: =SUMIF(현금흐름!$15:$15,'A&R'!H$68,현금흐름!27:27) -> 0 | I81: =SUMIF(현금흐름!$15:$15,'A&R'!I$68,현금흐름!27:27) -> 0 | J81: =SUMIF(현금흐름!$15:$15,'A&R'!J$68,현금흐름!27:27) -> 0 | K81: =SUMIF(현금흐름!$15:$15,'A&R'!K$68,현금흐름!27:27) -> 0 | L81: =SUMIF(현금흐름!$15:$15,'A&R'!L$68,현금흐름!27:27) -> 0 | ... S81: =SUMIF(현금흐름!$15:$15,'A&R'!S$68,현금흐름!27:27) -> 0
B82: =현금흐름!C28 -> 투자현금흐름 합계 | E82: =SUM(E79:E81) -> -258513.77 | F82: =SUM(F79:F81) -> 0 | G82: =SUM(G79:G81) -> 0 | H82: =SUM(H79:H81) -> 0 | I82: =SUM(I79:I81) -> 0 | J82: =SUM(J79:J81) -> 0 | K82: =SUM(K79:K81) -> 0 | L82: =SUM(L79:L81) -> 0 | ... S82: =SUM(S79:S81) -> 0 | U82: 3) N+1년차 Normalized 운영비용
U83: 구분 | V83: =Y45 -> 5 | W83: CAGR | X83: N+1년차
B84: =현금흐름!B30 -> 재무현금흐름 | U84: =$V35 -> PM Fee | V84: =SUMIF($Y$27:$AH$27,$V$83,$Y35:$AH35) -> 90.427986 | W84: =RATE($V$83-1,0,-$Y35,$V84) -> 0.025 | X84: =$V84*(1+$W84) -> 92.688685
B85: =현금흐름!C31 -> 자기자본 증자 | U85: =$V36 -> FM Fee | V85: =SUMIF($Y$27:$AH$27,$V$83,$Y36:$AH36) -> 1105.2309 | W85: =RATE($V$83-1,0,-$Y36,$V85) -> 0.025 | X85: =$V85*(1+$W85) -> 1132.8617
C86: =현금흐름!D32 -> 제1종수익증권 | E86: =SUMIF(현금흐름!$15:$15,'A&R'!E$68,현금흐름!32:32) -> 51500 | F86: =SUMIF(현금흐름!$15:$15,'A&R'!F$68,현금흐름!32:32) -> 0 | G86: =SUMIF(현금흐름!$15:$15,'A&R'!G$68,현금흐름!32:32) -> 0 | H86: =SUMIF(현금흐름!$15:$15,'A&R'!H$68,현금흐름!32:32) -> 0 | I86: =SUMIF(현금흐름!$15:$15,'A&R'!I$68,현금흐름!32:32) -> 0 | J86: =SUMIF(현금흐름!$15:$15,'A&R'!J$68,현금흐름!32:32) -> 0 | K86: =SUMIF(현금흐름!$15:$15,'A&R'!K$68,현금흐름!32:32) -> 0 | L86: =SUMIF(현금흐름!$15:$15,'A&R'!L$68,현금흐름!32:32) -> 0 | ... S86: =SUMIF(현금흐름!$15:$15,'A&R'!S$68,현금흐름!32:32) -> 0 | U86: =$V37 -> 수도광열비 | V86: =SUMIF($Y$27:$AH$27,$V$83,$Y37:$AH37) -> 803.80432 | W86: =RATE($V$83-1,0,-$Y37,$V86) -> 0.025 | X86: =$V86*(1+$W86) -> 823.89943
C87: =현금흐름!D33 -> 제2종수익증권 | E87: =SUMIF(현금흐름!$15:$15,'A&R'!E$68,현금흐름!33:33) -> 46500 | F87: =SUMIF(현금흐름!$15:$15,'A&R'!F$68,현금흐름!33:33) -> 0 | G87: =SUMIF(현금흐름!$15:$15,'A&R'!G$68,현금흐름!33:33) -> 0 | H87: =SUMIF(현금흐름!$15:$15,'A&R'!H$68,현금흐름!33:33) -> 0 | I87: =SUMIF(현금흐름!$15:$15,'A&R'!I$68,현금흐름!33:33) -> 0 | J87: =SUMIF(현금흐름!$15:$15,'A&R'!J$68,현금흐름!33:33) -> 0 | K87: =SUMIF(현금흐름!$15:$15,'A&R'!K$68,현금흐름!33:33) -> 0 | L87: =SUMIF(현금흐름!$15:$15,'A&R'!L$68,현금흐름!33:33) -> 0 | ... S87: =SUMIF(현금흐름!$15:$15,'A&R'!S$68,현금흐름!33:33) -> 0 | U87: =$V38 -> 유지관리비 | V87: =SUMIF($Y$27:$AH$27,$V$83,$Y38:$AH38) -> 246.16507 | W87: 0.025 | X87: =$V87*(1+$W87) -> 252.3192
B88: =현금흐름!C34 -> 타인자본 조달 | U88: =$V39 -> 보험료 | V88: =SUMIF($Y$27:$AH$27,$V$83,$Y39:$AH39) -> 20.095108 | W88: =RATE($V$83-1,0,-$Y39,$V88) -> 0.025 | X88: =$V88*(1+$W88) -> 20.597486
C89: =현금흐름!D35 -> Tr.A 담보대출 | E89: =SUMIF(현금흐름!$15:$15,'A&R'!E$68,현금흐름!35:35) -> 145594.83 | F89: =SUMIF(현금흐름!$15:$15,'A&R'!F$68,현금흐름!35:35) -> 0 | G89: =SUMIF(현금흐름!$15:$15,'A&R'!G$68,현금흐름!35:35) -> 0 | H89: =SUMIF(현금흐름!$15:$15,'A&R'!H$68,현금흐름!35:35) -> 0 | I89: =SUMIF(현금흐름!$15:$15,'A&R'!I$68,현금흐름!35:35) -> 0 | J89: =SUMIF(현금흐름!$15:$15,'A&R'!J$68,현금흐름!35:35) -> 0 | K89: =SUMIF(현금흐름!$15:$15,'A&R'!K$68,현금흐름!35:35) -> 0 | L89: =SUMIF(현금흐름!$15:$15,'A&R'!L$68,현금흐름!35:35) -> 0 | ... S89: =SUMIF(현금흐름!$15:$15,'A&R'!S$68,현금흐름!35:35) -> 0 | U89: =$V40 -> 제세공과금 | V89: =SUMIF($Y$27:$AH$27,$V$83,$Y40:$AH40) -> 1302.4992 | W89: =RATE($V$83-1,0,-$Y40,$V89) -> 0.025 | X89: =$V89*(1+$W89) -> 1335.0617 | AD89: N+1년차 NOI | AG89: =AH73+X80-X90 -> 14327.653 | AH89: 백만원
C90: =현금흐름!D36 -> Tr.B 담보대출 | E90: =SUMIF(현금흐름!$15:$15,'A&R'!E$68,현금흐름!36:36) -> 10000 | F90: =SUMIF(현금흐름!$15:$15,'A&R'!F$68,현금흐름!36:36) -> 0 | G90: =SUMIF(현금흐름!$15:$15,'A&R'!G$68,현금흐름!36:36) -> 0 | H90: =SUMIF(현금흐름!$15:$15,'A&R'!H$68,현금흐름!36:36) -> 0 | I90: =SUMIF(현금흐름!$15:$15,'A&R'!I$68,현금흐름!36:36) -> 0 | J90: =SUMIF(현금흐름!$15:$15,'A&R'!J$68,현금흐름!36:36) -> 0 | K90: =SUMIF(현금흐름!$15:$15,'A&R'!K$68,현금흐름!36:36) -> 0 | L90: =SUMIF(현금흐름!$15:$15,'A&R'!L$68,현금흐름!36:36) -> 0 | ... S90: =SUMIF(현금흐름!$15:$15,'A&R'!S$68,현금흐름!36:36) -> 0 | U90: 합계 | V90: =SUM(V84:V89) -> 3568.2226 | X90: =SUM(X84:X89) -> 3657.4282 | AE90: NOI Margin | AG90: =AG89/(AH73+X80) -> 0.79664099
C91: =현금흐름!D37 -> 보증금 | E91: =SUMIF(현금흐름!$15:$15,'A&R'!E$68,현금흐름!37:37) -> 4918.9383 | F91: =SUMIF(현금흐름!$15:$15,'A&R'!F$68,현금흐름!37:37) -> 0 | G91: =SUMIF(현금흐름!$15:$15,'A&R'!G$68,현금흐름!37:37) -> 0 | H91: =SUMIF(현금흐름!$15:$15,'A&R'!H$68,현금흐름!37:37) -> 0 | I91: =SUMIF(현금흐름!$15:$15,'A&R'!I$68,현금흐름!37:37) -> 0 | J91: =SUMIF(현금흐름!$15:$15,'A&R'!J$68,현금흐름!37:37) -> 0 | K91: =SUMIF(현금흐름!$15:$15,'A&R'!K$68,현금흐름!37:37) -> 0 | L91: =SUMIF(현금흐름!$15:$15,'A&R'!L$68,현금흐름!37:37) -> 0 | ... S91: =SUMIF(현금흐름!$15:$15,'A&R'!S$68,현금흐름!37:37) -> 0 | U91: 3. 매각가치 산정 (수익환원법)
C92: =현금흐름!D38 -> Tr.A 리파이낸싱 | E92: =SUMIF(현금흐름!$15:$15,'A&R'!E$68,현금흐름!38:38) -> 0 | F92: =SUMIF(현금흐름!$15:$15,'A&R'!F$68,현금흐름!38:38) -> 0 | G92: =SUMIF(현금흐름!$15:$15,'A&R'!G$68,현금흐름!38:38) -> 0 | H92: =SUMIF(현금흐름!$15:$15,'A&R'!H$68,현금흐름!38:38) -> 0 | I92: =SUMIF(현금흐름!$15:$15,'A&R'!I$68,현금흐름!38:38) -> 0 | J92: =SUMIF(현금흐름!$15:$15,'A&R'!J$68,현금흐름!38:38) -> 0 | K92: =SUMIF(현금흐름!$15:$15,'A&R'!K$68,현금흐름!38:38) -> 145594.83 | L92: =SUMIF(현금흐름!$15:$15,'A&R'!L$68,현금흐름!38:38) -> 0 | ... S92: =SUMIF(현금흐름!$15:$15,'A&R'!S$68,현금흐름!38:38) -> 0 | U92: 1) Exit Cap. Rate | W92: =$AG$110 -> 0.0465
C93: =현금흐름!D39 -> Tr.B 리파이낸싱 | E93: =SUMIF(현금흐름!$15:$15,'A&R'!E$68,현금흐름!39:39) -> 0 | F93: =SUMIF(현금흐름!$15:$15,'A&R'!F$68,현금흐름!39:39) -> 0 | G93: =SUMIF(현금흐름!$15:$15,'A&R'!G$68,현금흐름!39:39) -> 0 | H93: =SUMIF(현금흐름!$15:$15,'A&R'!H$68,현금흐름!39:39) -> 0 | I93: =SUMIF(현금흐름!$15:$15,'A&R'!I$68,현금흐름!39:39) -> 10000 | J93: =SUMIF(현금흐름!$15:$15,'A&R'!J$68,현금흐름!39:39) -> 0 | K93: =SUMIF(현금흐름!$15:$15,'A&R'!K$68,현금흐름!39:39) -> 0 | L93: =SUMIF(현금흐름!$15:$15,'A&R'!L$68,현금흐름!39:39) -> 0 | ... S93: =SUMIF(현금흐름!$15:$15,'A&R'!S$68,현금흐름!39:39) -> 0 | U93: 2) 임차보증금 | W93: =Rentroll!Y63 -> 7940.6603 | AD93: 매각가치 | AG93: =AG89/W92+W93 -> 316062.22 | AH93: 백만원
B94: =현금흐름!C40 -> 자기자본 감자 | U94: 3) 매각가치 = N+1년차 NOI/Cap rate + 임차보증금 | AE94: 연면적당 평당 매각가치 | AG94: =AG93/M20 -> 41.666685 | AH94: 백만원/평
C95: =현금흐름!D41 -> 제1종수익증권 | E95: =SUMIF(현금흐름!$15:$15,'A&R'!E$68,현금흐름!41:41) -> 0 | F95: =SUMIF(현금흐름!$15:$15,'A&R'!F$68,현금흐름!41:41) -> 0 | G95: =SUMIF(현금흐름!$15:$15,'A&R'!G$68,현금흐름!41:41) -> 0 | H95: =SUMIF(현금흐름!$15:$15,'A&R'!H$68,현금흐름!41:41) -> 0 | I95: =SUMIF(현금흐름!$15:$15,'A&R'!I$68,현금흐름!41:41) -> 0 | J95: =SUMIF(현금흐름!$15:$15,'A&R'!J$68,현금흐름!41:41) -> 0 | K95: =SUMIF(현금흐름!$15:$15,'A&R'!K$68,현금흐름!41:41) -> 0 | L95: =SUMIF(현금흐름!$15:$15,'A&R'!L$68,현금흐름!41:41) -> 0 | ... S95: =SUMIF(현금흐름!$15:$15,'A&R'!S$68,현금흐름!41:41) -> 0 | U95: 4. 순매각가치 산정
C96: =현금흐름!D42 -> 제2종수익증권 | E96: =SUMIF(현금흐름!$15:$15,'A&R'!E$68,현금흐름!42:42) -> 0 | F96: =SUMIF(현금흐름!$15:$15,'A&R'!F$68,현금흐름!42:42) -> 0 | G96: =SUMIF(현금흐름!$15:$15,'A&R'!G$68,현금흐름!42:42) -> 0 | H96: =SUMIF(현금흐름!$15:$15,'A&R'!H$68,현금흐름!42:42) -> 0 | I96: =SUMIF(현금흐름!$15:$15,'A&R'!I$68,현금흐름!42:42) -> 0 | J96: =SUMIF(현금흐름!$15:$15,'A&R'!J$68,현금흐름!42:42) -> 0 | K96: =SUMIF(현금흐름!$15:$15,'A&R'!K$68,현금흐름!42:42) -> 0 | L96: =SUMIF(현금흐름!$15:$15,'A&R'!L$68,현금흐름!42:42) -> 0 | ... S96: =SUMIF(현금흐름!$15:$15,'A&R'!S$68,현금흐름!42:42) -> 0 | U96: 1) 매각 부대비용
B97: =현금흐름!C43 -> 타인자본 상환 | V97: 매각 비용 | X97: 매각가의 | AA97: 0.003 | AB97: =AG93*AA97 -> 948.18667 | AC97: 백만원
C98: =현금흐름!D44 -> Tr.A 담보대출 | E98: =SUMIF(현금흐름!$15:$15,'A&R'!E$68,현금흐름!44:44) -> 0 | F98: =SUMIF(현금흐름!$15:$15,'A&R'!F$68,현금흐름!44:44) -> 0 | G98: =SUMIF(현금흐름!$15:$15,'A&R'!G$68,현금흐름!44:44) -> 0 | H98: =SUMIF(현금흐름!$15:$15,'A&R'!H$68,현금흐름!44:44) -> 0 | I98: =SUMIF(현금흐름!$15:$15,'A&R'!I$68,현금흐름!44:44) -> 0 | J98: =SUMIF(현금흐름!$15:$15,'A&R'!J$68,현금흐름!44:44) -> 0 | K98: =SUMIF(현금흐름!$15:$15,'A&R'!K$68,현금흐름!44:44) -> -145594.83 | L98: =SUMIF(현금흐름!$15:$15,'A&R'!L$68,현금흐름!44:44) -> 0 | ... S98: =SUMIF(현금흐름!$15:$15,'A&R'!S$68,현금흐름!44:44) -> 0 | V98: 매각 기본보수 | X98: 매각가의 | AA98: 0.005 | AB98: =AG93*AA98 -> 1580.3111 | AC98: 백만원
C99: =현금흐름!D45 -> Tr.B 담보대출 | E99: =SUMIF(현금흐름!$15:$15,'A&R'!E$68,현금흐름!45:45) -> 0 | F99: =SUMIF(현금흐름!$15:$15,'A&R'!F$68,현금흐름!45:45) -> 0 | G99: =SUMIF(현금흐름!$15:$15,'A&R'!G$68,현금흐름!45:45) -> 0 | H99: =SUMIF(현금흐름!$15:$15,'A&R'!H$68,현금흐름!45:45) -> 0 | I99: =SUMIF(현금흐름!$15:$15,'A&R'!I$68,현금흐름!45:45) -> -10000 | J99: =SUMIF(현금흐름!$15:$15,'A&R'!J$68,현금흐름!45:45) -> 0 | K99: =SUMIF(현금흐름!$15:$15,'A&R'!K$68,현금흐름!45:45) -> 0 | L99: =SUMIF(현금흐름!$15:$15,'A&R'!L$68,현금흐름!45:45) -> 0 | ... S99: =SUMIF(현금흐름!$15:$15,'A&R'!S$68,현금흐름!45:45) -> 0 | V99: 매각 성과보수 (2종 기준) | X99: IRR 초과분 | Y99: =MAX((E141-AG99)/AG99,0) -> 0.066552415 | Z99: 의 | AA99: 0.2 | AB99: =MAX(AG104*Y99*AA99,0) -> 651.30564 | AC99: 백만원 | AD99: *2종수익증권 목표 IRR | AF99: ➔ | AG99: 0.17
C100: =현금흐름!D46 -> 보증금 | E100: =SUMIF(현금흐름!$15:$15,'A&R'!E$68,현금흐름!46:46) -> 0 | F100: =SUMIF(현금흐름!$15:$15,'A&R'!F$68,현금흐름!46:46) -> 2073.9984 | G100: =SUMIF(현금흐름!$15:$15,'A&R'!G$68,현금흐름!46:46) -> 385.47055 | H100: =SUMIF(현금흐름!$15:$15,'A&R'!H$68,현금흐름!46:46) -> 0 | I100: =SUMIF(현금흐름!$15:$15,'A&R'!I$68,현금흐름!46:46) -> 0 | J100: =SUMIF(현금흐름!$15:$15,'A&R'!J$68,현금흐름!46:46) -> 229.4151 | K100: =SUMIF(현금흐름!$15:$15,'A&R'!K$68,현금흐름!46:46) -> 94.195716 | L100: =SUMIF(현금흐름!$15:$15,'A&R'!L$68,현금흐름!46:46) -> 105.1738 | ... S100: =SUMIF(현금흐름!$15:$15,'A&R'!S$68,현금흐름!46:46) -> 0 | V100: 소계 | AB100: =SUM(AB97:AB99) -> 3179.8034 | AC100: 백만원
C101: =현금흐름!D47 -> Tr.A 리파이낸싱 | E101: =SUMIF(현금흐름!$15:$15,'A&R'!E$68,현금흐름!47:47) -> 0 | F101: =SUMIF(현금흐름!$15:$15,'A&R'!F$68,현금흐름!47:47) -> 0 | G101: =SUMIF(현금흐름!$15:$15,'A&R'!G$68,현금흐름!47:47) -> 0 | H101: =SUMIF(현금흐름!$15:$15,'A&R'!H$68,현금흐름!47:47) -> 0 | I101: =SUMIF(현금흐름!$15:$15,'A&R'!I$68,현금흐름!47:47) -> 0 | J101: =SUMIF(현금흐름!$15:$15,'A&R'!J$68,현금흐름!47:47) -> 0 | K101: =SUMIF(현금흐름!$15:$15,'A&R'!K$68,현금흐름!47:47) -> 0 | L101: =SUMIF(현금흐름!$15:$15,'A&R'!L$68,현금흐름!47:47) -> 0 | ... S101: =SUMIF(현금흐름!$15:$15,'A&R'!S$68,현금흐름!47:47) -> 0 | U101: 2) 순 매각가치 | W101: = 매각가치 - 매각부대비용 | AD101: 순 매각가치 | AG101: =AG93-AB100 -> 312882.42 | AH101: 백만원
C102: =현금흐름!D48 -> Tr.B 리파이낸싱 | E102: =SUMIF(현금흐름!$15:$15,'A&R'!E$68,현금흐름!48:48) -> 0 | F102: =SUMIF(현금흐름!$15:$15,'A&R'!F$68,현금흐름!48:48) -> 0 | G102: =SUMIF(현금흐름!$15:$15,'A&R'!G$68,현금흐름!48:48) -> 0 | H102: =SUMIF(현금흐름!$15:$15,'A&R'!H$68,현금흐름!48:48) -> 0 | I102: =SUMIF(현금흐름!$15:$15,'A&R'!I$68,현금흐름!48:48) -> 0 | J102: =SUMIF(현금흐름!$15:$15,'A&R'!J$68,현금흐름!48:48) -> 0 | K102: =SUMIF(현금흐름!$15:$15,'A&R'!K$68,현금흐름!48:48) -> 0 | L102: =SUMIF(현금흐름!$15:$15,'A&R'!L$68,현금흐름!48:48) -> 0 | ... S102: =SUMIF(현금흐름!$15:$15,'A&R'!S$68,현금흐름!48:48) -> 0 | U102: 5. 매각차익 | AD102: 매각차익 | AG102: =AG101-$E$43 -> 54368.646 | AH102: 백만원
...

Sheet Rentroll
B2: Team LAVEL | E2: 재계약 및 임차확약 | W2: 변수입력 | X2: 합계1 | Y2: 제목
B3: KBC타워 재무모델 | E3: 신규 계약 | W3: 적정성확인 | X3: 합계2 | Y3: 표제목
E4: 운용기간과 무관 | W4: 오류확인 | X4: 합계3 | Y4: 작성자참고
A6: 단위: 백만원
A7: Rentroll
C8: 현 임대차 계약 | AC8: 보증금이자율 | AE8: 0.03
C9: 층수 | D9: 용도 | E9: 임차인 | F9: 면적 정보(㎡) | H9: 면적 정보(py) | J9: 전용률 | K9: 계약기간 | N9: 임대단가(원/py) | R9: TI (원/py) | S9: Fitout (개월) | T9: Rentfree (개월) | U9: 연상승률 | W9: NOC(원/py) | Y9: 보증금총액 (백만원) | Z9: 연 운영수입 (백만원) | AA9: 매입시 잔존월수
F10: 임대면적 | G10: 전용면적 | H10: 임대면적 | I10: 전용면적 | K10: 시작월 | L10: 종료월 | M10: 기간 | N10: 보증금 | O10: 명목 임대료 | P10: 실질 임대료 | Q10: 관리비 | U10: 임대료 | V10: 관리비 | W10: F.NOC | X10: E.NOC
C11: 17 | D11: Office | E11: 리마 상사 | F11: 1385.09 | G11: 683.57 | H11: =F11*py -> 418.98972 | I11: =G11*py -> 206.77993 | J11: =G11/F11 -> 0.49352028 | K11: 45322 | L11: 47148 | M11: =DATEDIF(K11,EOMONTH(L11,0),"m") -> 60 | N11: =O11*10 -> 1000000 | O11: 100000 | P11: =O11*(12-T11)/12 -> 75000 | Q11: 45000 | R11: 0 | S11: 0 | T11: 3 | U11: 0.03 | V11: 0.03 | W11: =(($O11+$Q11))/$J11 -> 293807.58 | X11: =IFERROR(((N11*$AE$8/12+$O11*($M11-$S11-($T11*M11/12))/$M11)+$Q11)/$J11-R11/M11,0) -> 248216.75 | Y11: =N11*H11/unit -> 418.98972 | Z11: =(P11*H11/unit+Q11*H11/unit)*12 -> 603.3452 | AA11: =IFERROR(DATEDIF(acq,$L11,"m"),0) -> 47
C12: 16 | D12: Office | E12: 리마 상사 | F12: 1385.09 | G12: 683.57 | H12: =F12*py -> 418.98972 | I12: =G12*py -> 206.77993 | J12: =G12/F12 -> 0.49352028 | K12: 45322 | L12: 47148 | M12: =DATEDIF(K12,EOMONTH(L12,0),"m") -> 60 | N12: =O12*10 -> 1000000 | O12: 100000 | P12: =O12*(12-T12)/12 -> 75000 | Q12: 45000 | R12: 0 | S12: 0 | T12: 3 | U12: 0.03 | V12: 0.03 | W12: =(($O12+$Q12))/$J12 -> 293807.58 | X12: =IFERROR(((N12*$AE$8/12+$O12*($M12-$S12-($T12*M12/12))/$M12)+$Q12)/$J12-R12/M12,0) -> 248216.75 | Y12: =N12*H12/unit -> 418.98972 | Z12: =(P12*H12/unit+Q12*H12/unit)*12 -> 603.3452 | AA12: =IFERROR(DATEDIF(acq,$L12,"m"),0) -> 47
C13: 15 | D13: Office | E13: 모빌리티 테크놀로지 | F13: 1385.09 | G13: 683.57 | H13: =F13*py -> 418.98972 | I13: =G13*py -> 206.77993 | J13: =G13/F13 -> 0.49352028 | K13: 44042 | L13: 45869 | M13: =DATEDIF(K13,EOMONTH(L13,0),"m") -> 60 | N13: 800000 | O13: 90041 | P13: =O13*(12-T13)/12 -> 67530.75 | Q13: 45020 | R13: 0 | S13: 0 | T13: 3 | U13: 0.03 | V13: 0.03 | W13: =(($O13+$Q13))/$J13 -> 273668.59 | X13: =IFERROR(((N13*$AE$8/12+$O13*($M13-$S13-($T13*M13/12))/$M13)+$Q13)/$J13-R13/M13,0) -> 232109.51 | Y13: =N13*H13/unit -> 335.19178 | Z13: =(P13*H13/unit+Q13*H13/unit)*12 -> 565.89129 | AA13: =IFERROR(DATEDIF(acq,$L13,"m"),0) -> 6
C14: 14 | D14: Office | E14: 모빌리티 테크놀로지 | F14: 1385.09 | G14: 683.57 | H14: =F14*py -> 418.98972 | I14: =G14*py -> 206.77993 | J14: =G14/F14 -> 0.49352028 | K14: 44043 | L14: 45868 | M14: =DATEDIF(K14,EOMONTH(L14,0),"m") -> 60 | N14: 800000 | O14: 90041 | P14: =O14*(12-T14)/12 -> 67530.75 | Q14: 45020 | R14: 0 | S14: 0 | T14: 3 | U14: 0.03 | V14: 0.03 | W14: =(($O14+$Q14))/$J14 -> 273668.59 | X14: =IFERROR(((N14*$AE$8/12+$O14*($M14-$S14-($T14*M14/12))/$M14)+$Q14)/$J14-R14/M14,0) -> 232109.51 | Y14: =N14*H14/unit -> 335.19178 | Z14: =(P14*H14/unit+Q14*H14/unit)*12 -> 565.89129 | AA14: =IFERROR(DATEDIF(acq,$L14,"m"),0) -> 5
C15: 13 | D15: Office | E15: 모빌리티 테크놀로지 | F15: 1385.09 | G15: 683.57 | H15: =F15*py -> 418.98972 | I15: =G15*py -> 206.77993 | J15: =G15/F15 -> 0.49352028 | K15: 44043 | L15: 45868 | M15: =DATEDIF(K15,EOMONTH(L15,0),"m") -> 60 | N15: 800000 | O15: 90041 | P15: =O15*(12-T15)/12 -> 67530.75 | Q15: 45020 | R15: 0 | S15: 0 | T15: 3 | U15: 0.03 | V15: 0.03 | W15: =(($O15+$Q15))/$J15 -> 273668.59 | X15: =IFERROR(((N15*$AE$8/12+$O15*($M15-$S15-($T15*M15/12))/$M15)+$Q15)/$J15-R15/M15,0) -> 232109.51 | Y15: =N15*H15/unit -> 335.19178 | Z15: =(P15*H15/unit+Q15*H15/unit)*12 -> 565.89129 | AA15: =IFERROR(DATEDIF(acq,$L15,"m"),0) -> 5
C16: 12 | D16: Office | E16: 모빌리티 테크놀로지 | F16: 1385.09 | G16: 683.57 | H16: =F16*py -> 418.98972 | I16: =G16*py -> 206.77993 | J16: =G16/F16 -> 0.49352028 | K16: 44043 | L16: 45868 | M16: =DATEDIF(K16,EOMONTH(L16,0),"m") -> 60 | N16: 800000 | O16: 90041 | P16: =O16*(12-T16)/12 -> 67530.75 | Q16: 45020 | R16: 0 | S16: 0 | T16: 3 | U16: 0.03 | V16: 0.03 | W16: =(($O16+$Q16))/$J16 -> 273668.59 | X16: =IFERROR(((N16*$AE$8/12+$O16*($M16-$S16-($T16*M16/12))/$M16)+$Q16)/$J16-R16/M16,0) -> 232109.51 | Y16: =N16*H16/unit -> 335.19178 | Z16: =(P16*H16/unit+Q16*H16/unit)*12 -> 565.89129 | AA16: =IFERROR(DATEDIF(acq,$L16,"m"),0) -> 5
C17: 11 | D17: Office | E17: 노벰버 건설 | F17: 1385.09 | G17: 683.57 | H17: =F17*py -> 418.98972 | I17: =G17*py -> 206.77993 | J17: =G17/F17 -> 0.49352028 | K17: 45077 | L17: 46903 | M17: =DATEDIF(K17,EOMONTH(L17,0),"m") -> 60 | N17: 1000000 | O17: 103000 | P17: =O17*(12-T17)/12 -> 85833.333 | Q17: 46350 | R17: 0 | S17: 0 | T17: 2 | U17: 0.03 | V17: 0.03 | W17: =(($O17+$Q17))/$J17 -> 302621.81 | X17: =IFERROR(((N17*$AE$8/12+$O17*($M17-$S17-($T17*M17/12))/$M17)+$Q17)/$J17-R17/M17,0) -> 272903.34 | Y17: =N17*H17/unit -> 418.98972 | Z17: =(P17*H17/unit+Q17*H17/unit)*12 -> 664.6015 | AA17: =IFERROR(DATEDIF(acq,$L17,"m"),0) -> 39
C18: 10 | D18: Office | E18: 노벰버 건설 | F18: 1385.09 | G18: 683.57 | H18: =F18*py -> 418.98972 | I18: =G18*py -> 206.77993 | J18: =G18/F18 -> 0.49352028 | K18: 45077 | L18: 46903 | M18: =DATEDIF(K18,EOMONTH(L18,0),"m") -> 60 | N18: 1000000 | O18: 103000 | P18: =O18*(12-T18)/12 -> 85833.333 | Q18: 46350 | R18: 0 | S18: 0 | T18: 2 | U18: 0.03 | V18: 0.03 | W18: =(($O18+$Q18))/$J18 -> 302621.81 | X18: =IFERROR(((N18*$AE$8/12+$O18*($M18-$S18-($T18*M18/12))/$M18)+$Q18)/$J18-R18/M18,0) -> 272903.34 | Y18: =N18*H18/unit -> 418.98972 | Z18: =(P18*H18/unit+Q18*H18/unit)*12 -> 664.6015 | AA18: =IFERROR(DATEDIF(acq,$L18,"m"),0) -> 39 | AC18: 신규 임대차 변수
C19: 9 | D19: Office | E19: 노벰버 건설 | F19: 1385.09 | G19: 683.57 | H19: =F19*py -> 418.98972 | I19: =G19*py -> 206.77993 | J19: =G19/F19 -> 0.49352028 | K19: 45077 | L19: 46903 | M19: =DATEDIF(K19,EOMONTH(L19,0),"m") -> 60 | N19: 1000000 | O19: 103000 | P19: =O19*(12-T19)/12 -> 85833.333 | Q19: 46350 | R19: 0 | S19: 0 | T19: 2 | U19: 0.03 | V19: 0.03 | W19: =(($O19+$Q19))/$J19 -> 302621.81 | X19: =IFERROR(((N19*$AE$8/12+$O19*($M19-$S19-($T19*M19/12))/$M19)+$Q19)/$J19-R19/M19,0) -> 272903.34 | Y19: =N19*H19/unit -> 418.98972 | Z19: =(P19*H19/unit+Q19*H19/unit)*12 -> 664.6015 | AA19: =IFERROR(DATEDIF(acq,$L19,"m"),0) -> 39 | AC19: 오피스 임대료 | AE19: ='A&R'!AG109 -> 103000
C20: 8 | D20: Office | E20: 오토 커머셜 | F20: 1385.09 | G20: 683.57 | H20: =F20*py -> 418.98972 | I20: =G20*py -> 206.77993 | J20: =G20/F20 -> 0.49352028 | K20: 44651 | L20: 46476 | M20: =DATEDIF(K20,EOMONTH(L20,0),"m") -> 60 | N20: 900000 | O20: 95481 | P20: =O20*(12-T20)/12 -> 87524.25 | Q20: 42436 | R20: 0 | S20: 0 | T20: 1 | U20: 0.03 | V20: 0.03 | W20: =(($O20+$Q20))/$J20 -> 279455.59 | X20: =IFERROR(((N20*$AE$8/12+$O20*($M20-$S20-($T20*M20/12))/$M20)+$Q20)/$J20-R20/M20,0) -> 267892.24 | Y20: =N20*H20/unit -> 377.09075 | Z20: =(P20*H20/unit+Q20*H20/unit)*12 -> 653.42411 | AA20: =IFERROR(DATEDIF(acq,$L20,"m"),0) -> 25 | AC20: 오피스 관리비 | AE20: 45000
C21: 7 | D21: Office | E21: 오토 커머셜 | F21: 1385.09 | G21: 683.57 | H21: =F21*py -> 418.98972 | I21: =G21*py -> 206.77993 | J21: =G21/F21 -> 0.49352028 | K21: 44651 | L21: 46476 | M21: =DATEDIF(K21,EOMONTH(L21,0),"m") -> 60 | N21: 900000 | O21: 95481 | P21: =O21*(12-T21)/12 -> 87524.25 | Q21: 42436 | R21: 0 | S21: 0 | T21: 1 | U21: 0.03 | V21: 0.03 | W21: =(($O21+$Q21))/$J21 -> 279455.59 | X21: =IFERROR(((N21*$AE$8/12+$O21*($M21-$S21-($T21*M21/12))/$M21)+$Q21)/$J21-R21/M21,0) -> 267892.24 | Y21: =N21*H21/unit -> 377.09075 | Z21: =(P21*H21/unit+Q21*H21/unit)*12 -> 653.42411 | AA21: =IFERROR(DATEDIF(acq,$L21,"m"),0) -> 25 | AC21: 1F 대비 B1 효용비율 | AE21: 0.3275
C22: 6 | D22: Office | E22: 오토 커머셜 | F22: 1385.09 | G22: 683.57 | H22: =F22*py -> 418.98972 | I22: =G22*py -> 206.77993 | J22: =G22/F22 -> 0.49352028 | K22: 44651 | L22: 46476 | M22: =DATEDIF(K22,EOMONTH(L22,0),"m") -> 60 | N22: 900000 | O22: 95481 | P22: =O22*(12-T22)/12 -> 87524.25 | Q22: 42436 | R22: 0 | S22: 0 | T22: 1 | U22: 0.03 | V22: 0.03 | W22: =(($O22+$Q22))/$J22 -> 279455.59 | X22: =IFERROR(((N22*$AE$8/12+$O22*($M22-$S22-($T22*M22/12))/$M22)+$Q22)/$J22-R22/M22,0) -> 267892.24 | Y22: =N22*H22/unit -> 377.09075 | Z22: =(P22*H22/unit+Q22*H22/unit)*12 -> 653.42411 | AA22: =IFERROR(DATEDIF(acq,$L22,"m"),0) -> 25
C23: 5 | D23: Office | E23: 공실 | F23: 1385.09 | G23: 683.57 | H23: =F23*py -> 418.98972 | I23: =G23*py -> 206.77993 | J23: =G23/F23 -> 0.49352028 | M23: =DATEDIF(K23,EOMONTH(L23,0),"m") -> 0 | N23: =O23*10 -> 0 | O23: 0 | P23: =O23*(12-T23)/12 -> 0 | Q23: 0 | R23: 0 | S23: 0 | T23: 0 | U23: 0 | V23: 0 | W23: =(($O23+$Q23))/$J23 -> 0 | X23: =IFERROR(((N23*$AE$8/12+$O23*($M23-$S23-($T23*M23/12))/$M23)+$Q23)/$J23-R23/M23,0) -> 0 | Y23: =N23*H23/unit -> 0 | Z23: =(P23*H23/unit+Q23*H23/unit)*12 -> 0 | AA23: =IFERROR(DATEDIF(acq,$L23,"m"),0) -> 0 | AC23: WALE
C24: 4 | D24: Office | E24: 공실 | F24: 1385.09 | G24: 683.57 | H24: =F24*py -> 418.98972 | I24: =G24*py -> 206.77993 | J24: =G24/F24 -> 0.49352028 | M24: =DATEDIF(K24,EOMONTH(L24,0),"m") -> 0 | N24: =O24*10 -> 0 | O24: 0 | P24: =O24*(12-T24)/12 -> 0 | Q24: 0 | R24: 0 | S24: 0 | T24: 0 | U24: 0 | V24: 0 | W24: =(($O24+$Q24))/$J24 -> 0 | X24: =IFERROR(((N24*$AE$8/12+$O24*($M24-$S24-($T24*M24/12))/$M24)+$Q24)/$J24-R24/M24,0) -> 0 | Y24: =N24*H24/unit -> 0 | Z24: =(P24*H24/unit+Q24*H24/unit)*12 -> 0 | AA24: =IFERROR(DATEDIF(acq,$L24,"m"),0) -> 0 | AD24: 오피스
C25: 3 | D25: Office | E25: 공실 | F25: 1385.09 | G25: 683.57 | H25: =F25*py -> 418.98972 | I25: =G25*py -> 206.77993 | J25: =G25/F25 -> 0.49352028 | M25: =DATEDIF(K25,EOMONTH(L25,0),"m") -> 0 | N25: =O25*10 -> 0 | O25: 0 | P25: =O25*(12-T25)/12 -> 0 | Q25: 0 | R25: 0 | S25: 0 | T25: 0 | U25: 0 | V25: 0 | W25: =(($O25+$Q25))/$J25 -> 0 | X25: =IFERROR(((N25*$AE$8/12+$O25*($M25-$S25-($T25*M25/12))/$M25)+$Q25)/$J25-R25/M25,0) -> 0 | Y25: =N25*H25/unit -> 0 | Z25: =(P25*H25/unit+Q25*H25/unit)*12 -> 0 | AA25: =IFERROR(DATEDIF(acq,$L25,"m"),0) -> 0 | AD25: 매입시점 | AE25: =SUMPRODUCT(AA11:AA26,F11:F26)/SUM(F11:F26)/12 -> 1.5989583
C26: 2 | D26: Office | E26: 공실 | F26: 1385.09 | G26: 683.57 | H26: =F26*py -> 418.98972 | I26: =G26*py -> 206.77993 | J26: =G26/F26 -> 0.49352028 | M26: =DATEDIF(K26,EOMONTH(L26,0),"m") -> 0 | N26: =O26*10 -> 0 | O26: 0 | P26: =O26*(12-T26)/12 -> 0 | Q26: 0 | R26: 0 | S26: 0 | T26: 0 | U26: 0 | V26: 0 | W26: =(($O26+$Q26))/$J26 -> 0 | X26: =IFERROR(((N26*$AE$8/12+$O26*($M26-$S26-($T26*M26/12))/$M26)+$Q26)/$J26-R26/M26,0) -> 0 | Y26: =N26*H26/unit -> 0 | Z26: =(P26*H26/unit+Q26*H26/unit)*12 -> 0 | AA26: =IFERROR(DATEDIF(acq,$L26,"m"),0) -> 0 | AD26: 매각시점 | AE26: =SUMPRODUCT(AE37:AE51,F37:F51)/SUM(F37:F51)/12 -> 1.7666667
C27: 1 | D27: Retail | E27: 파파 커피앤도넛 | F27: 969.56 | G27: 410.14 | H27: =F27*py -> 293.2919 | I27: =G27*py -> 124.06735 | J27: =G27/F27 -> 0.42301663 | K27: 42064 | L27: 45716 | M27: =DATEDIF(K27,EOMONTH(L27,1),"m") -> 120 | N27: 700000 | O27: 91334 | P27: =O27*(12-T27)/12 -> 83722.833 | Q27: 39143 | R27: 0 | S27: 0 | T27: 1 | U27: 0.03 | V27: 0.03 | W27: =(($O27+$Q27))/$J27 -> 308444.14 | X27: =IFERROR(((N27*$AE$8/12+$O27*($M27-$S27-($T27*M27/12))/$M27)+$Q27)/$J27-R27/M27,0) -> 294588.5 | Y27: =N27*H27/unit -> 205.30433 | Z27: =(P27*H27/unit+Q27*H27/unit)*12 -> 432.42664 | AA27: =IFERROR(DATEDIF(acq,$L27,"m"),0) -> 0 | AD27: 리테일
C28: B101호 | D28: Retail | E28: 퀸즈 샌드위치 | F28: 969.56 | G28: 410.14 | H28: =F28*py -> 293.2919 | I28: =G28*py -> 124.06735 | J28: =G28/F28 -> 0.42301663 | K28: 44926 | L28: 46751 | M28: =DATEDIF(K28,EOMONTH(L28,0),"m") -> 60 | N28: 200000 | O28: 21218 | P28: =O28*(12-T28)/12 -> 17681.667 | Q28: 31827 | R28: 0 | S28: 0 | T28: 2 | U28: 0.03 | V28: 0.03 | W28: =(($O28+$Q28))/$J28 -> 125396.96 | X28: =IFERROR(((N28*$AE$8/12+$O28*($M28-$S28-($T28*M28/12))/$M28)+$Q28)/$J28-R28/M28,0) -> 118219.15 | Y28: =N28*H28/unit -> 58.65838 | Z28: =(P28*H28/unit+Q28*H28/unit)*12 -> 174.24589 | AA28: =IFERROR(DATEDIF(acq,$L28,"m"),0) -> 34 | AD28: 매입시점 | AE28: =SUMPRODUCT(AA27:AA29,F27:F29)/SUM(F27:F29)/12 -> 1.5833333
C29: B102호 | D29: Retail | E29: 로미오 문구점 | F29: 969.56 | G29: 410.14 | H29: =F29*py -> 293.2919 | I29: =G29*py -> 124.06735 | J29: =G29/F29 -> 0.42301663 | K29: 44592 | L29: 46417 | M29: =DATEDIF(K29,EOMONTH(L29,0),"m") -> 60 | N29: 300000 | O29: 31827 | P29: =O29*(12-T29)/12 -> 23870.25 | Q29: 31827 | R29: 0 | S29: 0 | T29: 3 | U29: 0.03 | V29: 0.03 | W29: =(($O29+$Q29))/$J29 -> 150476.36 | X29: =IFERROR(((N29*$AE$8/12+$O29*($M29-$S29-($T29*M29/12))/$M29)+$Q29)/$J29-R29/M29,0) -> 133439.79 | Y29: =N29*H29/unit -> 87.98757 | Z29: =(P29*H29/unit+Q29*H29/unit)*12 -> 196.02663 | AA29: =IFERROR(DATEDIF(acq,$L29,"m"),0) -> 23 | AD29: 매각시점 | AE29: =SUMPRODUCT(AE52:AE60,F52:F60)/SUM(F52:F60)/12 -> 1.2392462
C30: Office Total | F30: =SUMIF($D$11:$D$29,D11,F$11:F$29) -> 22161.44 | G30: =SUMIF($D$11:$D$29,D11,G$11:G$29) -> 10937.12 | H30: =SUMIF($D$11:$D$29,D11,H$11:H$29) -> 6703.8356 | I30: =SUMIF($D$11:$D$29,D11,I$11:I$29) -> 3308.4788 | J30: =G30/F30 -> 0.49352028 | W30: =AVERAGE(W11:W22) -> 285710.15 | X30: =AVERAGE(X11:X22) -> 253938.19 | Y30: =SUMIF($D$11:$D$29,D11,Y$11:Y$29) -> 4566.988 | Z30: =SUMIF($D$11:$D$29,D11,Z$11:Z$29) -> 7424.3324 | AD30: 전체
C31: Retail Total | F31: =SUMIF($D$11:$D$29,$D$29,F$11:F$29) -> 2908.68 | G31: =SUMIF($D$11:$D$29,$D$29,G$11:G$29) -> 1230.42 | H31: =SUMIF($D$11:$D$29,$D$29,H$11:H$29) -> 879.8757 | I31: =SUMIF($D$11:$D$29,$D$29,I$11:I$29) -> 372.20205 | J31: =G31/F31 -> 0.42301663 | Y31: =SUMIF($D$11:$D$29,D29,Y$11:Y$29) -> 351.95028 | Z31: =SUMIF($D$11:$D$29,D29,Z$11:Z$29) -> 802.69916 | AD31: 매입시점 | AE31: =SUMPRODUCT(AA11:AA29,F11:F29)/SUM(F11:F29)/12 -> 1.5971455
C32: Total | F32: =SUM(F30:F31) -> 25070.12 | G32: =SUM(G30:G31) -> 12167.54 | H32: =SUM(H30:H31) -> 7583.7113 | I32: =SUM(I30:I31) -> 3680.6808 | J32: =G32/F32 -> 0.48534032 | Y32: =SUM(Y30:Y31) -> 4918.9383 | Z32: =SUM(Z30:Z31) -> 8227.0316 | AD32: 매각시점 | AE32: =SUMPRODUCT(AE37:AE60,F37:F60)/SUM(F37:F60)/12 -> 1.6763351
C34: 신규 임대차 계약
C35: 층수 | D35: 용도 | E35: 임차인 | F35: 면적 정보(㎡) | H35: 면적 정보(py) | J35: 전용률 | K35: 계약기간 | N35: 임대단가(원/py) | R35: TI (원/py) | S35: Fitout (개월) | T35: Rentfree (개월) | U35: 연상승률 | W35: NOC(원/py) | Y35: 보증금총액 (백만원) | Z35: 계약 유형 | AA35: 계약기간 시작기준일 | AB35: Downtime (개월) | AC35: TI 총액 | AD35: 월세 (원) | AE35: 매각시 잔존월수
F36: 임대면적 | G36: 전용면적 | H36: 임대면적 | I36: 전용면적 | K36: 시작월 | L36: 종료월 | M36: 기간 | N36: 보증금 | O36: 명목 임대료 | P36: 실질 임대료 | Q36: 관리비 | U36: 임대료 | V36: 관리비 | W36: F.NOC | X36: E.NOC
C37: 17 | D37: Office | E37: 리마 상사 | F37: 1385.09 | G37: 683.57 | H37: =F37*py -> 418.98972 | I37: =G37*py -> 206.77993 | J37: =G37/F37 -> 0.49352028 | K37: =EOMONTH($AA37,$AB37) -> 47149 | L37: =EOMONTH($K37,$M37) -> 48975 | M37: 60 | N37: =O37*10 -> 1159274.1 | O37: =(1+$U37)^(DATEDIF(acq,$K37,"y"))*$AE$19 -> 115927.41 | P37: =O37*(12-T37)/12 -> 106266.79 | Q37: =(1+$V37)^(DATEDIF(acq,$K37,"y"))*$AE$20 -> 50647.896 | R37: 0 | S37: 0 | T37: 1 | U37: 0.03 | V37: 0.03 | W37: =(($O37+$Q37))/$J37 -> 337524.74 | X37: =IFERROR(((N37*$AE$8/12+$O37*($M37-$S37-($T37*M37/12))/$M37)+$Q37)/$J37-R37/M37,0) -> 323822.3 | Y37: =N37*H37/unit -> 485.72393 | Z37: 0 | AA37: 47149 | AB37: 0 | AC37: =R37*H37/unit -> 0 | AD37: =O37*H37 -> 48572393 | AE37: =IFERROR(DATEDIF(exit,$L37,"m"),0) -> 48
C38: 16 | D38: Office | E38: 리마 상사 | F38: 1385.09 | G38: 683.57 | H38: =F38*py -> 418.98972 | I38: =G38*py -> 206.77993 | J38: =G38/F38 -> 0.49352028 | K38: =EOMONTH($AA38,$AB38) -> 47149 | L38: =EOMONTH($K38,$M38) -> 48975 | M38: 60 | N38: =O38*10 -> 1159274.1 | O38: =(1+$U38)^(DATEDIF(acq,$K38,"y"))*$AE$19 -> 115927.41 | P38: =O38*(12-T38)/12 -> 106266.79 | Q38: =(1+$V38)^(DATEDIF(acq,$K38,"y"))*$AE$20 -> 50647.896 | R38: 0 | S38: 0 | T38: 1 | U38: 0.03 | V38: 0.03 | W38: =(($O38+$Q38))/$J38 -> 337524.74 | X38: =IFERROR(((N38*$AE$8/12+$O38*($M38-$S38-($T38*M38/12))/$M38)+$Q38)/$J38-R38/M38,0) -> 323822.3 | Y38: =N38*H38/unit -> 485.72393 | Z38: 0 | AA38: 47149 | AB38: 0 | AC38: =R38*H38/unit -> 0 | AD38: =O38*H38 -> 48572393 | AE38: =IFERROR(DATEDIF(exit,$L38,"m"),0) -> 48
C39: 15 | D39: Office | E39: 111퍼센트 | F39: 1385.09 | G39: 683.57 | H39: =F39*py -> 418.98972 | I39: =G39*py -> 206.77993 | J39: =G39/F39 -> 0.49352028 | K39: =EOMONTH($AA39,$AB39) -> 45869 | L39: =EOMONTH($K39,$M39) -> 47695 | M39: 60 | N39: =O39*10 -> 1030000 | O39: =(1+$U39)^(DATEDIF(acq,$K39,"y"))*$AE$19 -> 103000 | P39: =O39*(12-T39)/12 -> 94416.667 | Q39: =(1+$V39)^(DATEDIF(acq,$K39,"y"))*$AE$20 -> 45000 | R39: 0 | S39: 1 | T39: 1 | U39: 0.03 | V39: 0.03 | W39: =(($O39+$Q39))/$J39 -> 299886.36 | X39: =IFERROR(((N39*$AE$8/12+$O39*($M39-$S39-($T39*M39/12))/$M39)+$Q39)/$J39-R39/M39,0) -> 284233.51 | Y39: =N39*H39/unit -> 431.55942 | Z39: 1 | AA39: 45869 | AB39: 0 | AC39: =R39*H39/unit -> 0 | AD39: =O39*H39 -> 43155942 | AE39: =IFERROR(DATEDIF(exit,$L39,"m"),0) -> 6
C40: 14 | D40: Office | E40: 111퍼센트 | F40: 1385.09 | G40: 683.57 | H40: =F40*py -> 418.98972 | I40: =G40*py -> 206.77993 | J40: =G40/F40 -> 0.49352028 | K40: =EOMONTH($AA40,$AB40) -> 45869 | L40: =EOMONTH($K40,$M40) -> 47695 | M40: 60 | N40: =O40*10 -> 1030000 | O40: =(1+$U40)^(DATEDIF(acq,$K40,"y"))*$AE$19 -> 103000 | P40: =O40*(12-T40)/12 -> 94416.667 | Q40: =(1+$V40)^(DATEDIF(acq,$K40,"y"))*$AE$20 -> 45000 | R40: 0 | S40: 1 | T40: 1 | U40: 0.03 | V40: 0.03 | W40: =(($O40+$Q40))/$J40 -> 299886.36 | X40: =IFERROR(((N40*$AE$8/12+$O40*($M40-$S40-($T40*M40/12))/$M40)+$Q40)/$J40-R40/M40,0) -> 284233.51 | Y40: =N40*H40/unit -> 431.55942 | Z40: 1 | AA40: 45869 | AB40: 0 | AC40: =R40*H40/unit -> 0 | AD40: =O40*H40 -> 43155942 | AE40: =IFERROR(DATEDIF(exit,$L40,"m"),0) -> 6
C41: 13 | D41: Office | E41: 111퍼센트 | F41: 1385.09 | G41: 683.57 | H41: =F41*py -> 418.98972 | I41: =G41*py -> 206.77993 | J41: =G41/F41 -> 0.49352028 | K41: =EOMONTH($AA41,$AB41) -> 45869 | L41: =EOMONTH($K41,$M41) -> 47695 | M41: 60 | N41: =O41*10 -> 1030000 | O41: =(1+$U41)^(DATEDIF(acq,$K41,"y"))*$AE$19 -> 103000 | P41: =O41*(12-T41)/12 -> 94416.667 | Q41: =(1+$V41)^(DATEDIF(acq,$K41,"y"))*$AE$20 -> 45000 | R41: 0 | S41: 1 | T41: 1 | U41: 0.03 | V41: 0.03 | W41: =(($O41+$Q41))/$J41 -> 299886.36 | X41: =IFERROR(((N41*$AE$8/12+$O41*($M41-$S41-($T41*M41/12))/$M41)+$Q41)/$J41-R41/M41,0) -> 284233.51 | Y41: =N41*H41/unit -> 431.55942 | Z41: 1 | AA41: 45869 | AB41: 0 | AC41: =R41*H41/unit -> 0 | AD41: =O41*H41 -> 43155942 | AE41: =IFERROR(DATEDIF(exit,$L41,"m"),0) -> 6
C42: 12 | D42: Office | E42: 신라젠 | F42: 1385.09 | G42: 683.57 | H42: =F42*py -> 418.98972 | I42: =G42*py -> 206.77993 | J42: =G42/F42 -> 0.49352028 | K42: =EOMONTH($AA42,$AB42) -> 45869 | L42: =EOMONTH($K42,$M42) -> 47695 | M42: 60 | N42: =O42*10 -> 1030000 | O42: =(1+$U42)^(DATEDIF(acq,$K42,"y"))*$AE$19 -> 103000 | P42: =O42*(12-T42)/12 -> 94416.667 | Q42: =(1+$V42)^(DATEDIF(acq,$K42,"y"))*$AE$20 -> 45000 | R42: 0 | S42: 1 | T42: 1 | U42: 0.03 | V42: 0.03 | W42: =(($O42+$Q42))/$J42 -> 299886.36 | X42: =IFERROR(((N42*$AE$8/12+$O42*($M42-$S42-($T42*M42/12))/$M42)+$Q42)/$J42-R42/M42,0) -> 284233.51 | Y42: =N42*H42/unit -> 431.55942 | Z42: 1 | AA42: 45869 | AB42: 0 | AC42: =R42*H42/unit -> 0 | AD42: =O42*H42 -> 43155942 | AE42: =IFERROR(DATEDIF(exit,$L42,"m"),0) -> 6
C43: 11 | D43: Office | E43: 노벰버 건설 | F43: 1385.09 | G43: 683.57 | H43: =F43*py -> 418.98972 | I43: =G43*py -> 206.77993 | J43: =G43/F43 -> 0.49352028 | K43: =EOMONTH($AA43,$AB43) -> 46904 | L43: =EOMONTH($K43,$M43) -> 48730 | M43: 60 | N43: =O43*10 -> 1125508.8 | O43: =(1+$U43)^(DATEDIF(acq,$K43,"y"))*$AE$19 -> 112550.88 | P43: =O43*(12-T43)/12 -> 103171.64 | Q43: =(1+$V43)^(DATEDIF(acq,$K43,"y"))*$AE$20 -> 49172.715 | R43: 0 | S43: 0 | T43: 1 | U43: 0.03 | V43: 0.03 | W43: =(($O43+$Q43))/$J43 -> 327693.92 | X43: =IFERROR(((N43*$AE$8/12+$O43*($M43-$S43-($T43*M43/12))/$M43)+$Q43)/$J43-R43/M43,0) -> 314390.58 | Y43: =N43*H43/unit -> 471.57663 | Z43: 0 | AA43: 46904 | AB43: 0 | AC43: =R43*H43/unit -> 0 | AD43: =O43*H43 -> 47157663 | AE43: =IFERROR(DATEDIF(exit,$L43,"m"),0) -> 40
C44: 10 | D44: Office | E44: 노벰버 건설 | F44: 1385.09 | G44: 683.57 | H44: =F44*py -> 418.98972 | I44: =G44*py -> 206.77993 | J44: =G44/F44 -> 0.49352028 | K44: =EOMONTH($AA44,$AB44) -> 46904 | L44: =EOMONTH($K44,$M44) -> 48730 | M44: 60 | N44: =O44*10 -> 1125508.8 | O44: =(1+$U44)^(DATEDIF(acq,$K44,"y"))*$AE$19 -> 112550.88 | P44: =O44*(12-T44)/12 -> 103171.64 | Q44: =(1+$V44)^(DATEDIF(acq,$K44,"y"))*$AE$20 -> 49172.715 | R44: 0 | S44: 0 | T44: 1 | U44: 0.03 | V44: 0.03 | W44: =(($O44+$Q44))/$J44 -> 327693.92 | X44: =IFERROR(((N44*$AE$8/12+$O44*($M44-$S44-($T44*M44/12))/$M44)+$Q44)/$J44-R44/M44,0) -> 314390.58 | Y44: =N44*H44/unit -> 471.57663 | Z44: 0 | AA44: 46904 | AB44: 0 | AC44: =R44*H44/unit -> 0 | AD44: =O44*H44 -> 47157663 | AE44: =IFERROR(DATEDIF(exit,$L44,"m"),0) -> 40
C45: 9 | D45: Office | E45: 노벰버 건설 | F45: 1385.09 | G45: 683.57 | H45: =F45*py -> 418.98972 | I45: =G45*py -> 206.77993 | J45: =G45/F45 -> 0.49352028 | K45: =EOMONTH($AA45,$AB45) -> 46904 | L45: =EOMONTH($K45,$M45) -> 48730 | M45: 60 | N45: 1000000 | O45: =(1+$U45)^(DATEDIF(acq,$K45,"y"))*$AE$19 -> 112550.88 | P45: =O45*(12-T45)/12 -> 103171.64 | Q45: =(1+$V45)^(DATEDIF(acq,$K45,"y"))*$AE$20 -> 49172.715 | R45: 0 | S45: 0 | T45: 1 | U45: 0.03 | V45: 0.03 | W45: =(($O45+$Q45))/$J45 -> 327693.92 | X45: =IFERROR(((N45*$AE$8/12+$O45*($M45-$S45-($T45*M45/12))/$M45)+$Q45)/$J45-R45/M45,0) -> 313754.8 | Y45: =N45*H45/unit -> 418.98972 | Z45: 0 | AA45: 46904 | AB45: 0 | AC45: =R45*H45/unit -> 0 | AD45: =O45*H45 -> 47157663 | AE45: =IFERROR(DATEDIF(exit,$L45,"m"),0) -> 40
C46: 8 | D46: Office | E46: 오케스트로 | F46: 1385.09 | G46: 683.57 | H46: =F46*py -> 418.98972 | I46: =G46*py -> 206.77993 | J46: =G46/F46 -> 0.49352028 | K46: =EOMONTH($AA46,$AB46) -> 46477 | L46: =EOMONTH($K46,$M46) -> 48304 | M46: 60 | N46: 1000000 | O46: =(1+$U46)^(DATEDIF(acq,$K46,"y"))*$AE$19 -> 109272.7 | P46: =O46*(12-T46)/12 -> 100166.64 | Q46: =(1+$V46)^(DATEDIF(acq,$K46,"y"))*$AE$20 -> 47740.5 | R46: 200000 | S46: 1 | T46: 1 | U46: 0.03 | V46: 0.03 | W46: =(($O46+$Q46))/$J46 -> 318149.44 | X46: =IFERROR(((N46*$AE$8/12+$O46*($M46-$S46-($T46*M46/12))/$M46)+$Q46)/$J46-R46/M46,0) -> 297740.27 | Y46: =N46*H46/unit -> 418.98972 | Z46: 1 | AA46: 46477 | AB46: 0 | AC46: =R46*H46/unit -> 83.797945 | AD46: =O46*H46 -> 45784139 | AE46: =IFERROR(DATEDIF(exit,$L46,"m"),0) -> 26
C47: 7 | D47: Office | E47: 오케스트로 | F47: 1385.09 | G47: 683.57 | H47: =F47*py -> 418.98972 | I47: =G47*py -> 206.77993 | J47: =G47/F47 -> 0.49352028 | K47: =EOMONTH($AA47,$AB47) -> 46477 | L47: =EOMONTH($K47,$M47) -> 48304 | M47: 60 | N47: 1000000 | O47: =(1+$U47)^(DATEDIF(acq,$K47,"y"))*$AE$19 -> 109272.7 | P47: =O47*(12-T47)/12 -> 100166.64 | Q47: =(1+$V47)^(DATEDIF(acq,$K47,"y"))*$AE$20 -> 47740.5 | R47: 200000 | S47: 1 | T47: 1 | U47: 0.03 | V47: 0.03 | W47: =(($O47+$Q47))/$J47 -> 318149.44 | X47: =IFERROR(((N47*$AE$8/12+$O47*($M47-$S47-($T47*M47/12))/$M47)+$Q47)/$J47-R47/M47,0) -> 297740.27 | Y47: =N47*H47/unit -> 418.98972 | Z47: 1 | AA47: 46477 | AB47: 0 | AC47: =R47*H47/unit -> 83.797945 | AD47: =O47*H47 -> 45784139 | AE47: =IFERROR(DATEDIF(exit,$L47,"m"),0) -> 26
C48: 6 | D48: Office | E48: 오케스트로 | F48: 1385.09 | G48: 683.57 | H48: =F48*py -> 418.98972 | I48: =G48*py -> 206.77993 | J48: =G48/F48 -> 0.49352028 | K48: =EOMONTH($AA48,$AB48) -> 46477 | L48: =EOMONTH($K48,$M48) -> 48304 | M48: 60 | N48: =O48*10 -> 1092727 | O48: =(1+$U48)^(DATEDIF(acq,$K48,"y"))*$AE$19 -> 109272.7 | P48: =O48*(12-T48)/12 -> 100166.64 | Q48: =(1+$V48)^(DATEDIF(acq,$K48,"y"))*$AE$20 -> 47740.5 | R48: 200000 | S48: 1 | T48: 1 | U48: 0.03 | V48: 0.03 | W48: =(($O48+$Q48))/$J48 -> 318149.44 | X48: =IFERROR(((N48*$AE$8/12+$O48*($M48-$S48-($T48*M48/12))/$M48)+$Q48)/$J48-R48/M48,0) -> 298210 | Y48: =N48*H48/unit -> 457.84139 | Z48: 1 | AA48: 46477 | AB48: 0 | AC48: =R48*H48/unit -> 83.797945 | AD48: =O48*H48 -> 45784139 | AE48: =IFERROR(DATEDIF(exit,$L48,"m"),0) -> 26
C49: 5 | D49: Office | E49: 타이거로켓 | F49: 1385.09 | G49: 683.57 | H49: =F49*py -> 418.98972 | I49: =G49*py -> 206.77993 | J49: =G49/F49 -> 0.49352028 | K49: =EOMONTH($AA49,$AB49) -> 45688 | L49: =EOMONTH($K49,$M49) -> 47514 | M49: 60 | N49: =O49*10 -> 1030000 | O49: =(1+$U49)^(DATEDIF(acq,$K49,"y"))*$AE$19 -> 103000 | P49: =O49*(12-T49)/12 -> 90125 | Q49: =(1+$V49)^(DATEDIF(acq,$K49,"y"))*$AE$20 -> 45000 | R49: 0 | S49: 1 | T49: 1.5 | U49: 0.03 | V49: 0.03 | W49: =(($O49+$Q49))/$J49 -> 299886.36 | X49: =IFERROR(((N49*$AE$8/12+$O49*($M49-$S49-($T49*M49/12))/$M49)+$Q49)/$J49-R49/M49,0) -> 275537.48 | Y49: =N49*H49/unit -> 431.55942 | Z49: 1 | AA49: 45688 | AB49: 0 | AC49: =R49*H49/unit -> 0 | AD49: =O49*H49 -> 43155942 | AE49: =IFERROR(DATEDIF(exit,$L49,"m"),0) -> 0
C50: 4 | D50: Office | E50: 타이거로켓 | F50: 1385.09 | G50: 683.57 | H50: =F50*py -> 418.98972 | I50: =G50*py -> 206.77993 | J50: =G50/F50 -> 0.49352028 | K50: =EOMONTH($AA50,$AB50) -> 45688 | L50: =EOMONTH($K50,$M50) -> 47514 | M50: 60 | N50: =O50*10 -> 1030000 | O50: =(1+$U50)^(DATEDIF(acq,$K50,"y"))*$AE$19 -> 103000 | P50: =O50*(12-T50)/12 -> 90125 | Q50: =(1+$V50)^(DATEDIF(acq,$K50,"y"))*$AE$20 -> 45000 | R50: 0 | S50: 1 | T50: 1.5 | U50: 0.03 | V50: 0.03 | W50: =(($O50+$Q50))/$J50 -> 299886.36 | X50: =IFERROR(((N50*$AE$8/12+$O50*($M50-$S50-($T50*M50/12))/$M50)+$Q50)/$J50-R50/M50,0) -> 275537.48 | Y50: =N50*H50/unit -> 431.55942 | Z50: 1 | AA50: 45688 | AB50: 0 | AC50: =R50*H50/unit -> 0 | AD50: =O50*H50 -> 43155942 | AE50: =IFERROR(DATEDIF(exit,$L50,"m"),0) -> 0
C51: 3 | D51: Office | E51: 타이거로켓 | F51: 1385.09 | G51: 683.57 | H51: =F51*py -> 418.98972 | I51: =G51*py -> 206.77993 | J51: =G51/F51 -> 0.49352028 | K51: =EOMONTH($AA51,$AB51) -> 45688 | L51: =EOMONTH($K51,$M51) -> 47514 | M51: 60 | N51: =O51*10 -> 1030000 | O51: =(1+$U51)^(DATEDIF(acq,$K51,"y"))*$AE$19 -> 103000 | P51: =O51*(12-T51)/12 -> 90125 | Q51: =(1+$V51)^(DATEDIF(acq,$K51,"y"))*$AE$20 -> 45000 | R51: 0 | S51: 1 | T51: 1.5 | U51: 0.03 | V51: 0.03 | W51: =(($O51+$Q51))/$J51 -> 299886.36 | X51: =IFERROR(((N51*$AE$8/12+$O51*($M51-$S51-($T51*M51/12))/$M51)+$Q51)/$J51-R51/M51,0) -> 275537.48 | Y51: =N51*H51/unit -> 431.55942 | Z51: 1 | AA51: 45688 | AB51: 0 | AC51: =R51*H51/unit -> 0 | AD51: =O51*H51 -> 43155942 | AE51: =IFERROR(DATEDIF(exit,$L51,"m"),0) -> 0
B52: 2층 | C52: 201호 | D52: Retail | E52: RMW CARNE | F52: 346.2725 | G52: 170.8925 | H52: =F52*py -> 104.74743 | I52: =G52*py -> 51.694981 | J52: =G52/F52 -> 0.49352028 | K52: =EOMONTH($AA52,$AB52) -> 45747 | L52: =EOMONTH($K52,$M52) -> 47573 | M52: 60 | N52: =O52*10 -> 1300000 | O52: 130000 | P52: =O52*(12-T52)/12 -> 130000 | Q52: 45000 | R52: 0 | S52: 2 | T52: 0 | U52: 0.03 | V52: 0.03 | W52: =(($O52+$Q52))/$J52 -> 354595.36 | X52: =IFERROR(((N52*$AE$8/12+$O52*($M52-$S52-($T52*M52/12))/$M52)+$Q52)/$J52-R52/M52,0) -> 352400.25 | Y52: =N52*H52/unit -> 136.17166 | Z52: 1 | AA52: 45688 | AB52: 2 | AC52: =R52*H52/unit -> 0 | AD52: =O52*H52 -> 13617166 | AE52: =IFERROR(DATEDIF(exit,$L52,"m"),0) -> 2
C53: 202호 | D53: Retail | E53: 키이로 | F53: 346.2725 | G53: 170.8925 | H53: =F53*py -> 104.74743 | I53: =G53*py -> 51.694981 | J53: =G53/F53 -> 0.49352028 | K53: =EOMONTH($AA53,$AB53) -> 45747 | L53: =EOMONTH($K53,$M53) -> 47573 | M53: 60 | N53: =O53*10 -> 1300000 | O53: 130000 | P53: =O53*(12-T53)/12 -> 130000 | Q53: 45000 | R53: 0 | S53: 2 | T53: 0 | U53: 0.03 | V53: 0.03 | W53: =(($O53+$Q53))/$J53 -> 354595.36 | X53: =IFERROR(((N53*$AE$8/12+$O53*($M53-$S53-($T53*M53/12))/$M53)+$Q53)/$J53-R53/M53,0) -> 352400.25 | Y53: =N53*H53/unit -> 136.17166 | Z53: 1 | AA53: 45688 | AB53: 2 | AC53: =R53*H53/unit -> 0 | AD53: =O53*H53 -> 13617166 | AE53: =IFERROR(DATEDIF(exit,$L53,"m"),0) -> 2
C54: 203호 | D54: Retail | E54: 주 052 | F54: 346.2725 | G54: 170.8925 | H54: =F54*py -> 104.74743 | I54: =G54*py -> 51.694981 | J54: =G54/F54 -> 0.49352028 | K54: =EOMONTH($AA54,$AB54) -> 45747 | L54: =EOMONTH($K54,$M54) -> 47573 | M54: 60 | N54: =O54*10 -> 1300000 | O54: 130000 | P54: =O54*(12-T54)/12 -> 130000 | Q54: 45000 | R54: 0 | S54: 2 | T54: 0 | U54: 0.03 | V54: 0.03 | W54: =(($O54+$Q54))/$J54 -> 354595.36 | X54: =IFERROR(((N54*$AE$8/12+$O54*($M54-$S54-($T54*M54/12))/$M54)+$Q54)/$J54-R54/M54,0) -> 352400.25 | Y54: =N54*H54/unit -> 136.17166 | Z54: 1 | AA54: 45688 | AB54: 2 | AC54: =R54*H54/unit -> 0 | AD54: =O54*H54 -> 13617166 | AE54: =IFERROR(DATEDIF(exit,$L54,"m"),0) -> 2
C55: 204호 | D55: Retail | E55: 바이닐 청계 | F55: 346.2725 | G55: 170.8925 | H55: =F55*py -> 104.74743 | I55: =G55*py -> 51.694981 | J55: =G55/F55 -> 0.49352028 | K55: =EOMONTH($AA55,$AB55) -> 45747 | L55: =EOMONTH($K55,$M55) -> 47573 | M55: 60 | N55: =O55*10 -> 1300000 | O55: 130000 | P55: =O55*(12-T55)/12 -> 130000 | Q55: 45000 | R55: 0 | S55: 2 | T55: 0 | U55: 0.03 | V55: 0.03 | W55: =(($O55+$Q55))/$J55 -> 354595.36 | X55: =IFERROR(((N55*$AE$8/12+$O55*($M55-$S55-($T55*M55/12))/$M55)+$Q55)/$J55-R55/M55,0) -> 352400.25 | Y55: =N55*H55/unit -> 136.17166 | Z55: 1 | AA55: 45688 | AB55: 2 | AC55: =R55*H55/unit -> 0 | AD55: =O55*H55 -> 13617166 | AE55: =IFERROR(DATEDIF(exit,$L55,"m"),0) -> 2
B56: 1층 | C56: 101호 | D56: Retail | E56: 카페 1리터 | F56: 484.78 | G56: 205.07 | H56: =F56*py -> 146.64595 | I56: =G56*py -> 62.033675 | J56: =G56/F56 -> 0.42301663 | K56: =EOMONTH($AA56,$AB56) -> 45838 | L56: =EOMONTH($K56,$M56-1) -> 47634 | M56: 60 | N56: =O56*10 -> 1500000 | O56: 150000 | P56: =O56*(12-T56)/12 -> 150000 | Q56: 45000 | R56: 0 | S56: 1 | T56: 0 | U56: 0.03 | V56: 0.03 | W56: =(($O56+$Q56))/$J56 -> 460974.79 | X56: =IFERROR(((N56*$AE$8/12+$O56*($M56-$S56-($T56*M56/12))/$M56)+$Q56)/$J56-R56/M56,0) -> 463929.76 | Y56: =N56*H56/unit -> 219.96893 | Z56: 1 | AA56: 45717 | AB56: 3 | AC56: =R56*H56/unit -> 0 | AD56: =O56*H56 -> 21996892 | AE56: =IFERROR(DATEDIF(exit,$L56,"m"),0) -> 4
C57: 102호 | D57: Retail | E57: DOTZ | F57: 484.78 | G57: 205.07 | H57: =F57*py -> 146.64595 | I57: =G57*py -> 62.033675 | J57: =G57/F57 -> 0.42301663 | K57: =EOMONTH($AA57,$AB57) -> 45838 | L57: =EOMONTH($K57,$M57-1) -> 47634 | M57: 60 | N57: =O57*10 -> 1500000 | O57: 150000 | P57: =O57*(12-T57)/12 -> 150000 | Q57: 45000 | R57: 0 | S57: 1 | T57: 0 | U57: 0.03 | V57: 0.03 | W57: =(($O57+$Q57))/$J57 -> 460974.79 | X57: =IFERROR(((N57*$AE$8/12+$O57*($M57-$S57-($T57*M57/12))/$M57)+$Q57)/$J57-R57/M57,0) -> 463929.76 | Y57: =N57*H57/unit -> 219.96893 | Z57: 1 | AA57: 45717 | AB57: 3 | AC57: =R57*H57/unit -> 0 | AD57: =O57*H57 -> 21996892 | AE57: =IFERROR(DATEDIF(exit,$L57,"m"),0) -> 4
B58: B1층 | C58: B101호 | D58: Retail | E58: 편안창고 스토리지 | F58: 969.56 | G58: 410.14 | H58: =F58*py -> 293.2919 | I58: =G58*py -> 124.06735 | J58: =G58/F58 -> 0.42301663 | K58: =EOMONTH($AA58,$AB58) -> 46752 | L58: =EOMONTH($K58,$M58) -> 48579 | M58: 60 | N58: =O58*10 -> 521167.12 | O58: =O56*$AE$21*(1+$U58)^(DATEDIF(acq,$K58,"y")) -> 52116.712 | P58: =O58*(12-T58)/12 -> 52116.712 | Q58: 40000 | R58: 0 | S58: 1 | T58: 0 | U58: 0.03 | V58: 0.03 | W58: =(($O58+$Q58))/$J58 -> 217761.45 | X58: =IFERROR(((N58*$AE$8/12+$O58*($M58-$S58-($T58*M58/12))/$M58)+$Q58)/$J58-R58/M58,0) -> 218788.13 | Y58: =N58*H58/unit -> 152.8541 | Z58: 1 | AA58: 46752 | AB58: 0 | AC58: =R58*H58/unit -> 0 | AD58: =O58*H58 -> 15285410 | AE58: =IFERROR(DATEDIF(exit,$L58,"m"),0) -> 35
C59: B102호 | D59: Retail | E59: 스크린 퀀텀 | F59: 969.56 | G59: 410.14 | H59: =F59*py -> 293.2919 | I59: =G59*py -> 124.06735 | J59: =G59/F59 -> 0.42301663 | K59: =EOMONTH($AA59,$AB59) -> 46418 | L59: =EOMONTH($K59,$M59) -> 48244 | M59: 60 | N59: =O59*10 -> 521167.12 | O59: =O57*$AE$21*(1+$U59)^(DATEDIF(acq,$K59,"y")) -> 52116.712 | P59: =O59*(12-T59)/12 -> 52116.712 | Q59: 40000 | R59: 0 | S59: 1 | T59: 0 | U59: 0.03 | V59: 0.03 | W59: =(($O59+$Q59))/$J59 -> 217761.45 | X59: =IFERROR(((N59*$AE$8/12+$O59*($M59-$S59-($T59*M59/12))/$M59)+$Q59)/$J59-R59/M59,0) -> 218788.13 | Y59: =N59*H59/unit -> 152.8541 | Z59: 1 | AA59: 46418 | AB59: 0 | AC59: =R59*H59/unit -> 0 | AD59: =O59*H59 -> 15285410 | AE59: =IFERROR(DATEDIF(exit,$L59,"m"),0) -> 24
C60: 0 | D60: Retail | F60: 0 | G60: 0 | H60: =F60*py -> 0 | I60: =G60*py -> 0 | M60: 0 | N60: =O60*10 -> 0 | O60: 0 | P60: =O60*(12-T60)/12 -> 0 | Q60: 0 | R60: 0 | S60: 0 | T60: 0 | U60: 0 | V60: 0 | W60: 0 | X60: =IFERROR(((N60*$AE$8/12+$O60*($M60-$S60-($T60*M60/12))/$M60)+$Q60)/$J60-R60/M60,0) -> 0 | Y60: =N60*H60/unit -> 0 | Z60: 0 | AB60: 0 | AC60: =R60*H60/unit -> 0 | AD60: =O60*H60 -> 0 | AE60: =IFERROR(DATEDIF(exit,$L60,"m"),0) -> 0
C61: Office Total | F61: =SUMIF($D$37:$D$60,D37,F$37:F$60) -> 20776.35 | G61: =SUMIF($D$37:$D$60,D37,G$37:G$60) -> 10253.55 | H61: =SUMIF($D$37:$D$60,D37,H$37:H$60) -> 6284.8459 | I61: =SUMIF($D$37:$D$60,D37,I$37:I$60) -> 3101.6989 | J61: =G61/F61 -> 0.49352028 | W61: =AVERAGE(W37:W51) -> 314118.94 | X61: =AVERAGE(X37:X51) -> 296494.51 | Y61: =SUMIF($D$37:$D$60,D37,Y$37:Y$60) -> 6650.3276
C62: Retail Total | F62: =SUMIF($D$37:$D$60,$D$60,F$37:F$60) -> 4293.77 | G62: =SUMIF($D$37:$D$60,$D$60,G$37:G$60) -> 1913.99 | H62: =SUMIF($D$37:$D$60,$D$60,H$37:H$60) -> 1298.8654 | I62: =SUMIF($D$37:$D$60,$D$60,I$37:I$60) -> 578.98198 | J62: =G62/F62 -> 0.44575979 | Y62: =SUMIF($D$37:$D$60,D60,Y$37:Y$60) -> 1290.3327
C63: Total | F63: =SUM(F61:F62) -> 25070.12 | G63: =SUM(G61:G62) -> 12167.54 | H63: =SUM(H61:H62) -> 7583.7113 | I63: =SUM(I61:I62) -> 3680.6808 | J63: =G63/F63 -> 0.48534032 | Y63: =SUM(Y61:Y62) -> 7940.6603 | AC63: =SUM(AC37:AC60) -> 251.39383

Sheet Index
B2: Team LAVEL | S2: 변수입력 | T2: 합계1 | U2: 제목
B3: KBC타워 재무모델 | S3: 적정성확인 | T3: 합계2 | U3: 표제목
S4: 오류확인 | T4: 합계3 | U4: 작성자참고
A6: 단위: 백만원
A7: Index
R8: 구분 | S8: 1 | T8: 2 | U8: 3 | V8: 4 | W8: 5 | X8: 6 | Y8: 7 | Z8: 8 | AA8: 9 | AB8: 10 | AC8: 11 | AD8: 12 | AE8: 13 | AF8: 14 | AG8: 15 | AH8: 16
R9: 시작월 | S9: =start -> 45716 | T9: =EOMONTH(S10,1) -> 45900 | U9: =EOMONTH(T10,1) -> 46081 | V9: =EOMONTH(U10,1) -> 46265 | W9: =EOMONTH(V10,1) -> 46446 | X9: =EOMONTH(W10,1) -> 46630 | Y9: =EOMONTH(X10,1) -> 46812 | Z9: =EOMONTH(Y10,1) -> 46996 | AA9: =EOMONTH(Z10,1) -> 47177 | ... AH9: =EOMONTH(AG10,1) -> 48457
R10: 종료월 | S10: =EOMONTH(S9,period-1) -> 45869 | T10: =EOMONTH(T9,period-1) -> 46053 | U10: =EOMONTH(U9,period-1) -> 46234 | V10: =EOMONTH(V9,period-1) -> 46418 | W10: =EOMONTH(W9,period-1) -> 46599 | X10: =EOMONTH(X9,period-1) -> 46783 | Y10: =EOMONTH(Y9,period-1) -> 46965 | Z10: =EOMONTH(Z9,period-1) -> 47149 | ... AH10: =EOMONTH(AH9,period-1) -> 48610
P11: 운영기간Index | R11: =(R14>=[0]!start)*(R14<=[0]!exit)*1 -> 0 | S11: =(S14>=[0]!start)*(S14<=[0]!exit)*1 -> 1 | T11: =(T14>=[0]!start)*(T14<=[0]!exit)*1 -> 1 | U11: =(U14>=[0]!start)*(U14<=[0]!exit)*1 -> 1 | V11: =(V14>=[0]!start)*(V14<=[0]!exit)*1 -> 1 | W11: =(W14>=[0]!start)*(W14<=[0]!exit)*1 -> 1 | X11: =(X14>=[0]!start)*(X14<=[0]!exit)*1 -> 1 | Y11: =(Y14>=[0]!start)*(Y14<=[0]!exit)*1 -> 1 | ... DL11: =(DL14>=[0]!start)*(DL14<=[0]!exit)*1 -> 0
P12: 누적운영기간Index | R12: =SUM($R$11:R11)*R11 -> 0 | S12: =SUM($R$11:S11)*S11 -> 1 | T12: =SUM($R$11:T11)*T11 -> 2 | U12: =SUM($R$11:U11)*U11 -> 3 | V12: =SUM($R$11:V11)*V11 -> 4 | W12: =SUM($R$11:W11)*W11 -> 5 | X12: =SUM($R$11:X11)*X11 -> 6 | Y12: =SUM($R$11:Y11)*Y11 -> 7 | ... DL12: =SUM($R$11:DL11)*DL11 -> 0
P13: 12개월Index | R13: =(MOD(R12,12)=1)*1 -> 0 | S13: =(MOD(S12,12)=1)*1 -> 1 | T13: =(MOD(T12,12)=1)*1 -> 0 | U13: =(MOD(U12,12)=1)*1 -> 0 | V13: =(MOD(V12,12)=1)*1 -> 0 | W13: =(MOD(W12,12)=1)*1 -> 0 | X13: =(MOD(X12,12)=1)*1 -> 0 | Y13: =(MOD(Y12,12)=1)*1 -> 0 | ... DL13: =(MOD(DL12,12)=1)*1 -> 0
P14: Date | R14: =acq -> 45688 | S14: =EOMONTH(R14,1) -> 45716 | T14: =EOMONTH(S14,1) -> 45747 | U14: =EOMONTH(T14,1) -> 45777 | V14: =EOMONTH(U14,1) -> 45808 | W14: =EOMONTH(V14,1) -> 45838 | X14: =EOMONTH(W14,1) -> 45869 | Y14: =EOMONTH(X14,1) -> 45900 | Z14: =EOMONTH(Y14,1) -> 45930 | ... DL14: =EOMONTH(DK14,1) -> 48669
P15: 회계기간 | R15: =SUMIFS($S$8:$AH$8,$S$9:$AH$9,"<="&R$14,$S$10:$AH$10,">="&R$14) -> 0 | S15: =SUMIFS($S$8:$AH$8,$S$9:$AH$9,"<="&S$14,$S$10:$AH$10,">="&S$14) -> 1 | T15: =SUMIFS($S$8:$AH$8,$S$9:$AH$9,"<="&T$14,$S$10:$AH$10,">="&T$14) -> 1 | U15: =SUMIFS($S$8:$AH$8,$S$9:$AH$9,"<="&U$14,$S$10:$AH$10,">="&U$14) -> 1 | V15: =SUMIFS($S$8:$AH$8,$S$9:$AH$9,"<="&V$14,$S$10:$AH$10,">="&V$14) -> 1 | W15: =SUMIFS($S$8:$AH$8,$S$9:$AH$9,"<="&W$14,$S$10:$AH$10,">="&W$14) -> 1 | X15: =SUMIFS($S$8:$AH$8,$S$9:$AH$9,"<="&X$14,$S$10:$AH$10,">="&X$14) -> 1 | Y15: =SUMIFS($S$8:$AH$8,$S$9:$AH$9,"<="&Y$14,$S$10:$AH$10,">="&Y$14) -> 2 | ... DL15: =SUMIFS($S$8:$AH$8,$S$9:$AH$9,"<="&DL$14,$S$10:$AH$10,">="&DL$14) -> 0
P16: 운영년차 | R16: =SUM($R$13:R13)*R11 -> 0 | S16: =SUM($R$13:S13)*S11 -> 1 | T16: =SUM($R$13:T13)*T11 -> 1 | U16: =SUM($R$13:U13)*U11 -> 1 | V16: =SUM($R$13:V13)*V11 -> 1 | W16: =SUM($R$13:W13)*W11 -> 1 | X16: =SUM($R$13:X13)*X11 -> 1 | Y16: =SUM($R$13:Y13)*Y11 -> 1 | ... DL16: =SUM($R$13:DL13)*DL11 -> 0
B17: 현(위) 및 신규(아래) 임대차 계약 | O17: 계약기간 Index | R17: =SUM(R38,R18) -> 0 | S17: =SUM(S38,S18) -> 18 | T17: =SUM(T38,T18) -> 17 | U17: =SUM(U38,U18) -> 21 | V17: =SUM(V38,V18) -> 21 | W17: =SUM(W38,W18) -> 21 | X17: =SUM(X38,X18) -> 23 | Y17: =SUM(Y38,Y18) -> 23 | ... DL17: =SUM(DL38,DL18) -> 0
B18: 층수 | C18: 임차인 | D18: 시작일 | E18: 종료일 | F18: 기간 | G18: 명목 임대료(원) | H18: 실질 임대료(원) | I18: 관리비(원) | J18: 상승률 | K18: 임대면적(㎡) | L18: Fitout | M18: Rentfree | O18: 기존 임대차 | R18: =SUM(R19:R37) -> 0 | S18: =SUM(S19:S37) -> 15 | T18: =SUM(T19:T37) -> 14 | U18: =SUM(U19:U37) -> 14 | V18: =SUM(V19:V37) -> 14 | W18: =SUM(W19:W37) -> 14 | X18: =SUM(X19:X37) -> 14 | Y18: =SUM(Y19:Y37) -> 10 | ... DL18: =SUM(DL19:DL37) -> 0
B19: =Rentroll!$C$11 -> 17 | C19: =VLOOKUP($B19,Rentroll!$C$11:$X$29,3,FALSE) -> 리마 상사 | D19: =VLOOKUP($B19,Rentroll!$C$11:$X$29,9,FALSE) -> 45322 | E19: =VLOOKUP($B19,Rentroll!$C$11:$X$29,10,FALSE) -> 47148 | F19: =VLOOKUP($B19,Rentroll!$C$11:$X$29,11,FALSE) -> 60 | G19: =VLOOKUP($B19,Rentroll!$C$11:$X$29,13,FALSE) -> 100000 | H19: =VLOOKUP($B19,Rentroll!$C$11:$X$29,14,FALSE) -> 75000 | I19: =VLOOKUP($B19,Rentroll!$C$11:$X$29,15,FALSE) -> 45000 | J19: =VLOOKUP($B19,Rentroll!$C$11:$X$29,19,FALSE) -> 0.03 | K19: =VLOOKUP($B19,Rentroll!$C$11:$X$29,4,FALSE) -> 1385.09 | L19: =VLOOKUP($B19,Rentroll!$C$11:$X$29,17,FALSE) -> 0 | M19: =VLOOKUP($B19,Rentroll!$C$11:$X$29,18,FALSE) -> 3 | O19: =B19 -> 17 | R19: =IF(R$14<EOMONTH($E19,1),1,0)*R$11 -> 0 | S19: =IF(S$14<EOMONTH($E19,1),1,0)*S$11 -> 1 | T19: =IF(T$14<EOMONTH($E19,1),1,0)*T$11 -> 1 | U19: =IF(U$14<EOMONTH($E19,1),1,0)*U$11 -> 1 | V19: =IF(V$14<EOMONTH($E19,1),1,0)*V$11 -> 1 | W19: =IF(W$14<EOMONTH($E19,1),1,0)*W$11 -> 1 | X19: =IF(X$14<EOMONTH($E19,1),1,0)*X$11 -> 1 | Y19: =IF(Y$14<EOMONTH($E19,1),1,0)*Y$11 -> 1 | ... DL19: =IF(DL$14<EOMONTH($E19,1),1,0)*DL$11 -> 0
B20: =Rentroll!$C$12 -> 16 | C20: =VLOOKUP($B20,Rentroll!$C$11:$X$29,3,FALSE) -> 리마 상사 | D20: =VLOOKUP($B20,Rentroll!$C$11:$X$29,9,FALSE) -> 45322 | E20: =VLOOKUP($B20,Rentroll!$C$11:$X$29,10,FALSE) -> 47148 | F20: =VLOOKUP($B20,Rentroll!$C$11:$X$29,11,FALSE) -> 60 | G20: =VLOOKUP($B20,Rentroll!$C$11:$X$29,13,FALSE) -> 100000 | H20: =VLOOKUP($B20,Rentroll!$C$11:$X$29,14,FALSE) -> 75000 | I20: =VLOOKUP($B20,Rentroll!$C$11:$X$29,15,FALSE) -> 45000 | J20: =VLOOKUP($B20,Rentroll!$C$11:$X$29,19,FALSE) -> 0.03 | K20: =VLOOKUP($B20,Rentroll!$C$11:$X$29,4,FALSE) -> 1385.09 | L20: =VLOOKUP($B20,Rentroll!$C$11:$X$29,17,FALSE) -> 0 | M20: =VLOOKUP($B20,Rentroll!$C$11:$X$29,18,FALSE) -> 3 | O20: =B20 -> 16 | R20: =IF(R$14<EOMONTH($E20,1),1,0)*R$11 -> 0 | S20: =IF(S$14<EOMONTH($E20,1),1,0)*S$11 -> 1 | T20: =IF(T$14<EOMONTH($E20,1),1,0)*T$11 -> 1 | U20: =IF(U$14<EOMONTH($E20,1),1,0)*U$11 -> 1 | V20: =IF(V$14<EOMONTH($E20,1),1,0)*V$11 -> 1 | W20: =IF(W$14<EOMONTH($E20,1),1,0)*W$11 -> 1 | X20: =IF(X$14<EOMONTH($E20,1),1,0)*X$11 -> 1 | Y20: =IF(Y$14<EOMONTH($E20,1),1,0)*Y$11 -> 1 | ... DL20: =IF(DL$14<EOMONTH($E20,1),1,0)*DL$11 -> 0
B21: =Rentroll!$C$13 -> 15 | C21: =VLOOKUP($B21,Rentroll!$C$11:$X$29,3,FALSE) -> 모빌리티 테크놀로지 | D21: =VLOOKUP($B21,Rentroll!$C$11:$X$29,9,FALSE) -> 44042 | E21: =VLOOKUP($B21,Rentroll!$C$11:$X$29,10,FALSE) -> 45869 | F21: =VLOOKUP($B21,Rentroll!$C$11:$X$29,11,FALSE) -> 60 | G21: =VLOOKUP($B21,Rentroll!$C$11:$X$29,13,FALSE) -> 90041 | H21: =VLOOKUP($B21,Rentroll!$C$11:$X$29,14,FALSE) -> 67530.75 | I21: =VLOOKUP($B21,Rentroll!$C$11:$X$29,15,FALSE) -> 45020 | J21: =VLOOKUP($B21,Rentroll!$C$11:$X$29,19,FALSE) -> 0.03 | K21: =VLOOKUP($B21,Rentroll!$C$11:$X$29,4,FALSE) -> 1385.09 | L21: =VLOOKUP($B21,Rentroll!$C$11:$X$29,17,FALSE) -> 0 | M21: =VLOOKUP($B21,Rentroll!$C$11:$X$29,18,FALSE) -> 3 | O21: =B21 -> 15 | R21: =IF(R$14<EOMONTH($E21,1),1,0)*R$11 -> 0 | S21: =IF(S$14<EOMONTH($E21,1),1,0)*S$11 -> 1 | T21: =IF(T$14<EOMONTH($E21,1),1,0)*T$11 -> 1 | U21: =IF(U$14<EOMONTH($E21,1),1,0)*U$11 -> 1 | V21: =IF(V$14<EOMONTH($E21,1),1,0)*V$11 -> 1 | W21: =IF(W$14<EOMONTH($E21,1),1,0)*W$11 -> 1 | X21: =IF(X$14<EOMONTH($E21,1),1,0)*X$11 -> 1 | Y21: =IF(Y$14<EOMONTH($E21,1),1,0)*Y$11 -> 0 | ... DL21: =IF(DL$14<EOMONTH($E21,1),1,0)*DL$11 -> 0
B22: =Rentroll!$C$14 -> 14 | C22: =VLOOKUP($B22,Rentroll!$C$11:$X$29,3,FALSE) -> 모빌리티 테크놀로지 | D22: =VLOOKUP($B22,Rentroll!$C$11:$X$29,9,FALSE) -> 44043 | E22: =VLOOKUP($B22,Rentroll!$C$11:$X$29,10,FALSE) -> 45868 | F22: =VLOOKUP($B22,Rentroll!$C$11:$X$29,11,FALSE) -> 60 | G22: =VLOOKUP($B22,Rentroll!$C$11:$X$29,13,FALSE) -> 90041 | H22: =VLOOKUP($B22,Rentroll!$C$11:$X$29,14,FALSE) -> 67530.75 | I22: =VLOOKUP($B22,Rentroll!$C$11:$X$29,15,FALSE) -> 45020 | J22: =VLOOKUP($B22,Rentroll!$C$11:$X$29,19,FALSE) -> 0.03 | K22: =VLOOKUP($B22,Rentroll!$C$11:$X$29,4,FALSE) -> 1385.09 | L22: =VLOOKUP($B22,Rentroll!$C$11:$X$29,17,FALSE) -> 0 | M22: =VLOOKUP($B22,Rentroll!$C$11:$X$29,18,FALSE) -> 3 | O22: =B22 -> 14 | R22: =IF(R$14<EOMONTH($E22,1),1,0)*R$11 -> 0 | S22: =IF(S$14<EOMONTH($E22,1),1,0)*S$11 -> 1 | T22: =IF(T$14<EOMONTH($E22,1),1,0)*T$11 -> 1 | U22: =IF(U$14<EOMONTH($E22,1),1,0)*U$11 -> 1 | V22: =IF(V$14<EOMONTH($E22,1),1,0)*V$11 -> 1 | W22: =IF(W$14<EOMONTH($E22,1),1,0)*W$11 -> 1 | X22: =IF(X$14<EOMONTH($E22,1),1,0)*X$11 -> 1 | Y22: =IF(Y$14<EOMONTH($E22,1),1,0)*Y$11 -> 0 | ... DL22: =IF(DL$14<EOMONTH($E22,1),1,0)*DL$11 -> 0
B23: =Rentroll!$C$15 -> 13 | C23: =VLOOKUP($B23,Rentroll!$C$11:$X$29,3,FALSE) -> 모빌리티 테크놀로지 | D23: =VLOOKUP($B23,Rentroll!$C$11:$X$29,9,FALSE) -> 44043 | E23: =VLOOKUP($B23,Rentroll!$C$11:$X$29,10,FALSE) -> 45868 | F23: =VLOOKUP($B23,Rentroll!$C$11:$X$29,11,FALSE) -> 60 | G23: =VLOOKUP($B23,Rentroll!$C$11:$X$29,13,FALSE) -> 90041 | H23: =VLOOKUP($B23,Rentroll!$C$11:$X$29,14,FALSE) -> 67530.75 | I23: =VLOOKUP($B23,Rentroll!$C$11:$X$29,15,FALSE) -> 45020 | J23: =VLOOKUP($B23,Rentroll!$C$11:$X$29,19,FALSE) -> 0.03 | K23: =VLOOKUP($B23,Rentroll!$C$11:$X$29,4,FALSE) -> 1385.09 | L23: =VLOOKUP($B23,Rentroll!$C$11:$X$29,17,FALSE) -> 0 | M23: =VLOOKUP($B23,Rentroll!$C$11:$X$29,18,FALSE) -> 3 | O23: =B23 -> 13 | R23: =IF(R$14<EOMONTH($E23,1),1,0)*R$11 -> 0 | S23: =IF(S$14<EOMONTH($E23,1),1,0)*S$11 -> 1 | T23: =IF(T$14<EOMONTH($E23,1),1,0)*T$11 -> 1 | U23: =IF(U$14<EOMONTH($E23,1),1,0)*U$11 -> 1 | V23: =IF(V$14<EOMONTH($E23,1),1,0)*V$11 -> 1 | W23: =IF(W$14<EOMONTH($E23,1),1,0)*W$11 -> 1 | X23: =IF(X$14<EOMONTH($E23,1),1,0)*X$11 -> 1 | Y23: =IF(Y$14<EOMONTH($E23,1),1,0)*Y$11 -> 0 | ... DL23: =IF(DL$14<EOMONTH($E23,1),1,0)*DL$11 -> 0
B24: =Rentroll!$C$16 -> 12 | C24: =VLOOKUP($B24,Rentroll!$C$11:$X$29,3,FALSE) -> 모빌리티 테크놀로지 | D24: =VLOOKUP($B24,Rentroll!$C$11:$X$29,9,FALSE) -> 44043 | E24: =VLOOKUP($B24,Rentroll!$C$11:$X$29,10,FALSE) -> 45868 | F24: =VLOOKUP($B24,Rentroll!$C$11:$X$29,11,FALSE) -> 60 | G24: =VLOOKUP($B24,Rentroll!$C$11:$X$29,13,FALSE) -> 90041 | H24: =VLOOKUP($B24,Rentroll!$C$11:$X$29,14,FALSE) -> 67530.75 | I24: =VLOOKUP($B24,Rentroll!$C$11:$X$29,15,FALSE) -> 45020 | J24: =VLOOKUP($B24,Rentroll!$C$11:$X$29,19,FALSE) -> 0.03 | K24: =VLOOKUP($B24,Rentroll!$C$11:$X$29,4,FALSE) -> 1385.09 | L24: =VLOOKUP($B24,Rentroll!$C$11:$X$29,17,FALSE) -> 0 | M24: =VLOOKUP($B24,Rentroll!$C$11:$X$29,18,FALSE) -> 3 | O24: =B24 -> 12 | R24: =IF(R$14<EOMONTH($E24,1),1,0)*R$11 -> 0 | S24: =IF(S$14<EOMONTH($E24,1),1,0)*S$11 -> 1 | T24: =IF(T$14<EOMONTH($E24,1),1,0)*T$11 -> 1 | U24: =IF(U$14<EOMONTH($E24,1),1,0)*U$11 -> 1 | V24: =IF(V$14<EOMONTH($E24,1),1,0)*V$11 -> 1 | W24: =IF(W$14<EOMONTH($E24,1),1,0)*W$11 -> 1 | X24: =IF(X$14<EOMONTH($E24,1),1,0)*X$11 -> 1 | Y24: =IF(Y$14<EOMONTH($E24,1),1,0)*Y$11 -> 0 | ... DL24: =IF(DL$14<EOMONTH($E24,1),1,0)*DL$11 -> 0
B25: =Rentroll!$C$17 -> 11 | C25: =VLOOKUP($B25,Rentroll!$C$11:$X$29,3,FALSE) -> 노벰버 건설 | D25: =VLOOKUP($B25,Rentroll!$C$11:$X$29,9,FALSE) -> 45077 | E25: =VLOOKUP($B25,Rentroll!$C$11:$X$29,10,FALSE) -> 46903 | F25: =VLOOKUP($B25,Rentroll!$C$11:$X$29,11,FALSE) -> 60 | G25: =VLOOKUP($B25,Rentroll!$C$11:$X$29,13,FALSE) -> 103000 | H25: =VLOOKUP($B25,Rentroll!$C$11:$X$29,14,FALSE) -> 85833.333 | I25: =VLOOKUP($B25,Rentroll!$C$11:$X$29,15,FALSE) -> 46350 | J25: =VLOOKUP($B25,Rentroll!$C$11:$X$29,19,FALSE) -> 0.03 | K25: =VLOOKUP($B25,Rentroll!$C$11:$X$29,4,FALSE) -> 1385.09 | L25: =VLOOKUP($B25,Rentroll!$C$11:$X$29,17,FALSE) -> 0 | M25: =VLOOKUP($B25,Rentroll!$C$11:$X$29,18,FALSE) -> 2 | O25: =B25 -> 11 | R25: =IF(R$14<EOMONTH($E25,1),1,0)*R$11 -> 0 | S25: =IF(S$14<EOMONTH($E25,1),1,0)*S$11 -> 1 | T25: =IF(T$14<EOMONTH($E25,1),1,0)*T$11 -> 1 | U25: =IF(U$14<EOMONTH($E25,1),1,0)*U$11 -> 1 | V25: =IF(V$14<EOMONTH($E25,1),1,0)*V$11 -> 1 | W25: =IF(W$14<EOMONTH($E25,1),1,0)*W$11 -> 1 | X25: =IF(X$14<EOMONTH($E25,1),1,0)*X$11 -> 1 | Y25: =IF(Y$14<EOMONTH($E25,1),1,0)*Y$11 -> 1 | ... DL25: =IF(DL$14<EOMONTH($E25,1),1,0)*DL$11 -> 0
B26: =Rentroll!$C$18 -> 10 | C26: =VLOOKUP($B26,Rentroll!$C$11:$X$29,3,FALSE) -> 노벰버 건설 | D26: =VLOOKUP($B26,Rentroll!$C$11:$X$29,9,FALSE) -> 45077 | E26: =VLOOKUP($B26,Rentroll!$C$11:$X$29,10,FALSE) -> 46903 | F26: =VLOOKUP($B26,Rentroll!$C$11:$X$29,11,FALSE) -> 60 | G26: =VLOOKUP($B26,Rentroll!$C$11:$X$29,13,FALSE) -> 103000 | H26: =VLOOKUP($B26,Rentroll!$C$11:$X$29,14,FALSE) -> 85833.333 | I26: =VLOOKUP($B26,Rentroll!$C$11:$X$29,15,FALSE) -> 46350 | J26: =VLOOKUP($B26,Rentroll!$C$11:$X$29,19,FALSE) -> 0.03 | K26: =VLOOKUP($B26,Rentroll!$C$11:$X$29,4,FALSE) -> 1385.09 | L26: =VLOOKUP($B26,Rentroll!$C$11:$X$29,17,FALSE) -> 0 | M26: =VLOOKUP($B26,Rentroll!$C$11:$X$29,18,FALSE) -> 2 | O26: =B26 -> 10 | R26: =IF(R$14<EOMONTH($E26,1),1,0)*R$11 -> 0 | S26: =IF(S$14<EOMONTH($E26,1),1,0)*S$11 -> 1 | T26: =IF(T$14<EOMONTH($E26,1),1,0)*T$11 -> 1 | U26: =IF(U$14<EOMONTH($E26,1),1,0)*U$11 -> 1 | V26: =IF(V$14<EOMONTH($E26,1),1,0)*V$11 -> 1 | W26: =IF(W$14<EOMONTH($E26,1),1,0)*W$11 -> 1 | X26: =IF(X$14<EOMONTH($E26,1),1,0)*X$11 -> 1 | Y26: =IF(Y$14<EOMONTH($E26,1),1,0)*Y$11 -> 1 | ... DL26: =IF(DL$14<EOMONTH($E26,1),1,0)*DL$11 -> 0
B27: =Rentroll!$C$19 -> 9 | C27: =VLOOKUP($B27,Rentroll!$C$11:$X$29,3,FALSE) -> 노벰버 건설 | D27: =VLOOKUP($B27,Rentroll!$C$11:$X$29,9,FALSE) -> 45077 | E27: =VLOOKUP($B27,Rentroll!$C$11:$X$29,10,FALSE) -> 46903 | F27: =VLOOKUP($B27,Rentroll!$C$11:$X$29,11,FALSE) -> 60 | G27: =VLOOKUP($B27,Rentroll!$C$11:$X$29,13,FALSE) -> 103000 | H27: =VLOOKUP($B27,Rentroll!$C$11:$X$29,14,FALSE) -> 85833.333 | I27: =VLOOKUP($B27,Rentroll!$C$11:$X$29,15,FALSE) -> 46350 | J27: =VLOOKUP($B27,Rentroll!$C$11:$X$29,19,FALSE) -> 0.03 | K27: =VLOOKUP($B27,Rentroll!$C$11:$X$29,4,FALSE) -> 1385.09 | L27: =VLOOKUP($B27,Rentroll!$C$11:$X$29,17,FALSE) -> 0 | M27: =VLOOKUP($B27,Rentroll!$C$11:$X$29,18,FALSE) -> 2 | O27: =B27 -> 9 | R27: =IF(R$14<EOMONTH($E27,1),1,0)*R$11 -> 0 | S27: =IF(S$14<EOMONTH($E27,1),1,0)*S$11 -> 1 | T27: =IF(T$14<EOMONTH($E27,1),1,0)*T$11 -> 1 | U27: =IF(U$14<EOMONTH($E27,1),1,0)*U$11 -> 1 | V27: =IF(V$14<EOMONTH($E27,1),1,0)*V$11 -> 1 | W27: =IF(W$14<EOMONTH($E27,1),1,0)*W$11 -> 1 | X27: =IF(X$14<EOMONTH($E27,1),1,0)*X$11 -> 1 | Y27: =IF(Y$14<EOMONTH($E27,1),1,0)*Y$11 -> 1 | ... DL27: =IF(DL$14<EOMONTH($E27,1),1,0)*DL$11 -> 0
B28: =Rentroll!$C$20 -> 8 | C28: =VLOOKUP($B28,Rentroll!$C$11:$X$29,3,FALSE) -> 오토 커머셜 | D28: =VLOOKUP($B28,Rentroll!$C$11:$X$29,9,FALSE) -> 44651 | E28: =VLOOKUP($B28,Rentroll!$C$11:$X$29,10,FALSE) -> 46476 | F28: =VLOOKUP($B28,Rentroll!$C$11:$X$29,11,FALSE) -> 60 | G28: =VLOOKUP($B28,Rentroll!$C$11:$X$29,13,FALSE) -> 95481 | H28: =VLOOKUP($B28,Rentroll!$C$11:$X$29,14,FALSE) -> 87524.25 | I28: =VLOOKUP($B28,Rentroll!$C$11:$X$29,15,FALSE) -> 42436 | J28: =VLOOKUP($B28,Rentroll!$C$11:$X$29,19,FALSE) -> 0.03 | K28: =VLOOKUP($B28,Rentroll!$C$11:$X$29,4,FALSE) -> 1385.09 | L28: =VLOOKUP($B28,Rentroll!$C$11:$X$29,17,FALSE) -> 0 | M28: =VLOOKUP($B28,Rentroll!$C$11:$X$29,18,FALSE) -> 1 | O28: =B28 -> 8 | R28: =IF(R$14<EOMONTH($E28,1),1,0)*R$11 -> 0 | S28: =IF(S$14<EOMONTH($E28,1),1,0)*S$11 -> 1 | T28: =IF(T$14<EOMONTH($E28,1),1,0)*T$11 -> 1 | U28: =IF(U$14<EOMONTH($E28,1),1,0)*U$11 -> 1 | V28: =IF(V$14<EOMONTH($E28,1),1,0)*V$11 -> 1 | W28: =IF(W$14<EOMONTH($E28,1),1,0)*W$11 -> 1 | X28: =IF(X$14<EOMONTH($E28,1),1,0)*X$11 -> 1 | Y28: =IF(Y$14<EOMONTH($E28,1),1,0)*Y$11 -> 1 | ... DL28: =IF(DL$14<EOMONTH($E28,1),1,0)*DL$11 -> 0
B29: =Rentroll!$C$21 -> 7 | C29: =VLOOKUP($B29,Rentroll!$C$11:$X$29,3,FALSE) -> 오토 커머셜 | D29: =VLOOKUP($B29,Rentroll!$C$11:$X$29,9,FALSE) -> 44651 | E29: =VLOOKUP($B29,Rentroll!$C$11:$X$29,10,FALSE) -> 46476 | F29: =VLOOKUP($B29,Rentroll!$C$11:$X$29,11,FALSE) -> 60 | G29: =VLOOKUP($B29,Rentroll!$C$11:$X$29,13,FALSE) -> 95481 | H29: =VLOOKUP($B29,Rentroll!$C$11:$X$29,14,FALSE) -> 87524.25 | I29: =VLOOKUP($B29,Rentroll!$C$11:$X$29,15,FALSE) -> 42436 | J29: =VLOOKUP($B29,Rentroll!$C$11:$X$29,19,FALSE) -> 0.03 | K29: =VLOOKUP($B29,Rentroll!$C$11:$X$29,4,FALSE) -> 1385.09 | L29: =VLOOKUP($B29,Rentroll!$C$11:$X$29,17,FALSE) -> 0 | M29: =VLOOKUP($B29,Rentroll!$C$11:$X$29,18,FALSE) -> 1 | O29: =B29 -> 7 | R29: =IF(R$14<EOMONTH($E29,1),1,0)*R$11 -> 0 | S29: =IF(S$14<EOMONTH($E29,1),1,0)*S$11 -> 1 | T29: =IF(T$14<EOMONTH($E29,1),1,0)*T$11 -> 1 | U29: =IF(U$14<EOMONTH($E29,1),1,0)*U$11 -> 1 | V29: =IF(V$14<EOMONTH($E29,1),1,0)*V$11 -> 1 | W29: =IF(W$14<EOMONTH($E29,1),1,0)*W$11 -> 1 | X29: =IF(X$14<EOMONTH($E29,1),1,0)*X$11 -> 1 | Y29: =IF(Y$14<EOMONTH($E29,1),1,0)*Y$11 -> 1 | ... DL29: =IF(DL$14<EOMONTH($E29,1),1,0)*DL$11 -> 0
B30: =Rentroll!$C$22 -> 6 | C30: =VLOOKUP($B30,Rentroll!$C$11:$X$29,3,FALSE) -> 오토 커머셜 | D30: =VLOOKUP($B30,Rentroll!$C$11:$X$29,9,FALSE) -> 44651 | E30: =VLOOKUP($B30,Rentroll!$C$11:$X$29,10,FALSE) -> 46476 | F30: =VLOOKUP($B30,Rentroll!$C$11:$X$29,11,FALSE) -> 60 | G30: =VLOOKUP($B30,Rentroll!$C$11:$X$29,13,FALSE) -> 95481 | H30: =VLOOKUP($B30,Rentroll!$C$11:$X$29,14,FALSE) -> 87524.25 | I30: =VLOOKUP($B30,Rentroll!$C$11:$X$29,15,FALSE) -> 42436 | J30: =VLOOKUP($B30,Rentroll!$C$11:$X$29,19,FALSE) -> 0.03 | K30: =VLOOKUP($B30,Rentroll!$C$11:$X$29,4,FALSE) -> 1385.09 | L30: =VLOOKUP($B30,Rentroll!$C$11:$X$29,17,FALSE) -> 0 | M30: =VLOOKUP($B30,Rentroll!$C$11:$X$29,18,FALSE) -> 1 | O30: =B30 -> 6 | R30: =IF(R$14<EOMONTH($E30,1),1,0)*R$11 -> 0 | S30: =IF(S$14<EOMONTH($E30,1),1,0)*S$11 -> 1 | T30: =IF(T$14<EOMONTH($E30,1),1,0)*T$11 -> 1 | U30: =IF(U$14<EOMONTH($E30,1),1,0)*U$11 -> 1 | V30: =IF(V$14<EOMONTH($E30,1),1,0)*V$11 -> 1 | W30: =IF(W$14<EOMONTH($E30,1),1,0)*W$11 -> 1 | X30: =IF(X$14<EOMONTH($E30,1),1,0)*X$11 -> 1 | Y30: =IF(Y$14<EOMONTH($E30,1),1,0)*Y$11 -> 1 | ... DL30: =IF(DL$14<EOMONTH($E30,1),1,0)*DL$11 -> 0
B31: =Rentroll!$C$23 -> 5 | C31: =VLOOKUP($B31,Rentroll!$C$11:$X$29,3,FALSE) -> 공실 | F31: =VLOOKUP($B31,Rentroll!$C$11:$X$29,11,FALSE) -> 0 | G31: =VLOOKUP($B31,Rentroll!$C$11:$X$29,13,FALSE) -> 0 | H31: =VLOOKUP($B31,Rentroll!$C$11:$X$29,14,FALSE) -> 0 | I31: =VLOOKUP($B31,Rentroll!$C$11:$X$29,15,FALSE) -> 0 | J31: =VLOOKUP($B31,Rentroll!$C$11:$X$29,19,FALSE) -> 0 | K31: =VLOOKUP($B31,Rentroll!$C$11:$X$29,4,FALSE) -> 1385.09 | L31: =VLOOKUP($B31,Rentroll!$C$11:$X$29,17,FALSE) -> 0 | M31: =VLOOKUP($B31,Rentroll!$C$11:$X$29,18,FALSE) -> 0 | O31: =B31 -> 5 | R31: =IF(R$14<EOMONTH($E31,1),1,0)*R$11 -> 0 | S31: =IF(S$14<EOMONTH($E31,1),1,0)*S$11 -> 0 | T31: =IF(T$14<EOMONTH($E31,1),1,0)*T$11 -> 0 | U31: =IF(U$14<EOMONTH($E31,1),1,0)*U$11 -> 0 | V31: =IF(V$14<EOMONTH($E31,1),1,0)*V$11 -> 0 | W31: =IF(W$14<EOMONTH($E31,1),1,0)*W$11 -> 0 | X31: =IF(X$14<EOMONTH($E31,1),1,0)*X$11 -> 0 | Y31: =IF(Y$14<EOMONTH($E31,1),1,0)*Y$11 -> 0 | ... DL31: =IF(DL$14<EOMONTH($E31,1),1,0)*DL$11 -> 0
B32: =Rentroll!$C$24 -> 4 | C32: =VLOOKUP($B32,Rentroll!$C$11:$X$29,3,FALSE) -> 공실 | F32: =VLOOKUP($B32,Rentroll!$C$11:$X$29,11,FALSE) -> 0 | G32: =VLOOKUP($B32,Rentroll!$C$11:$X$29,13,FALSE) -> 0 | H32: =VLOOKUP($B32,Rentroll!$C$11:$X$29,14,FALSE) -> 0 | I32: =VLOOKUP($B32,Rentroll!$C$11:$X$29,15,FALSE) -> 0 | J32: =VLOOKUP($B32,Rentroll!$C$11:$X$29,19,FALSE) -> 0 | K32: =VLOOKUP($B32,Rentroll!$C$11:$X$29,4,FALSE) -> 1385.09 | L32: =VLOOKUP($B32,Rentroll!$C$11:$X$29,17,FALSE) -> 0 | M32: =VLOOKUP($B32,Rentroll!$C$11:$X$29,18,FALSE) -> 0 | O32: =B32 -> 4 | R32: =IF(R$14<EOMONTH($E32,1),1,0)*R$11 -> 0 | S32: =IF(S$14<EOMONTH($E32,1),1,0)*S$11 -> 0 | T32: =IF(T$14<EOMONTH($E32,1),1,0)*T$11 -> 0 | U32: =IF(U$14<EOMONTH($E32,1),1,0)*U$11 -> 0 | V32: =IF(V$14<EOMONTH($E32,1),1,0)*V$11 -> 0 | W32: =IF(W$14<EOMONTH($E32,1),1,0)*W$11 -> 0 | X32: =IF(X$14<EOMONTH($E32,1),1,0)*X$11 -> 0 | Y32: =IF(Y$14<EOMONTH($E32,1),1,0)*Y$11 -> 0 | ... DL32: =IF(DL$14<EOMONTH($E32,1),1,0)*DL$11 -> 0
B33: =Rentroll!$C$25 -> 3 | C33: =VLOOKUP($B33,Rentroll!$C$11:$X$29,3,FALSE) -> 공실 | F33: =VLOOKUP($B33,Rentroll!$C$11:$X$29,11,FALSE) -> 0 | G33: =VLOOKUP($B33,Rentroll!$C$11:$X$29,13,FALSE) -> 0 | H33: =VLOOKUP($B33,Rentroll!$C$11:$X$29,14,FALSE) -> 0 | I33: =VLOOKUP($B33,Rentroll!$C$11:$X$29,15,FALSE) -> 0 | J33: =VLOOKUP($B33,Rentroll!$C$11:$X$29,19,FALSE) -> 0 | K33: =VLOOKUP($B33,Rentroll!$C$11:$X$29,4,FALSE) -> 1385.09 | L33: =VLOOKUP($B33,Rentroll!$C$11:$X$29,17,FALSE) -> 0 | M33: =VLOOKUP($B33,Rentroll!$C$11:$X$29,18,FALSE) -> 0 | O33: =B33 -> 3 | R33: =IF(R$14<EOMONTH($E33,1),1,0)*R$11 -> 0 | S33: =IF(S$14<EOMONTH($E33,1),1,0)*S$11 -> 0 | T33: =IF(T$14<EOMONTH($E33,1),1,0)*T$11 -> 0 | U33: =IF(U$14<EOMONTH($E33,1),1,0)*U$11 -> 0 | V33: =IF(V$14<EOMONTH($E33,1),1,0)*V$11 -> 0 | W33: =IF(W$14<EOMONTH($E33,1),1,0)*W$11 -> 0 | X33: =IF(X$14<EOMONTH($E33,1),1,0)*X$11 -> 0 | Y33: =IF(Y$14<EOMONTH($E33,1),1,0)*Y$11 -> 0 | ... DL33: =IF(DL$14<EOMONTH($E33,1),1,0)*DL$11 -> 0
B34: =Rentroll!$C$26 -> 2 | C34: =VLOOKUP($B34,Rentroll!$C$11:$X$29,3,FALSE) -> 공실 | F34: =VLOOKUP($B34,Rentroll!$C$11:$X$29,11,FALSE) -> 0 | G34: =VLOOKUP($B34,Rentroll!$C$11:$X$29,13,FALSE) -> 0 | H34: =VLOOKUP($B34,Rentroll!$C$11:$X$29,14,FALSE) -> 0 | I34: =VLOOKUP($B34,Rentroll!$C$11:$X$29,15,FALSE) -> 0 | J34: =VLOOKUP($B34,Rentroll!$C$11:$X$29,19,FALSE) -> 0 | K34: =VLOOKUP($B34,Rentroll!$C$11:$X$29,4,FALSE) -> 1385.09 | L34: =VLOOKUP($B34,Rentroll!$C$11:$X$29,17,FALSE) -> 0 | M34: =VLOOKUP($B34,Rentroll!$C$11:$X$29,18,FALSE) -> 0 | O34: =B34 -> 2 | R34: =IF(R$14<EOMONTH($E34,1),1,0)*R$11 -> 0 | S34: =IF(S$14<EOMONTH($E34,1),1,0)*S$11 -> 0 | T34: =IF(T$14<EOMONTH($E34,1),1,0)*T$11 -> 0 | U34: =IF(U$14<EOMONTH($E34,1),1,0)*U$11 -> 0 | V34: =IF(V$14<EOMONTH($E34,1),1,0)*V$11 -> 0 | W34: =IF(W$14<EOMONTH($E34,1),1,0)*W$11 -> 0 | X34: =IF(X$14<EOMONTH($E34,1),1,0)*X$11 -> 0 | Y34: =IF(Y$14<EOMONTH($E34,1),1,0)*Y$11 -> 0 | ... DL34: =IF(DL$14<EOMONTH($E34,1),1,0)*DL$11 -> 0
B35: =Rentroll!$C$27 -> 1 | C35: =VLOOKUP($B35,Rentroll!$C$11:$X$29,3,FALSE) -> 파파 커피앤도넛 | D35: =VLOOKUP($B35,Rentroll!$C$11:$X$29,9,FALSE) -> 42064 | E35: =VLOOKUP($B35,Rentroll!$C$11:$X$29,10,FALSE) -> 45716 | F35: =VLOOKUP($B35,Rentroll!$C$11:$X$29,11,FALSE) -> 120 | G35: =VLOOKUP($B35,Rentroll!$C$11:$X$29,13,FALSE) -> 91334 | H35: =VLOOKUP($B35,Rentroll!$C$11:$X$29,14,FALSE) -> 83722.833 | I35: =VLOOKUP($B35,Rentroll!$C$11:$X$29,15,FALSE) -> 39143 | J35: =VLOOKUP($B35,Rentroll!$C$11:$X$29,19,FALSE) -> 0.03 | K35: =VLOOKUP($B35,Rentroll!$C$11:$X$29,4,FALSE) -> 969.56 | L35: =VLOOKUP($B35,Rentroll!$C$11:$X$29,17,FALSE) -> 0 | M35: =VLOOKUP($B35,Rentroll!$C$11:$X$29,18,FALSE) -> 1 | O35: =B35 -> 1 | R35: =IF(R$14<EOMONTH($E35,1),1,0)*R$11 -> 0 | S35: =IF(S$14<EOMONTH($E35,1),1,0)*S$11 -> 1 | T35: =IF(T$14<EOMONTH($E35,1),1,0)*T$11 -> 0 | U35: =IF(U$14<EOMONTH($E35,1),1,0)*U$11 -> 0 | V35: =IF(V$14<EOMONTH($E35,1),1,0)*V$11 -> 0 | W35: =IF(W$14<EOMONTH($E35,1),1,0)*W$11 -> 0 | X35: =IF(X$14<EOMONTH($E35,1),1,0)*X$11 -> 0 | Y35: =IF(Y$14<EOMONTH($E35,1),1,0)*Y$11 -> 0 | ... DL35: =IF(DL$14<EOMONTH($E35,1),1,0)*DL$11 -> 0
B36: =Rentroll!$C$28 -> B101호 | C36: =VLOOKUP($B36,Rentroll!$C$11:$X$29,3,FALSE) -> 퀸즈 샌드위치 | D36: =VLOOKUP($B36,Rentroll!$C$11:$X$29,9,FALSE) -> 44926 | E36: =VLOOKUP($B36,Rentroll!$C$11:$X$29,10,FALSE) -> 46751 | F36: =VLOOKUP($B36,Rentroll!$C$11:$X$29,11,FALSE) -> 60 | G36: =VLOOKUP($B36,Rentroll!$C$11:$X$29,13,FALSE) -> 21218 | H36: =VLOOKUP($B36,Rentroll!$C$11:$X$29,14,FALSE) -> 17681.667 | I36: =VLOOKUP($B36,Rentroll!$C$11:$X$29,15,FALSE) -> 31827 | J36: =VLOOKUP($B36,Rentroll!$C$11:$X$29,19,FALSE) -> 0.03 | K36: =VLOOKUP($B36,Rentroll!$C$11:$X$29,4,FALSE) -> 969.56 | L36: =VLOOKUP($B36,Rentroll!$C$11:$X$29,17,FALSE) -> 0 | M36: =VLOOKUP($B36,Rentroll!$C$11:$X$29,18,FALSE) -> 2 | O36: =B36 -> B101호 | R36: =IF(R$14<EOMONTH($E36,1),1,0)*R$11 -> 0 | S36: =IF(S$14<EOMONTH($E36,1),1,0)*S$11 -> 1 | T36: =IF(T$14<EOMONTH($E36,1),1,0)*T$11 -> 1 | U36: =IF(U$14<EOMONTH($E36,1),1,0)*U$11 -> 1 | V36: =IF(V$14<EOMONTH($E36,1),1,0)*V$11 -> 1 | W36: =IF(W$14<EOMONTH($E36,1),1,0)*W$11 -> 1 | X36: =IF(X$14<EOMONTH($E36,1),1,0)*X$11 -> 1 | Y36: =IF(Y$14<EOMONTH($E36,1),1,0)*Y$11 -> 1 | ... DL36: =IF(DL$14<EOMONTH($E36,1),1,0)*DL$11 -> 0
B37: =Rentroll!$C$29 -> B102호 | C37: =VLOOKUP($B37,Rentroll!$C$11:$X$29,3,FALSE) -> 로미오 문구점 | D37: =VLOOKUP($B37,Rentroll!$C$11:$X$29,9,FALSE) -> 44592 | E37: =VLOOKUP($B37,Rentroll!$C$11:$X$29,10,FALSE) -> 46417 | F37: =VLOOKUP($B37,Rentroll!$C$11:$X$29,11,FALSE) -> 60 | G37: =VLOOKUP($B37,Rentroll!$C$11:$X$29,13,FALSE) -> 31827 | H37: =VLOOKUP($B37,Rentroll!$C$11:$X$29,14,FALSE) -> 23870.25 | I37: =VLOOKUP($B37,Rentroll!$C$11:$X$29,15,FALSE) -> 31827 | J37: =VLOOKUP($B37,Rentroll!$C$11:$X$29,19,FALSE) -> 0.03 | K37: =VLOOKUP($B37,Rentroll!$C$11:$X$29,4,FALSE) -> 969.56 | L37: =VLOOKUP($B37,Rentroll!$C$11:$X$29,17,FALSE) -> 0 | M37: =VLOOKUP($B37,Rentroll!$C$11:$X$29,18,FALSE) -> 3 | O37: =B37 -> B102호 | R37: =IF(R$14<EOMONTH($E37,1),1,0)*R$11 -> 0 | S37: =IF(S$14<EOMONTH($E37,1),1,0)*S$11 -> 1 | T37: =IF(T$14<EOMONTH($E37,1),1,0)*T$11 -> 1 | U37: =IF(U$14<EOMONTH($E37,1),1,0)*U$11 -> 1 | V37: =IF(V$14<EOMONTH($E37,1),1,0)*V$11 -> 1 | W37: =IF(W$14<EOMONTH($E37,1),1,0)*W$11 -> 1 | X37: =IF(X$14<EOMONTH($E37,1),1,0)*X$11 -> 1 | Y37: =IF(Y$14<EOMONTH($E37,1),1,0)*Y$11 -> 1 | ... DL37: =IF(DL$14<EOMONTH($E37,1),1,0)*DL$11 -> 0
B38: 층수 | C38: 임차인 | D38: 시작일 | E38: 종료일 | F38: 기간 | G38: 명목 임대료(원) | H38: 실질 임대료(원) | I38: 관리비(원) | J38: 상승률 | K38: 임대면적(㎡) | L38: Fitout | M38: Rentfree | O38: 신규 임대차 | R38: =SUM(R39:R62) -> 0 | S38: =SUM(S39:S62) -> 3 | T38: =SUM(T39:T62) -> 3 | U38: =SUM(U39:U62) -> 7 | V38: =SUM(V39:V62) -> 7 | W38: =SUM(W39:W62) -> 7 | X38: =SUM(X39:X62) -> 9 | Y38: =SUM(Y39:Y62) -> 13 | ... DL38: =SUM(DL39:DL62) -> 0
B39: =Rentroll!$C$37 -> 17 | C39: =VLOOKUP($B39,Rentroll!$C$37:$Z$60,3,FALSE) -> 리마 상사 | D39: =VLOOKUP($B39,Rentroll!$C$37:$Z$60,9,FALSE) -> 47149 | E39: =VLOOKUP($B39,Rentroll!$C$37:$Z$60,10,FALSE) -> 48975 | F39: =VLOOKUP($B39,Rentroll!$C$37:$Z$60,11,FALSE) -> 60 | G39: =VLOOKUP($B39,Rentroll!$C$37:$Z$60,13,FALSE) -> 115927.41 | H39: =VLOOKUP($B39,Rentroll!$C$37:$Z$60,14,FALSE) -> 106266.79 | I39: =VLOOKUP($B39,Rentroll!$C$37:$Z$60,15,FALSE) -> 50647.896 | J39: =VLOOKUP($B39,Rentroll!$C$37:$Z$60,19,FALSE) -> 0.03 | K39: =VLOOKUP($B39,Rentroll!$C$37:$Z$60,4,FALSE) -> 1385.09 | L39: =VLOOKUP($B39,Rentroll!$C$37:$Z$60,17,FALSE) -> 0 | M39: =VLOOKUP($B39,Rentroll!$C$37:$Z$60,18,FALSE) -> 1 | O39: =B39 -> 17 | R39: =(R$14>$D39)*(R$14<=$E39)*R$11*1 -> 0 | S39: =(S$14>$D39)*(S$14<=$E39)*S$11*1 -> 0 | T39: =(T$14>$D39)*(T$14<=$E39)*T$11*1 -> 0 | U39: =(U$14>$D39)*(U$14<=$E39)*U$11*1 -> 0 | V39: =(V$14>$D39)*(V$14<=$E39)*V$11*1 -> 0 | W39: =(W$14>$D39)*(W$14<=$E39)*W$11*1 -> 0 | X39: =(X$14>$D39)*(X$14<=$E39)*X$11*1 -> 0 | Y39: =(Y$14>$D39)*(Y$14<=$E39)*Y$11*1 -> 0 | ... DL39: =(DL$14>$D39)*(DL$14<=$E39)*DL$11*1 -> 0
B40: =Rentroll!$C$38 -> 16 | C40: =VLOOKUP($B40,Rentroll!$C$37:$Z$60,3,FALSE) -> 리마 상사 | D40: =VLOOKUP($B40,Rentroll!$C$37:$Z$60,9,FALSE) -> 47149 | E40: =VLOOKUP($B40,Rentroll!$C$37:$Z$60,10,FALSE) -> 48975 | F40: =VLOOKUP($B40,Rentroll!$C$37:$Z$60,11,FALSE) -> 60 | G40: =VLOOKUP($B40,Rentroll!$C$37:$Z$60,13,FALSE) -> 115927.41 | H40: =VLOOKUP($B40,Rentroll!$C$37:$Z$60,14,FALSE) -> 106266.79 | I40: =VLOOKUP($B40,Rentroll!$C$37:$Z$60,15,FALSE) -> 50647.896 | J40: =VLOOKUP($B40,Rentroll!$C$37:$Z$60,19,FALSE) -> 0.03 | K40: =VLOOKUP($B40,Rentroll!$C$37:$Z$60,4,FALSE) -> 1385.09 | L40: =VLOOKUP($B40,Rentroll!$C$37:$Z$60,17,FALSE) -> 0 | M40: =VLOOKUP($B40,Rentroll!$C$37:$Z$60,18,FALSE) -> 1 | O40: =B40 -> 16 | R40: =(R$14>$D40)*(R$14<=$E40)*R$11*1 -> 0 | S40: =(S$14>$D40)*(S$14<=$E40)*S$11*1 -> 0 | T40: =(T$14>$D40)*(T$14<=$E40)*T$11*1 -> 0 | U40: =(U$14>$D40)*(U$14<=$E40)*U$11*1 -> 0 | V40: =(V$14>$D40)*(V$14<=$E40)*V$11*1 -> 0 | W40: =(W$14>$D40)*(W$14<=$E40)*W$11*1 -> 0 | X40: =(X$14>$D40)*(X$14<=$E40)*X$11*1 -> 0 | Y40: =(Y$14>$D40)*(Y$14<=$E40)*Y$11*1 -> 0 | ... DL40: =(DL$14>$D40)*(DL$14<=$E40)*DL$11*1 -> 0
B41: =Rentroll!$C$39 -> 15 | C41: =VLOOKUP($B41,Rentroll!$C$37:$Z$60,3,FALSE) -> 111퍼센트 | D41: =VLOOKUP($B41,Rentroll!$C$37:$Z$60,9,FALSE) -> 45869 | E41: =VLOOKUP($B41,Rentroll!$C$37:$Z$60,10,FALSE) -> 47695 | F41: =VLOOKUP($B41,Rentroll!$C$37:$Z$60,11,FALSE) -> 60 | G41: =VLOOKUP($B41,Rentroll!$C$37:$Z$60,13,FALSE) -> 103000 | H41: =VLOOKUP($B41,Rentroll!$C$37:$Z$60,14,FALSE) -> 94416.667 | I41: =VLOOKUP($B41,Rentroll!$C$37:$Z$60,15,FALSE) -> 45000 | J41: =VLOOKUP($B41,Rentroll!$C$37:$Z$60,19,FALSE) -> 0.03 | K41: =VLOOKUP($B41,Rentroll!$C$37:$Z$60,4,FALSE) -> 1385.09 | L41: =VLOOKUP($B41,Rentroll!$C$37:$Z$60,17,FALSE) -> 1 | M41: =VLOOKUP($B41,Rentroll!$C$37:$Z$60,18,FALSE) -> 1 | O41: =B41 -> 15 | R41: =(R$14>$D41)*(R$14<=$E41)*R$11*1 -> 0 | S41: =(S$14>$D41)*(S$14<=$E41)*S$11*1 -> 0 | T41: =(T$14>$D41)*(T$14<=$E41)*T$11*1 -> 0 | U41: =(U$14>$D41)*(U$14<=$E41)*U$11*1 -> 0 | V41: =(V$14>$D41)*(V$14<=$E41)*V$11*1 -> 0 | W41: =(W$14>$D41)*(W$14<=$E41)*W$11*1 -> 0 | X41: =(X$14>$D41)*(X$14<=$E41)*X$11*1 -> 0 | Y41: =(Y$14>$D41)*(Y$14<=$E41)*Y$11*1 -> 1 | ... DL41: =(DL$14>$D41)*(DL$14<=$E41)*DL$11*1 -> 0
B42: =Rentroll!$C$40 -> 14 | C42: =VLOOKUP($B42,Rentroll!$C$37:$Z$60,3,FALSE) -> 111퍼센트 | D42: =VLOOKUP($B42,Rentroll!$C$37:$Z$60,9,FALSE) -> 45869 | E42: =VLOOKUP($B42,Rentroll!$C$37:$Z$60,10,FALSE) -> 47695 | F42: =VLOOKUP($B42,Rentroll!$C$37:$Z$60,11,FALSE) -> 60 | G42: =VLOOKUP($B42,Rentroll!$C$37:$Z$60,13,FALSE) -> 103000 | H42: =VLOOKUP($B42,Rentroll!$C$37:$Z$60,14,FALSE) -> 94416.667 | I42: =VLOOKUP($B42,Rentroll!$C$37:$Z$60,15,FALSE) -> 45000 | J42: =VLOOKUP($B42,Rentroll!$C$37:$Z$60,19,FALSE) -> 0.03 | K42: =VLOOKUP($B42,Rentroll!$C$37:$Z$60,4,FALSE) -> 1385.09 | L42: =VLOOKUP($B42,Rentroll!$C$37:$Z$60,17,FALSE) -> 1 | M42: =VLOOKUP($B42,Rentroll!$C$37:$Z$60,18,FALSE) -> 1 | O42: =B42 -> 14 | R42: =(R$14>$D42)*(R$14<=$E42)*R$11*1 -> 0 | S42: =(S$14>$D42)*(S$14<=$E42)*S$11*1 -> 0 | T42: =(T$14>$D42)*(T$14<=$E42)*T$11*1 -> 0 | U42: =(U$14>$D42)*(U$14<=$E42)*U$11*1 -> 0 | V42: =(V$14>$D42)*(V$14<=$E42)*V$11*1 -> 0 | W42: =(W$14>$D42)*(W$14<=$E42)*W$11*1 -> 0 | X42: =(X$14>$D42)*(X$14<=$E42)*X$11*1 -> 0 | Y42: =(Y$14>$D42)*(Y$14<=$E42)*Y$11*1 -> 1 | ... DL42: =(DL$14>$D42)*(DL$14<=$E42)*DL$11*1 -> 0
B43: =Rentroll!$C$41 -> 13 | C43: =VLOOKUP($B43,Rentroll!$C$37:$Z$60,3,FALSE) -> 111퍼센트 | D43: =VLOOKUP($B43,Rentroll!$C$37:$Z$60,9,FALSE) -> 45869 | E43: =VLOOKUP($B43,Rentroll!$C$37:$Z$60,10,FALSE) -> 47695 | F43: =VLOOKUP($B43,Rentroll!$C$37:$Z$60,11,FALSE) -> 60 | G43: =VLOOKUP($B43,Rentroll!$C$37:$Z$60,13,FALSE) -> 103000 | H43: =VLOOKUP($B43,Rentroll!$C$37:$Z$60,14,FALSE) -> 94416.667 | I43: =VLOOKUP($B43,Rentroll!$C$37:$Z$60,15,FALSE) -> 45000 | J43: =VLOOKUP($B43,Rentroll!$C$37:$Z$60,19,FALSE) -> 0.03 | K43: =VLOOKUP($B43,Rentroll!$C$37:$Z$60,4,FALSE) -> 1385.09 | L43: =VLOOKUP($B43,Rentroll!$C$37:$Z$60,17,FALSE) -> 1 | M43: =VLOOKUP($B43,Rentroll!$C$37:$Z$60,18,FALSE) -> 1 | O43: =B43 -> 13 | R43: =(R$14>$D43)*(R$14<=$E43)*R$11*1 -> 0 | S43: =(S$14>$D43)*(S$14<=$E43)*S$11*1 -> 0 | T43: =(T$14>$D43)*(T$14<=$E43)*T$11*1 -> 0 | U43: =(U$14>$D43)*(U$14<=$E43)*U$11*1 -> 0 | V43: =(V$14>$D43)*(V$14<=$E43)*V$11*1 -> 0 | W43: =(W$14>$D43)*(W$14<=$E43)*W$11*1 -> 0 | X43: =(X$14>$D43)*(X$14<=$E43)*X$11*1 -> 0 | Y43: =(Y$14>$D43)*(Y$14<=$E43)*Y$11*1 -> 1 | ... DL43: =(DL$14>$D43)*(DL$14<=$E43)*DL$11*1 -> 0
B44: =Rentroll!$C$42 -> 12 | C44: =VLOOKUP($B44,Rentroll!$C$37:$Z$60,3,FALSE) -> 신라젠 | D44: =VLOOKUP($B44,Rentroll!$C$37:$Z$60,9,FALSE) -> 45869 | E44: =VLOOKUP($B44,Rentroll!$C$37:$Z$60,10,FALSE) -> 47695 | F44: =VLOOKUP($B44,Rentroll!$C$37:$Z$60,11,FALSE) -> 60 | G44: =VLOOKUP($B44,Rentroll!$C$37:$Z$60,13,FALSE) -> 103000 | H44: =VLOOKUP($B44,Rentroll!$C$37:$Z$60,14,FALSE) -> 94416.667 | I44: =VLOOKUP($B44,Rentroll!$C$37:$Z$60,15,FALSE) -> 45000 | J44: =VLOOKUP($B44,Rentroll!$C$37:$Z$60,19,FALSE) -> 0.03 | K44: =VLOOKUP($B44,Rentroll!$C$37:$Z$60,4,FALSE) -> 1385.09 | L44: =VLOOKUP($B44,Rentroll!$C$37:$Z$60,17,FALSE) -> 1 | M44: =VLOOKUP($B44,Rentroll!$C$37:$Z$60,18,FALSE) -> 1 | O44: =B44 -> 12 | R44: =(R$14>$D44)*(R$14<=$E44)*R$11*1 -> 0 | S44: =(S$14>$D44)*(S$14<=$E44)*S$11*1 -> 0 | T44: =(T$14>$D44)*(T$14<=$E44)*T$11*1 -> 0 | U44: =(U$14>$D44)*(U$14<=$E44)*U$11*1 -> 0 | V44: =(V$14>$D44)*(V$14<=$E44)*V$11*1 -> 0 | W44: =(W$14>$D44)*(W$14<=$E44)*W$11*1 -> 0 | X44: =(X$14>$D44)*(X$14<=$E44)*X$11*1 -> 0 | Y44: =(Y$14>$D44)*(Y$14<=$E44)*Y$11*1 -> 1 | ... DL44: =(DL$14>$D44)*(DL$14<=$E44)*DL$11*1 -> 0
B45: =Rentroll!$C$43 -> 11 | C45: =VLOOKUP($B45,Rentroll!$C$37:$Z$60,3,FALSE) -> 노벰버 건설 | D45: =VLOOKUP($B45,Rentroll!$C$37:$Z$60,9,FALSE) -> 46904 | E45: =VLOOKUP($B45,Rentroll!$C$37:$Z$60,10,FALSE) -> 48730 | F45: =VLOOKUP($B45,Rentroll!$C$37:$Z$60,11,FALSE) -> 60 | G45: =VLOOKUP($B45,Rentroll!$C$37:$Z$60,13,FALSE) -> 112550.88 | H45: =VLOOKUP($B45,Rentroll!$C$37:$Z$60,14,FALSE) -> 103171.64 | I45: =VLOOKUP($B45,Rentroll!$C$37:$Z$60,15,FALSE) -> 49172.715 | J45: =VLOOKUP($B45,Rentroll!$C$37:$Z$60,19,FALSE) -> 0.03 | K45: =VLOOKUP($B45,Rentroll!$C$37:$Z$60,4,FALSE) -> 1385.09 | L45: =VLOOKUP($B45,Rentroll!$C$37:$Z$60,17,FALSE) -> 0 | M45: =VLOOKUP($B45,Rentroll!$C$37:$Z$60,18,FALSE) -> 1 | O45: =B45 -> 11 | R45: =(R$14>$D45)*(R$14<=$E45)*R$11*1 -> 0 | S45: =(S$14>$D45)*(S$14<=$E45)*S$11*1 -> 0 | T45: =(T$14>$D45)*(T$14<=$E45)*T$11*1 -> 0 | U45: =(U$14>$D45)*(U$14<=$E45)*U$11*1 -> 0 | V45: =(V$14>$D45)*(V$14<=$E45)*V$11*1 -> 0 | W45: =(W$14>$D45)*(W$14<=$E45)*W$11*1 -> 0 | X45: =(X$14>$D45)*(X$14<=$E45)*X$11*1 -> 0 | Y45: =(Y$14>$D45)*(Y$14<=$E45)*Y$11*1 -> 0 | ... DL45: =(DL$14>$D45)*(DL$14<=$E45)*DL$11*1 -> 0
B46: =Rentroll!$C$44 -> 10 | C46: =VLOOKUP($B46,Rentroll!$C$37:$Z$60,3,FALSE) -> 노벰버 건설 | D46: =VLOOKUP($B46,Rentroll!$C$37:$Z$60,9,FALSE) -> 46904 | E46: =VLOOKUP($B46,Rentroll!$C$37:$Z$60,10,FALSE) -> 48730 | F46: =VLOOKUP($B46,Rentroll!$C$37:$Z$60,11,FALSE) -> 60 | G46: =VLOOKUP($B46,Rentroll!$C$37:$Z$60,13,FALSE) -> 112550.88 | H46: =VLOOKUP($B46,Rentroll!$C$37:$Z$60,14,FALSE) -> 103171.64 | I46: =VLOOKUP($B46,Rentroll!$C$37:$Z$60,15,FALSE) -> 49172.715 | J46: =VLOOKUP($B46,Rentroll!$C$37:$Z$60,19,FALSE) -> 0.03 | K46: =VLOOKUP($B46,Rentroll!$C$37:$Z$60,4,FALSE) -> 1385.09 | L46: =VLOOKUP($B46,Rentroll!$C$37:$Z$60,17,FALSE) -> 0 | M46: =VLOOKUP($B46,Rentroll!$C$37:$Z$60,18,FALSE) -> 1 | O46: =B46 -> 10 | R46: =(R$14>$D46)*(R$14<=$E46)*R$11*1 -> 0 | S46: =(S$14>$D46)*(S$14<=$E46)*S$11*1 -> 0 | T46: =(T$14>$D46)*(T$14<=$E46)*T$11*1 -> 0 | U46: =(U$14>$D46)*(U$14<=$E46)*U$11*1 -> 0 | V46: =(V$14>$D46)*(V$14<=$E46)*V$11*1 -> 0 | W46: =(W$14>$D46)*(W$14<=$E46)*W$11*1 -> 0 | X46: =(X$14>$D46)*(X$14<=$E46)*X$11*1 -> 0 | Y46: =(Y$14>$D46)*(Y$14<=$E46)*Y$11*1 -> 0 | ... DL46: =(DL$14>$D46)*(DL$14<=$E46)*DL$11*1 -> 0
B47: =Rentroll!$C$45 -> 9 | C47: =VLOOKUP($B47,Rentroll!$C$37:$Z$60,3,FALSE) -> 노벰버 건설 | D47: =VLOOKUP($B47,Rentroll!$C$37:$Z$60,9,FALSE) -> 46904 | E47: =VLOOKUP($B47,Rentroll!$C$37:$Z$60,10,FALSE) -> 48730 | F47: =VLOOKUP($B47,Rentroll!$C$37:$Z$60,11,FALSE) -> 60 | G47: =VLOOKUP($B47,Rentroll!$C$37:$Z$60,13,FALSE) -> 112550.88 | H47: =VLOOKUP($B47,Rentroll!$C$37:$Z$60,14,FALSE) -> 103171.64 | I47: =VLOOKUP($B47,Rentroll!$C$37:$Z$60,15,FALSE) -> 49172.715 | J47: =VLOOKUP($B47,Rentroll!$C$37:$Z$60,19,FALSE) -> 0.03 | K47: =VLOOKUP($B47,Rentroll!$C$37:$Z$60,4,FALSE) -> 1385.09 | L47: =VLOOKUP($B47,Rentroll!$C$37:$Z$60,17,FALSE) -> 0 | M47: =VLOOKUP($B47,Rentroll!$C$37:$Z$60,18,FALSE) -> 1 | O47: =B47 -> 9 | R47: =(R$14>$D47)*(R$14<=$E47)*R$11*1 -> 0 | S47: =(S$14>$D47)*(S$14<=$E47)*S$11*1 -> 0 | T47: =(T$14>$D47)*(T$14<=$E47)*T$11*1 -> 0 | U47: =(U$14>$D47)*(U$14<=$E47)*U$11*1 -> 0 | V47: =(V$14>$D47)*(V$14<=$E47)*V$11*1 -> 0 | W47: =(W$14>$D47)*(W$14<=$E47)*W$11*1 -> 0 | X47: =(X$14>$D47)*(X$14<=$E47)*X$11*1 -> 0 | Y47: =(Y$14>$D47)*(Y$14<=$E47)*Y$11*1 -> 0 | ... DL47: =(DL$14>$D47)*(DL$14<=$E47)*DL$11*1 -> 0
B48: =Rentroll!$C$46 -> 8 | C48: =VLOOKUP($B48,Rentroll!$C$37:$Z$60,3,FALSE) -> 오케스트로 | D48: =VLOOKUP($B48,Rentroll!$C$37:$Z$60,9,FALSE) -> 46477 | E48: =VLOOKUP($B48,Rentroll!$C$37:$Z$60,10,FALSE) -> 48304 | F48: =VLOOKUP($B48,Rentroll!$C$37:$Z$60,11,FALSE) -> 60 | G48: =VLOOKUP($B48,Rentroll!$C$37:$Z$60,13,FALSE) -> 109272.7 | H48: =VLOOKUP($B48,Rentroll!$C$37:$Z$60,14,FALSE) -> 100166.64 | I48: =VLOOKUP($B48,Rentroll!$C$37:$Z$60,15,FALSE) -> 47740.5 | J48: =VLOOKUP($B48,Rentroll!$C$37:$Z$60,19,FALSE) -> 0.03 | K48: =VLOOKUP($B48,Rentroll!$C$37:$Z$60,4,FALSE) -> 1385.09 | L48: =VLOOKUP($B48,Rentroll!$C$37:$Z$60,17,FALSE) -> 1 | M48: =VLOOKUP($B48,Rentroll!$C$37:$Z$60,18,FALSE) -> 1 | O48: =B48 -> 8 | R48: =(R$14>$D48)*(R$14<=$E48)*R$11*1 -> 0 | S48: =(S$14>$D48)*(S$14<=$E48)*S$11*1 -> 0 | T48: =(T$14>$D48)*(T$14<=$E48)*T$11*1 -> 0 | U48: =(U$14>$D48)*(U$14<=$E48)*U$11*1 -> 0 | V48: =(V$14>$D48)*(V$14<=$E48)*V$11*1 -> 0 | W48: =(W$14>$D48)*(W$14<=$E48)*W$11*1 -> 0 | X48: =(X$14>$D48)*(X$14<=$E48)*X$11*1 -> 0 | Y48: =(Y$14>$D48)*(Y$14<=$E48)*Y$11*1 -> 0 | ... DL48: =(DL$14>$D48)*(DL$14<=$E48)*DL$11*1 -> 0
B49: =Rentroll!$C$47 -> 7 | C49: =VLOOKUP($B49,Rentroll!$C$37:$Z$60,3,FALSE) -> 오케스트로 | D49: =VLOOKUP($B49,Rentroll!$C$37:$Z$60,9,FALSE) -> 46477 | E49: =VLOOKUP($B49,Rentroll!$C$37:$Z$60,10,FALSE) -> 48304 | F49: =VLOOKUP($B49,Rentroll!$C$37:$Z$60,11,FALSE) -> 60 | G49: =VLOOKUP($B49,Rentroll!$C$37:$Z$60,13,FALSE) -> 109272.7 | H49: =VLOOKUP($B49,Rentroll!$C$37:$Z$60,14,FALSE) -> 100166.64 | I49: =VLOOKUP($B49,Rentroll!$C$37:$Z$60,15,FALSE) -> 47740.5 | J49: =VLOOKUP($B49,Rentroll!$C$37:$Z$60,19,FALSE) -> 0.03 | K49: =VLOOKUP($B49,Rentroll!$C$37:$Z$60,4,FALSE) -> 1385.09 | L49: =VLOOKUP($B49,Rentroll!$C$37:$Z$60,17,FALSE) -> 1 | M49: =VLOOKUP($B49,Rentroll!$C$37:$Z$60,18,FALSE) -> 1 | O49: =B49 -> 7 | R49: =(R$14>$D49)*(R$14<=$E49)*R$11*1 -> 0 | S49: =(S$14>$D49)*(S$14<=$E49)*S$11*1 -> 0 | T49: =(T$14>$D49)*(T$14<=$E49)*T$11*1 -> 0 | U49: =(U$14>$D49)*(U$14<=$E49)*U$11*1 -> 0 | V49: =(V$14>$D49)*(V$14<=$E49)*V$11*1 -> 0 | W49: =(W$14>$D49)*(W$14<=$E49)*W$11*1 -> 0 | X49: =(X$14>$D49)*(X$14<=$E49)*X$11*1 -> 0 | Y49: =(Y$14>$D49)*(Y$14<=$E49)*Y$11*1 -> 0 | ... DL49: =(DL$14>$D49)*(DL$14<=$E49)*DL$11*1 -> 0
B50: =Rentroll!$C$48 -> 6 | C50: =VLOOKUP($B50,Rentroll!$C$37:$Z$60,3,FALSE) -> 오케스트로 | D50: =VLOOKUP($B50,Rentroll!$C$37:$Z$60,9,FALSE) -> 46477 | E50: =VLOOKUP($B50,Rentroll!$C$37:$Z$60,10,FALSE) -> 48304 | F50: =VLOOKUP($B50,Rentroll!$C$37:$Z$60,11,FALSE) -> 60 | G50: =VLOOKUP($B50,Rentroll!$C$37:$Z$60,13,FALSE) -> 109272.7 | H50: =VLOOKUP($B50,Rentroll!$C$37:$Z$60,14,FALSE) -> 100166.64 | I50: =VLOOKUP($B50,Rentroll!$C$37:$Z$60,15,FALSE) -> 47740.5 | J50: =VLOOKUP($B50,Rentroll!$C$37:$Z$60,19,FALSE) -> 0.03 | K50: =VLOOKUP($B50,Rentroll!$C$37:$Z$60,4,FALSE) -> 1385.09 | L50: =VLOOKUP($B50,Rentroll!$C$37:$Z$60,17,FALSE) -> 1 | M50: =VLOOKUP($B50,Rentroll!$C$37:$Z$60,18,FALSE) -> 1 | O50: =B50 -> 6 | R50: =(R$14>$D50)*(R$14<=$E50)*R$11*1 -> 0 | S50: =(S$14>$D50)*(S$14<=$E50)*S$11*1 -> 0 | T50: =(T$14>$D50)*(T$14<=$E50)*T$11*1 -> 0 | U50: =(U$14>$D50)*(U$14<=$E50)*U$11*1 -> 0 | V50: =(V$14>$D50)*(V$14<=$E50)*V$11*1 -> 0 | W50: =(W$14>$D50)*(W$14<=$E50)*W$11*1 -> 0 | X50: =(X$14>$D50)*(X$14<=$E50)*X$11*1 -> 0 | Y50: =(Y$14>$D50)*(Y$14<=$E50)*Y$11*1 -> 0 | ... DL50: =(DL$14>$D50)*(DL$14<=$E50)*DL$11*1 -> 0
B51: =Rentroll!$C$49 -> 5 | C51: =VLOOKUP($B51,Rentroll!$C$37:$Z$60,3,FALSE) -> 타이거로켓 | D51: =VLOOKUP($B51,Rentroll!$C$37:$Z$60,9,FALSE) -> 45688 | E51: =VLOOKUP($B51,Rentroll!$C$37:$Z$60,10,FALSE) -> 47514 | F51: =VLOOKUP($B51,Rentroll!$C$37:$Z$60,11,FALSE) -> 60 | G51: =VLOOKUP($B51,Rentroll!$C$37:$Z$60,13,FALSE) -> 103000 | H51: =VLOOKUP($B51,Rentroll!$C$37:$Z$60,14,FALSE) -> 90125 | I51: =VLOOKUP($B51,Rentroll!$C$37:$Z$60,15,FALSE) -> 45000 | J51: =VLOOKUP($B51,Rentroll!$C$37:$Z$60,19,FALSE) -> 0.03 | K51: =VLOOKUP($B51,Rentroll!$C$37:$Z$60,4,FALSE) -> 1385.09 | L51: =VLOOKUP($B51,Rentroll!$C$37:$Z$60,17,FALSE) -> 1 | M51: =VLOOKUP($B51,Rentroll!$C$37:$Z$60,18,FALSE) -> 1.5 | O51: =B51 -> 5 | R51: =(R$14>$D51)*(R$14<=$E51)*R$11*1 -> 0 | S51: =(S$14>$D51)*(S$14<=$E51)*S$11*1 -> 1 | T51: =(T$14>$D51)*(T$14<=$E51)*T$11*1 -> 1 | U51: =(U$14>$D51)*(U$14<=$E51)*U$11*1 -> 1 | V51: =(V$14>$D51)*(V$14<=$E51)*V$11*1 -> 1 | W51: =(W$14>$D51)*(W$14<=$E51)*W$11*1 -> 1 | X51: =(X$14>$D51)*(X$14<=$E51)*X$11*1 -> 1 | Y51: =(Y$14>$D51)*(Y$14<=$E51)*Y$11*1 -> 1 | ... DL51: =(DL$14>$D51)*(DL$14<=$E51)*DL$11*1 -> 0
B52: =Rentroll!$C$50 -> 4 | C52: =VLOOKUP($B52,Rentroll!$C$37:$Z$60,3,FALSE) -> 타이거로켓 | D52: =VLOOKUP($B52,Rentroll!$C$37:$Z$60,9,FALSE) -> 45688 | E52: =VLOOKUP($B52,Rentroll!$C$37:$Z$60,10,FALSE) -> 47514 | F52: =VLOOKUP($B52,Rentroll!$C$37:$Z$60,11,FALSE) -> 60 | G52: =VLOOKUP($B52,Rentroll!$C$37:$Z$60,13,FALSE) -> 103000 | H52: =VLOOKUP($B52,Rentroll!$C$37:$Z$60,14,FALSE) -> 90125 | I52: =VLOOKUP($B52,Rentroll!$C$37:$Z$60,15,FALSE) -> 45000 | J52: =VLOOKUP($B52,Rentroll!$C$37:$Z$60,19,FALSE) -> 0.03 | K52: =VLOOKUP($B52,Rentroll!$C$37:$Z$60,4,FALSE) -> 1385.09 | L52: =VLOOKUP($B52,Rentroll!$C$37:$Z$60,17,FALSE) -> 1 | M52: =VLOOKUP($B52,Rentroll!$C$37:$Z$60,18,FALSE) -> 1.5 | O52: =B52 -> 4 | R52: =(R$14>$D52)*(R$14<=$E52)*R$11*1 -> 0 | S52: =(S$14>$D52)*(S$14<=$E52)*S$11*1 -> 1 | T52: =(T$14>$D52)*(T$14<=$E52)*T$11*1 -> 1 | U52: =(U$14>$D52)*(U$14<=$E52)*U$11*1 -> 1 | V52: =(V$14>$D52)*(V$14<=$E52)*V$11*1 -> 1 | W52: =(W$14>$D52)*(W$14<=$E52)*W$11*1 -> 1 | X52: =(X$14>$D52)*(X$14<=$E52)*X$11*1 -> 1 | Y52: =(Y$14>$D52)*(Y$14<=$E52)*Y$11*1 -> 1 | ... DL52: =(DL$14>$D52)*(DL$14<=$E52)*DL$11*1 -> 0
B53: =Rentroll!$C$51 -> 3 | C53: =VLOOKUP($B53,Rentroll!$C$37:$Z$60,3,FALSE) -> 타이거로켓 | D53: =VLOOKUP($B53,Rentroll!$C$37:$Z$60,9,FALSE) -> 45688 | E53: =VLOOKUP($B53,Rentroll!$C$37:$Z$60,10,FALSE) -> 47514 | F53: =VLOOKUP($B53,Rentroll!$C$37:$Z$60,11,FALSE) -> 60 | G53: =VLOOKUP($B53,Rentroll!$C$37:$Z$60,13,FALSE) -> 103000 | H53: =VLOOKUP($B53,Rentroll!$C$37:$Z$60,14,FALSE) -> 90125 | I53: =VLOOKUP($B53,Rentroll!$C$37:$Z$60,15,FALSE) -> 45000 | J53: =VLOOKUP($B53,Rentroll!$C$37:$Z$60,19,FALSE) -> 0.03 | K53: =VLOOKUP($B53,Rentroll!$C$37:$Z$60,4,FALSE) -> 1385.09 | L53: =VLOOKUP($B53,Rentroll!$C$37:$Z$60,17,FALSE) -> 1 | M53: =VLOOKUP($B53,Rentroll!$C$37:$Z$60,18,FALSE) -> 1.5 | O53: =B53 -> 3 | R53: =(R$14>$D53)*(R$14<=$E53)*R$11*1 -> 0 | S53: =(S$14>$D53)*(S$14<=$E53)*S$11*1 -> 1 | T53: =(T$14>$D53)*(T$14<=$E53)*T$11*1 -> 1 | U53: =(U$14>$D53)*(U$14<=$E53)*U$11*1 -> 1 | V53: =(V$14>$D53)*(V$14<=$E53)*V$11*1 -> 1 | W53: =(W$14>$D53)*(W$14<=$E53)*W$11*1 -> 1 | X53: =(X$14>$D53)*(X$14<=$E53)*X$11*1 -> 1 | Y53: =(Y$14>$D53)*(Y$14<=$E53)*Y$11*1 -> 1 | ... DL53: =(DL$14>$D53)*(DL$14<=$E53)*DL$11*1 -> 0
B54: =Rentroll!$C$52 -> 201호 | C54: =VLOOKUP($B54,Rentroll!$C$37:$Z$60,3,FALSE) -> RMW CARNE | D54: =VLOOKUP($B54,Rentroll!$C$37:$Z$60,9,FALSE) -> 45747 | E54: =VLOOKUP($B54,Rentroll!$C$37:$Z$60,10,FALSE) -> 47573 | F54: =VLOOKUP($B54,Rentroll!$C$37:$Z$60,11,FALSE) -> 60 | G54: =VLOOKUP($B54,Rentroll!$C$37:$Z$60,13,FALSE) -> 130000 | H54: =VLOOKUP($B54,Rentroll!$C$37:$Z$60,14,FALSE) -> 130000 | I54: =VLOOKUP($B54,Rentroll!$C$37:$Z$60,15,FALSE) -> 45000 | J54: =VLOOKUP($B54,Rentroll!$C$37:$Z$60,19,FALSE) -> 0.03 | K54: =VLOOKUP($B54,Rentroll!$C$37:$Z$60,4,FALSE) -> 346.2725 | L54: =VLOOKUP($B54,Rentroll!$C$37:$Z$60,17,FALSE) -> 2 | M54: =VLOOKUP($B54,Rentroll!$C$37:$Z$60,18,FALSE) -> 0 | O54: =B54 -> 201호 | R54: =(R$14>$D54)*(R$14<=$E54)*R$11*1 -> 0 | S54: =(S$14>$D54)*(S$14<=$E54)*S$11*1 -> 0 | T54: =(T$14>$D54)*(T$14<=$E54)*T$11*1 -> 0 | U54: =(U$14>$D54)*(U$14<=$E54)*U$11*1 -> 1 | V54: =(V$14>$D54)*(V$14<=$E54)*V$11*1 -> 1 | W54: =(W$14>$D54)*(W$14<=$E54)*W$11*1 -> 1 | X54: =(X$14>$D54)*(X$14<=$E54)*X$11*1 -> 1 | Y54: =(Y$14>$D54)*(Y$14<=$E54)*Y$11*1 -> 1 | ... DL54: =(DL$14>$D54)*(DL$14<=$E54)*DL$11*1 -> 0
B55: =Rentroll!$C$53 -> 202호 | C55: =VLOOKUP($B55,Rentroll!$C$37:$Z$60,3,FALSE) -> 키이로 | D55: =VLOOKUP($B55,Rentroll!$C$37:$Z$60,9,FALSE) -> 45747 | E55: =VLOOKUP($B55,Rentroll!$C$37:$Z$60,10,FALSE) -> 47573 | F55: =VLOOKUP($B55,Rentroll!$C$37:$Z$60,11,FALSE) -> 60 | G55: =VLOOKUP($B55,Rentroll!$C$37:$Z$60,13,FALSE) -> 130000 | H55: =VLOOKUP($B55,Rentroll!$C$37:$Z$60,14,FALSE) -> 130000 | I55: =VLOOKUP($B55,Rentroll!$C$37:$Z$60,15,FALSE) -> 45000 | J55: =VLOOKUP($B55,Rentroll!$C$37:$Z$60,19,FALSE) -> 0.03 | K55: =VLOOKUP($B55,Rentroll!$C$37:$Z$60,4,FALSE) -> 346.2725 | L55: =VLOOKUP($B55,Rentroll!$C$37:$Z$60,17,FALSE) -> 2 | M55: =VLOOKUP($B55,Rentroll!$C$37:$Z$60,18,FALSE) -> 0 | O55: =B55 -> 202호 | R55: =(R$14>$D55)*(R$14<=$E55)*R$11*1 -> 0 | S55: =(S$14>$D55)*(S$14<=$E55)*S$11*1 -> 0 | T55: =(T$14>$D55)*(T$14<=$E55)*T$11*1 -> 0 | U55: =(U$14>$D55)*(U$14<=$E55)*U$11*1 -> 1 | V55: =(V$14>$D55)*(V$14<=$E55)*V$11*1 -> 1 | W55: =(W$14>$D55)*(W$14<=$E55)*W$11*1 -> 1 | X55: =(X$14>$D55)*(X$14<=$E55)*X$11*1 -> 1 | Y55: =(Y$14>$D55)*(Y$14<=$E55)*Y$11*1 -> 1 | ... DL55: =(DL$14>$D55)*(DL$14<=$E55)*DL$11*1 -> 0
B56: =Rentroll!$C$54 -> 203호 | C56: =VLOOKUP($B56,Rentroll!$C$37:$Z$60,3,FALSE) -> 주 052 | D56: =VLOOKUP($B56,Rentroll!$C$37:$Z$60,9,FALSE) -> 45747 | E56: =VLOOKUP($B56,Rentroll!$C$37:$Z$60,10,FALSE) -> 47573 | F56: =VLOOKUP($B56,Rentroll!$C$37:$Z$60,11,FALSE) -> 60 | G56: =VLOOKUP($B56,Rentroll!$C$37:$Z$60,13,FALSE) -> 130000 | H56: =VLOOKUP($B56,Rentroll!$C$37:$Z$60,14,FALSE) -> 130000 | I56: =VLOOKUP($B56,Rentroll!$C$37:$Z$60,15,FALSE) -> 45000 | J56: =VLOOKUP($B56,Rentroll!$C$37:$Z$60,19,FALSE) -> 0.03 | K56: =VLOOKUP($B56,Rentroll!$C$37:$Z$60,4,FALSE) -> 346.2725 | L56: =VLOOKUP($B56,Rentroll!$C$37:$Z$60,17,FALSE) -> 2 | M56: =VLOOKUP($B56,Rentroll!$C$37:$Z$60,18,FALSE) -> 0 | O56: =B56 -> 203호 | R56: =(R$14>$D56)*(R$14<=$E56)*R$11*1 -> 0 | S56: =(S$14>$D56)*(S$14<=$E56)*S$11*1 -> 0 | T56: =(T$14>$D56)*(T$14<=$E56)*T$11*1 -> 0 | U56: =(U$14>$D56)*(U$14<=$E56)*U$11*1 -> 1 | V56: =(V$14>$D56)*(V$14<=$E56)*V$11*1 -> 1 | W56: =(W$14>$D56)*(W$14<=$E56)*W$11*1 -> 1 | X56: =(X$14>$D56)*(X$14<=$E56)*X$11*1 -> 1 | Y56: =(Y$14>$D56)*(Y$14<=$E56)*Y$11*1 -> 1 | ... DL56: =(DL$14>$D56)*(DL$14<=$E56)*DL$11*1 -> 0
B57: =Rentroll!$C$55 -> 204호 | C57: =VLOOKUP($B57,Rentroll!$C$37:$Z$60,3,FALSE) -> 바이닐 청계 | D57: =VLOOKUP($B57,Rentroll!$C$37:$Z$60,9,FALSE) -> 45747 | E57: =VLOOKUP($B57,Rentroll!$C$37:$Z$60,10,FALSE) -> 47573 | F57: =VLOOKUP($B57,Rentroll!$C$37:$Z$60,11,FALSE) -> 60 | G57: =VLOOKUP($B57,Rentroll!$C$37:$Z$60,13,FALSE) -> 130000 | H57: =VLOOKUP($B57,Rentroll!$C$37:$Z$60,14,FALSE) -> 130000 | I57: =VLOOKUP($B57,Rentroll!$C$37:$Z$60,15,FALSE) -> 45000 | J57: =VLOOKUP($B57,Rentroll!$C$37:$Z$60,19,FALSE) -> 0.03 | K57: =VLOOKUP($B57,Rentroll!$C$37:$Z$60,4,FALSE) -> 346.2725 | L57: =VLOOKUP($B57,Rentroll!$C$37:$Z$60,17,FALSE) -> 2 | M57: =VLOOKUP($B57,Rentroll!$C$37:$Z$60,18,FALSE) -> 0 | O57: =B57 -> 204호 | R57: =(R$14>$D57)*(R$14<=$E57)*R$11*1 -> 0 | S57: =(S$14>$D57)*(S$14<=$E57)*S$11*1 -> 0 | T57: =(T$14>$D57)*(T$14<=$E57)*T$11*1 -> 0 | U57: =(U$14>$D57)*(U$14<=$E57)*U$11*1 -> 1 | V57: =(V$14>$D57)*(V$14<=$E57)*V$11*1 -> 1 | W57: =(W$14>$D57)*(W$14<=$E57)*W$11*1 -> 1 | X57: =(X$14>$D57)*(X$14<=$E57)*X$11*1 -> 1 | Y57: =(Y$14>$D57)*(Y$14<=$E57)*Y$11*1 -> 1 | ... DL57: =(DL$14>$D57)*(DL$14<=$E57)*DL$11*1 -> 0
B58: =Rentroll!$C$56 -> 101호 | C58: =VLOOKUP($B58,Rentroll!$C$37:$Z$60,3,FALSE) -> 카페 1리터 | D58: =VLOOKUP($B58,Rentroll!$C$37:$Z$60,9,FALSE) -> 45838 | E58: =VLOOKUP($B58,Rentroll!$C$37:$Z$60,10,FALSE) -> 47634 | F58: =VLOOKUP($B58,Rentroll!$C$37:$Z$60,11,FALSE) -> 60 | G58: =VLOOKUP($B58,Rentroll!$C$37:$Z$60,13,FALSE) -> 150000 | H58: =VLOOKUP($B58,Rentroll!$C$37:$Z$60,14,FALSE) -> 150000 | I58: =VLOOKUP($B58,Rentroll!$C$37:$Z$60,15,FALSE) -> 45000 | J58: =VLOOKUP($B58,Rentroll!$C$37:$Z$60,19,FALSE) -> 0.03 | K58: =VLOOKUP($B58,Rentroll!$C$37:$Z$60,4,FALSE) -> 484.78 | L58: =VLOOKUP($B58,Rentroll!$C$37:$Z$60,17,FALSE) -> 1 | M58: =VLOOKUP($B58,Rentroll!$C$37:$Z$60,18,FALSE) -> 0 | O58: =B58 -> 101호 | R58: =(R$14>$D58)*(R$14<=$E58)*R$11*1 -> 0 | S58: =(S$14>$D58)*(S$14<=$E58)*S$11*1 -> 0 | T58: =(T$14>$D58)*(T$14<=$E58)*T$11*1 -> 0 | U58: =(U$14>$D58)*(U$14<=$E58)*U$11*1 -> 0 | V58: =(V$14>$D58)*(V$14<=$E58)*V$11*1 -> 0 | W58: =(W$14>$D58)*(W$14<=$E58)*W$11*1 -> 0 | X58: =(X$14>$D58)*(X$14<=$E58)*X$11*1 -> 1 | Y58: =(Y$14>$D58)*(Y$14<=$E58)*Y$11*1 -> 1 | ... DL58: =(DL$14>$D58)*(DL$14<=$E58)*DL$11*1 -> 0
B59: =Rentroll!$C$57 -> 102호 | C59: =VLOOKUP($B59,Rentroll!$C$37:$Z$60,3,FALSE) -> DOTZ | D59: =VLOOKUP($B59,Rentroll!$C$37:$Z$60,9,FALSE) -> 45838 | E59: =VLOOKUP($B59,Rentroll!$C$37:$Z$60,10,FALSE) -> 47634 | F59: =VLOOKUP($B59,Rentroll!$C$37:$Z$60,11,FALSE) -> 60 | G59: =VLOOKUP($B59,Rentroll!$C$37:$Z$60,13,FALSE) -> 150000 | H59: =VLOOKUP($B59,Rentroll!$C$37:$Z$60,14,FALSE) -> 150000 | I59: =VLOOKUP($B59,Rentroll!$C$37:$Z$60,15,FALSE) -> 45000 | J59: =VLOOKUP($B59,Rentroll!$C$37:$Z$60,19,FALSE) -> 0.03 | K59: =VLOOKUP($B59,Rentroll!$C$37:$Z$60,4,FALSE) -> 484.78 | L59: =VLOOKUP($B59,Rentroll!$C$37:$Z$60,17,FALSE) -> 1 | M59: =VLOOKUP($B59,Rentroll!$C$37:$Z$60,18,FALSE) -> 0 | O59: =B59 -> 102호 | R59: =(R$14>$D59)*(R$14<=$E59)*R$11*1 -> 0 | S59: =(S$14>$D59)*(S$14<=$E59)*S$11*1 -> 0 | T59: =(T$14>$D59)*(T$14<=$E59)*T$11*1 -> 0 | U59: =(U$14>$D59)*(U$14<=$E59)*U$11*1 -> 0 | V59: =(V$14>$D59)*(V$14<=$E59)*V$11*1 -> 0 | W59: =(W$14>$D59)*(W$14<=$E59)*W$11*1 -> 0 | X59: =(X$14>$D59)*(X$14<=$E59)*X$11*1 -> 1 | Y59: =(Y$14>$D59)*(Y$14<=$E59)*Y$11*1 -> 1 | ... DL59: =(DL$14>$D59)*(DL$14<=$E59)*DL$11*1 -> 0
B60: =Rentroll!$C$58 -> B101호 | C60: =VLOOKUP($B60,Rentroll!$C$37:$Z$60,3,FALSE) -> 편안창고 스토리지 | D60: =VLOOKUP($B60,Rentroll!$C$37:$Z$60,9,FALSE) -> 46752 | E60: =VLOOKUP($B60,Rentroll!$C$37:$Z$60,10,FALSE) -> 48579 | F60: =VLOOKUP($B60,Rentroll!$C$37:$Z$60,11,FALSE) -> 60 | G60: =VLOOKUP($B60,Rentroll!$C$37:$Z$60,13,FALSE) -> 52116.712 | H60: =VLOOKUP($B60,Rentroll!$C$37:$Z$60,14,FALSE) -> 52116.712 | I60: =VLOOKUP($B60,Rentroll!$C$37:$Z$60,15,FALSE) -> 40000 | J60: =VLOOKUP($B60,Rentroll!$C$37:$Z$60,19,FALSE) -> 0.03 | K60: =VLOOKUP($B60,Rentroll!$C$37:$Z$60,4,FALSE) -> 969.56 | L60: =VLOOKUP($B60,Rentroll!$C$37:$Z$60,17,FALSE) -> 1 | M60: =VLOOKUP($B60,Rentroll!$C$37:$Z$60,18,FALSE) -> 0 | O60: =B60 -> B101호 | R60: =(R$14>$D60)*(R$14<=$E60)*R$11*1 -> 0 | S60: =(S$14>$D60)*(S$14<=$E60)*S$11*1 -> 0 | T60: =(T$14>$D60)*(T$14<=$E60)*T$11*1 -> 0 | U60: =(U$14>$D60)*(U$14<=$E60)*U$11*1 -> 0 | V60: =(V$14>$D60)*(V$14<=$E60)*V$11*1 -> 0 | W60: =(W$14>$D60)*(W$14<=$E60)*W$11*1 -> 0 | X60: =(X$14>$D60)*(X$14<=$E60)*X$11*1 -> 0 | Y60: =(Y$14>$D60)*(Y$14<=$E60)*Y$11*1 -> 0 | ... DL60: =(DL$14>$D60)*(DL$14<=$E60)*DL$11*1 -> 0
B61: =Rentroll!$C$59 -> B102호 | C61: =VLOOKUP($B61,Rentroll!$C$37:$Z$60,3,FALSE) -> 스크린 퀀텀 | D61: =VLOOKUP($B61,Rentroll!$C$37:$Z$60,9,FALSE) -> 46418 | E61: =VLOOKUP($B61,Rentroll!$C$37:$Z$60,10,FALSE) -> 48244 | F61: =VLOOKUP($B61,Rentroll!$C$37:$Z$60,11,FALSE) -> 60 | G61: =VLOOKUP($B61,Rentroll!$C$37:$Z$60,13,FALSE) -> 52116.712 | H61: =VLOOKUP($B61,Rentroll!$C$37:$Z$60,14,FALSE) -> 52116.712 | I61: =VLOOKUP($B61,Rentroll!$C$37:$Z$60,15,FALSE) -> 40000 | J61: =VLOOKUP($B61,Rentroll!$C$37:$Z$60,19,FALSE) -> 0.03 | K61: =VLOOKUP($B61,Rentroll!$C$37:$Z$60,4,FALSE) -> 969.56 | L61: =VLOOKUP($B61,Rentroll!$C$37:$Z$60,17,FALSE) -> 1 | M61: =VLOOKUP($B61,Rentroll!$C$37:$Z$60,18,FALSE) -> 0 | O61: =B61 -> B102호 | R61: =(R$14>$D61)*(R$14<=$E61)*R$11*1 -> 0 | S61: =(S$14>$D61)*(S$14<=$E61)*S$11*1 -> 0 | T61: =(T$14>$D61)*(T$14<=$E61)*T$11*1 -> 0 | U61: =(U$14>$D61)*(U$14<=$E61)*U$11*1 -> 0 | V61: =(V$14>$D61)*(V$14<=$E61)*V$11*1 -> 0 | W61: =(W$14>$D61)*(W$14<=$E61)*W$11*1 -> 0 | X61: =(X$14>$D61)*(X$14<=$E61)*X$11*1 -> 0 | Y61: =(Y$14>$D61)*(Y$14<=$E61)*Y$11*1 -> 0 | ... DL61: =(DL$14>$D61)*(DL$14<=$E61)*DL$11*1 -> 0
B62: =Rentroll!$C$60 -> 0 | C62: =VLOOKUP($B62,Rentroll!$C$37:$Z$60,3,FALSE) -> 0 | D62: =VLOOKUP($B62,Rentroll!$C$37:$Z$60,9,FALSE) -> 0 | E62: =VLOOKUP($B62,Rentroll!$C$37:$Z$60,10,FALSE) -> 0 | F62: =VLOOKUP($B62,Rentroll!$C$37:$Z$60,11,FALSE) -> 0 | G62: =VLOOKUP($B62,Rentroll!$C$37:$Z$60,13,FALSE) -> 0 | H62: =VLOOKUP($B62,Rentroll!$C$37:$Z$60,14,FALSE) -> 0 | I62: =VLOOKUP($B62,Rentroll!$C$37:$Z$60,15,FALSE) -> 0 | J62: =VLOOKUP($B62,Rentroll!$C$37:$Z$60,19,FALSE) -> 0 | K62: =VLOOKUP($B62,Rentroll!$C$37:$Z$60,4,FALSE) -> 0 | L62: =VLOOKUP($B62,Rentroll!$C$37:$Z$60,17,FALSE) -> 0 | M62: =VLOOKUP($B62,Rentroll!$C$37:$Z$60,18,FALSE) -> 0 | O62: =B62 -> 0 | R62: =(R$14>$D62)*(R$14<=$E62)*R$11*1 -> 0 | S62: =(S$14>$D62)*(S$14<=$E62)*S$11*1 -> 0 | T62: =(T$14>$D62)*(T$14<=$E62)*T$11*1 -> 0 | U62: =(U$14>$D62)*(U$14<=$E62)*U$11*1 -> 0 | V62: =(V$14>$D62)*(V$14<=$E62)*V$11*1 -> 0 | W62: =(W$14>$D62)*(W$14<=$E62)*W$11*1 -> 0 | X62: =(X$14>$D62)*(X$14<=$E62)*X$11*1 -> 0 | Y62: =(Y$14>$D62)*(Y$14<=$E62)*Y$11*1 -> 0 | ... DL62: =(DL$14>$D62)*(DL$14<=$E62)*DL$11*1 -> 0
B64: 현(위) 및 신규(아래) 임대차 계약 | O64: Fit-out기간 Index
B65: 층수 | C65: 임차인 | D65: 시작일 | E65: 종료일 | F65: 기간 | G65: 명목 임대료(원) | H65: 실질 임대료(원) | I65: 관리비(원) | J65: 상승률 | K65: 임대면적(㎡) | L65: Fitout | M65: Rentfree | O65: 기존 임대차
B66: =Rentroll!$C$11 -> 17 | C66: =VLOOKUP($B66,Rentroll!$C$11:$X$29,3,FALSE) -> 리마 상사 | D66: =VLOOKUP($B66,Rentroll!$C$11:$X$29,9,FALSE) -> 45322 | E66: =VLOOKUP($B66,Rentroll!$C$11:$X$29,10,FALSE) -> 47148 | F66: =VLOOKUP($B66,Rentroll!$C$11:$X$29,11,FALSE) -> 60 | G66: =VLOOKUP($B66,Rentroll!$C$11:$X$29,13,FALSE) -> 100000 | H66: =VLOOKUP($B66,Rentroll!$C$11:$X$29,14,FALSE) -> 75000 | I66: =VLOOKUP($B66,Rentroll!$C$11:$X$29,15,FALSE) -> 45000 | J66: =VLOOKUP($B66,Rentroll!$C$11:$X$29,19,FALSE) -> 0.03 | K66: =VLOOKUP($B66,Rentroll!$C$11:$X$29,4,FALSE) -> 1385.09 | L66: =VLOOKUP($B66,Rentroll!$C$11:$X$29,17,FALSE) -> 0 | M66: =VLOOKUP($B66,Rentroll!$C$11:$X$29,18,FALSE) -> 3 | O66: =B66 -> 17 | R66: 0 | S66: 0 | T66: 0 | U66: 0 | V66: 0 | W66: 0 | X66: 0 | Y66: 0 | Z66: 0 | AA66: 0 | AB66: 0 | AC66: 0 | AD66: 0 | AE66: 0 | AF66: 0 | AG66: 0 | AH66: 0 | AI66: 0 | AJ66: 0 | AK66: 0 | AL66: 0 | AM66: 0 | AN66: 0 | AO66: 0 | AP66: 0 | AQ66: 0 | AR66: 0 | AS66: 0 | AT66: 0 | AU66: 0 | AV66: 0 | AW66: 0 | AX66: 0 | AY66: 0 | AZ66: 0 | BA66: 0 | BB66: 0 | BC66: 0 | BD66: 0 | BE66: 0 | BF66: 0 | BG66: 0 | BH66: 0 | BI66: 0 | BJ66: 0 | BK66: 0 | BL66: 0 | BM66: 0 | BN66: 0 | BO66: 0 | BP66: 0 | BQ66: 0 | BR66: 0 | BS66: 0 | BT66: 0 | BU66: 0 | BV66: 0 | BW66: 0 | BX66: 0 | BY66: 0 | BZ66: 0 | CA66: 0 | CB66: 0 | CC66: 0 | CD66: 0 | CE66: 0 | CF66: 0 | CG66: 0 | CH66: 0 | CI66: 0 | CJ66: 0 | CK66: 0 | CL66: 0 | CM66: 0 | CN66: 0 | CO66: 0 | CP66: 0 | CQ66: 0 | CR66: 0 | CS66: 0 | CT66: 0 | CU66: 0 | CV66: 0 | CW66: 0 | CX66: 0 | CY66: 0 | CZ66: 0 | DA66: 0 | DB66: 0 | DC66: 0 | DD66: 0 | DE66: 0 | DF66: 0 | DG66: 0 | DH66: 0 | DI66: 0 | DJ66: 0 | DK66: 0 | DL66: 0
B67: =Rentroll!$C$12 -> 16 | C67: =VLOOKUP($B67,Rentroll!$C$11:$X$29,3,FALSE) -> 리마 상사 | D67: =VLOOKUP($B67,Rentroll!$C$11:$X$29,9,FALSE) -> 45322 | E67: =VLOOKUP($B67,Rentroll!$C$11:$X$29,10,FALSE) -> 47148 | F67: =VLOOKUP($B67,Rentroll!$C$11:$X$29,11,FALSE) -> 60 | G67: =VLOOKUP($B67,Rentroll!$C$11:$X$29,13,FALSE) -> 100000 | H67: =VLOOKUP($B67,Rentroll!$C$11:$X$29,14,FALSE) -> 75000 | I67: =VLOOKUP($B67,Rentroll!$C$11:$X$29,15,FALSE) -> 45000 | J67: =VLOOKUP($B67,Rentroll!$C$11:$X$29,19,FALSE) -> 0.03 | K67: =VLOOKUP($B67,Rentroll!$C$11:$X$29,4,FALSE) -> 1385.09 | L67: =VLOOKUP($B67,Rentroll!$C$11:$X$29,17,FALSE) -> 0 | M67: =VLOOKUP($B67,Rentroll!$C$11:$X$29,18,FALSE) -> 3 | O67: =B67 -> 16 | R67: 0 | S67: 0 | T67: 0 | U67: 0 | V67: 0 | W67: 0 | X67: 0 | Y67: 0 | Z67: 0 | AA67: 0 | AB67: 0 | AC67: 0 | AD67: 0 | AE67: 0 | AF67: 0 | AG67: 0 | AH67: 0 | AI67: 0 | AJ67: 0 | AK67: 0 | AL67: 0 | AM67: 0 | AN67: 0 | AO67: 0 | AP67: 0 | AQ67: 0 | AR67: 0 | AS67: 0 | AT67: 0 | AU67: 0 | AV67: 0 | AW67: 0 | AX67: 0 | AY67: 0 | AZ67: 0 | BA67: 0 | BB67: 0 | BC67: 0 | BD67: 0 | BE67: 0 | BF67: 0 | BG67: 0 | BH67: 0 | BI67: 0 | BJ67: 0 | BK67: 0 | BL67: 0 | BM67: 0 | BN67: 0 | BO67: 0 | BP67: 0 | BQ67: 0 | BR67: 0 | BS67: 0 | BT67: 0 | BU67: 0 | BV67: 0 | BW67: 0 | BX67: 0 | BY67: 0 | BZ67: 0 | CA67: 0 | CB67: 0 | CC67: 0 | CD67: 0 | CE67: 0 | CF67: 0 | CG67: 0 | CH67: 0 | CI67: 0 | CJ67: 0 | CK67: 0 | CL67: 0 | CM67: 0 | CN67: 0 | CO67: 0 | CP67: 0 | CQ67: 0 | CR67: 0 | CS67: 0 | CT67: 0 | CU67: 0 | CV67: 0 | CW67: 0 | CX67: 0 | CY67: 0 | CZ67: 0 | DA67: 0 | DB67: 0 | DC67: 0 | DD67: 0 | DE67: 0 | DF67: 0 | DG67: 0 | DH67: 0 | DI67: 0 | DJ67: 0 | DK67: 0 | DL67: 0
B68: =Rentroll!$C$13 -> 15 | C68: =VLOOKUP($B68,Rentroll!$C$11:$X$29,3,FALSE) -> 모빌리티 테크놀로지 | D68: =VLOOKUP($B68,Rentroll!$C$11:$X$29,9,FALSE) -> 44042 | E68: =VLOOKUP($B68,Rentroll!$C$11:$X$29,10,FALSE) -> 45869 | F68: =VLOOKUP($B68,Rentroll!$C$11:$X$29,11,FALSE) -> 60 | G68: =VLOOKUP($B68,Rentroll!$C$11:$X$29,13,FALSE) -> 90041 | H68: =VLOOKUP($B68,Rentroll!$C$11:$X$29,14,FALSE) -> 67530.75 | I68: =VLOOKUP($B68,Rentroll!$C$11:$X$29,15,FALSE) -> 45020 | J68: =VLOOKUP($B68,Rentroll!$C$11:$X$29,19,FALSE) -> 0.03 | K68: =VLOOKUP($B68,Rentroll!$C$11:$X$29,4,FALSE) -> 1385.09 | L68: =VLOOKUP($B68,Rentroll!$C$11:$X$29,17,FALSE) -> 0 | M68: =VLOOKUP($B68,Rentroll!$C$11:$X$29,18,FALSE) -> 3 | O68: =B68 -> 15 | R68: 0 | S68: 0 | T68: 0 | U68: 0 | V68: 0 | W68: 0 | X68: 0 | Y68: 0 | Z68: 0 | AA68: 0 | AB68: 0 | AC68: 0 | AD68: 0 | AE68: 0 | AF68: 0 | AG68: 0 | AH68: 0 | AI68: 0 | AJ68: 0 | AK68: 0 | AL68: 0 | AM68: 0 | AN68: 0 | AO68: 0 | AP68: 0 | AQ68: 0 | AR68: 0 | AS68: 0 | AT68: 0 | AU68: 0 | AV68: 0 | AW68: 0 | AX68: 0 | AY68: 0 | AZ68: 0 | BA68: 0 | BB68: 0 | BC68: 0 | BD68: 0 | BE68: 0 | BF68: 0 | BG68: 0 | BH68: 0 | BI68: 0 | BJ68: 0 | BK68: 0 | BL68: 0 | BM68: 0 | BN68: 0 | BO68: 0 | BP68: 0 | BQ68: 0 | BR68: 0 | BS68: 0 | BT68: 0 | BU68: 0 | BV68: 0 | BW68: 0 | BX68: 0 | BY68: 0 | BZ68: 0 | CA68: 0 | CB68: 0 | CC68: 0 | CD68: 0 | CE68: 0 | CF68: 0 | CG68: 0 | CH68: 0 | CI68: 0 | CJ68: 0 | CK68: 0 | CL68: 0 | CM68: 0 | CN68: 0 | CO68: 0 | CP68: 0 | CQ68: 0 | CR68: 0 | CS68: 0 | CT68: 0 | CU68: 0 | CV68: 0 | CW68: 0 | CX68: 0 | CY68: 0 | CZ68: 0 | DA68: 0 | DB68: 0 | DC68: 0 | DD68: 0 | DE68: 0 | DF68: 0 | DG68: 0 | DH68: 0 | DI68: 0 | DJ68: 0 | DK68: 0 | DL68: 0
B69: =Rentroll!$C$14 -> 14 | C69: =VLOOKUP($B69,Rentroll!$C$11:$X$29,3,FALSE) -> 모빌리티 테크놀로지 | D69: =VLOOKUP($B69,Rentroll!$C$11:$X$29,9,FALSE) -> 44043 | E69: =VLOOKUP($B69,Rentroll!$C$11:$X$29,10,FALSE) -> 45868 | F69: =VLOOKUP($B69,Rentroll!$C$11:$X$29,11,FALSE) -> 60 | G69: =VLOOKUP($B69,Rentroll!$C$11:$X$29,13,FALSE) -> 90041 | H69: =VLOOKUP($B69,Rentroll!$C$11:$X$29,14,FALSE) -> 67530.75 | I69: =VLOOKUP($B69,Rentroll!$C$11:$X$29,15,FALSE) -> 45020 | J69: =VLOOKUP($B69,Rentroll!$C$11:$X$29,19,FALSE) -> 0.03 | K69: =VLOOKUP($B69,Rentroll!$C$11:$X$29,4,FALSE) -> 1385.09 | L69: =VLOOKUP($B69,Rentroll!$C$11:$X$29,17,FALSE) -> 0 | M69: =VLOOKUP($B69,Rentroll!$C$11:$X$29,18,FALSE) -> 3 | O69: =B69 -> 14 | R69: 0 | S69: 0 | T69: 0 | U69: 0 | V69: 0 | W69: 0 | X69: 0 | Y69: 0 | Z69: 0 | AA69: 0 | AB69: 0 | AC69: 0 | AD69: 0 | AE69: 0 | AF69: 0 | AG69: 0 | AH69: 0 | AI69: 0 | AJ69: 0 | AK69: 0 | AL69: 0 | AM69: 0 | AN69: 0 | AO69: 0 | AP69: 0 | AQ69: 0 | AR69: 0 | AS69: 0 | AT69: 0 | AU69: 0 | AV69: 0 | AW69: 0 | AX69: 0 | AY69: 0 | AZ69: 0 | BA69: 0 | BB69: 0 | BC69: 0 | BD69: 0 | BE69: 0 | BF69: 0 | BG69: 0 | BH69: 0 | BI69: 0 | BJ69: 0 | BK69: 0 | BL69: 0 | BM69: 0 | BN69: 0 | BO69: 0 | BP69: 0 | BQ69: 0 | BR69: 0 | BS69: 0 | BT69: 0 | BU69: 0 | BV69: 0 | BW69: 0 | BX69: 0 | BY69: 0 | BZ69: 0 | CA69: 0 | CB69: 0 | CC69: 0 | CD69: 0 | CE69: 0 | CF69: 0 | CG69: 0 | CH69: 0 | CI69: 0 | CJ69: 0 | CK69: 0 | CL69: 0 | CM69: 0 | CN69: 0 | CO69: 0 | CP69: 0 | CQ69: 0 | CR69: 0 | CS69: 0 | CT69: 0 | CU69: 0 | CV69: 0 | CW69: 0 | CX69: 0 | CY69: 0 | CZ69: 0 | DA69: 0 | DB69: 0 | DC69: 0 | DD69: 0 | DE69: 0 | DF69: 0 | DG69: 0 | DH69: 0 | DI69: 0 | DJ69: 0 | DK69: 0 | DL69: 0
B70: =Rentroll!$C$15 -> 13 | C70: =VLOOKUP($B70,Rentroll!$C$11:$X$29,3,FALSE) -> 모빌리티 테크놀로지 | D70: =VLOOKUP($B70,Rentroll!$C$11:$X$29,9,FALSE) -> 44043 | E70: =VLOOKUP($B70,Rentroll!$C$11:$X$29,10,FALSE) -> 45868 | F70: =VLOOKUP($B70,Rentroll!$C$11:$X$29,11,FALSE) -> 60 | G70: =VLOOKUP($B70,Rentroll!$C$11:$X$29,13,FALSE) -> 90041 | H70: =VLOOKUP($B70,Rentroll!$C$11:$X$29,14,FALSE) -> 67530.75 | I70: =VLOOKUP($B70,Rentroll!$C$11:$X$29,15,FALSE) -> 45020 | J70: =VLOOKUP($B70,Rentroll!$C$11:$X$29,19,FALSE) -> 0.03 | K70: =VLOOKUP($B70,Rentroll!$C$11:$X$29,4,FALSE) -> 1385.09 | L70: =VLOOKUP($B70,Rentroll!$C$11:$X$29,17,FALSE) -> 0 | M70: =VLOOKUP($B70,Rentroll!$C$11:$X$29,18,FALSE) -> 3 | O70: =B70 -> 13 | R70: 0 | S70: 0 | T70: 0 | U70: 0 | V70: 0 | W70: 0 | X70: 0 | Y70: 0 | Z70: 0 | AA70: 0 | AB70: 0 | AC70: 0 | AD70: 0 | AE70: 0 | AF70: 0 | AG70: 0 | AH70: 0 | AI70: 0 | AJ70: 0 | AK70: 0 | AL70: 0 | AM70: 0 | AN70: 0 | AO70: 0 | AP70: 0 | AQ70: 0 | AR70: 0 | AS70: 0 | AT70: 0 | AU70: 0 | AV70: 0 | AW70: 0 | AX70: 0 | AY70: 0 | AZ70: 0 | BA70: 0 | BB70: 0 | BC70: 0 | BD70: 0 | BE70: 0 | BF70: 0 | BG70: 0 | BH70: 0 | BI70: 0 | BJ70: 0 | BK70: 0 | BL70: 0 | BM70: 0 | BN70: 0 | BO70: 0 | BP70: 0 | BQ70: 0 | BR70: 0 | BS70: 0 | BT70: 0 | BU70: 0 | BV70: 0 | BW70: 0 | BX70: 0 | BY70: 0 | BZ70: 0 | CA70: 0 | CB70: 0 | CC70: 0 | CD70: 0 | CE70: 0 | CF70: 0 | CG70: 0 | CH70: 0 | CI70: 0 | CJ70: 0 | CK70: 0 | CL70: 0 | CM70: 0 | CN70: 0 | CO70: 0 | CP70: 0 | CQ70: 0 | CR70: 0 | CS70: 0 | CT70: 0 | CU70: 0 | CV70: 0 | CW70: 0 | CX70: 0 | CY70: 0 | CZ70: 0 | DA70: 0 | DB70: 0 | DC70: 0 | DD70: 0 | DE70: 0 | DF70: 0 | DG70: 0 | DH70: 0 | DI70: 0 | DJ70: 0 | DK70: 0 | DL70: 0
B71: =Rentroll!$C$16 -> 12 | C71: =VLOOKUP($B71,Rentroll!$C$11:$X$29,3,FALSE) -> 모빌리티 테크놀로지 | D71: =VLOOKUP($B71,Rentroll!$C$11:$X$29,9,FALSE) -> 44043 | E71: =VLOOKUP($B71,Rentroll!$C$11:$X$29,10,FALSE) -> 45868 | F71: =VLOOKUP($B71,Rentroll!$C$11:$X$29,11,FALSE) -> 60 | G71: =VLOOKUP($B71,Rentroll!$C$11:$X$29,13,FALSE) -> 90041 | H71: =VLOOKUP($B71,Rentroll!$C$11:$X$29,14,FALSE) -> 67530.75 | I71: =VLOOKUP($B71,Rentroll!$C$11:$X$29,15,FALSE) -> 45020 | J71: =VLOOKUP($B71,Rentroll!$C$11:$X$29,19,FALSE) -> 0.03 | K71: =VLOOKUP($B71,Rentroll!$C$11:$X$29,4,FALSE) -> 1385.09 | L71: =VLOOKUP($B71,Rentroll!$C$11:$X$29,17,FALSE) -> 0 | M71: =VLOOKUP($B71,Rentroll!$C$11:$X$29,18,FALSE) -> 3 | O71: =B71 -> 12 | R71: 0 | S71: 0 | T71: 0 | U71: 0 | V71: 0 | W71: 0 | X71: 0 | Y71: 0 | Z71: 0 | AA71: 0 | AB71: 0 | AC71: 0 | AD71: 0 | AE71: 0 | AF71: 0 | AG71: 0 | AH71: 0 | AI71: 0 | AJ71: 0 | AK71: 0 | AL71: 0 | AM71: 0 | AN71: 0 | AO71: 0 | AP71: 0 | AQ71: 0 | AR71: 0 | AS71: 0 | AT71: 0 | AU71: 0 | AV71: 0 | AW71: 0 | AX71: 0 | AY71: 0 | AZ71: 0 | BA71: 0 | BB71: 0 | BC71: 0 | BD71: 0 | BE71: 0 | BF71: 0 | BG71: 0 | BH71: 0 | BI71: 0 | BJ71: 0 | BK71: 0 | BL71: 0 | BM71: 0 | BN71: 0 | BO71: 0 | BP71: 0 | BQ71: 0 | BR71: 0 | BS71: 0 | BT71: 0 | BU71: 0 | BV71: 0 | BW71: 0 | BX71: 0 | BY71: 0 | BZ71: 0 | CA71: 0 | CB71: 0 | CC71: 0 | CD71: 0 | CE71: 0 | CF71: 0 | CG71: 0 | CH71: 0 | CI71: 0 | CJ71: 0 | CK71: 0 | CL71: 0 | CM71: 0 | CN71: 0 | CO71: 0 | CP71: 0 | CQ71: 0 | CR71: 0 | CS71: 0 | CT71: 0 | CU71: 0 | CV71: 0 | CW71: 0 | CX71: 0 | CY71: 0 | CZ71: 0 | DA71: 0 | DB71: 0 | DC71: 0 | DD71: 0 | DE71: 0 | DF71: 0 | DG71: 0 | DH71: 0 | DI71: 0 | DJ71: 0 | DK71: 0 | DL71: 0
B72: =Rentroll!$C$17 -> 11 | C72: =VLOOKUP($B72,Rentroll!$C$11:$X$29,3,FALSE) -> 노벰버 건설 | D72: =VLOOKUP($B72,Rentroll!$C$11:$X$29,9,FALSE) -> 45077 | E72: =VLOOKUP($B72,Rentroll!$C$11:$X$29,10,FALSE) -> 46903 | F72: =VLOOKUP($B72,Rentroll!$C$11:$X$29,11,FALSE) -> 60 | G72: =VLOOKUP($B72,Rentroll!$C$11:$X$29,13,FALSE) -> 103000 | H72: =VLOOKUP($B72,Rentroll!$C$11:$X$29,14,FALSE) -> 85833.333 | I72: =VLOOKUP($B72,Rentroll!$C$11:$X$29,15,FALSE) -> 46350 | J72: =VLOOKUP($B72,Rentroll!$C$11:$X$29,19,FALSE) -> 0.03 | K72: =VLOOKUP($B72,Rentroll!$C$11:$X$29,4,FALSE) -> 1385.09 | L72: =VLOOKUP($B72,Rentroll!$C$11:$X$29,17,FALSE) -> 0 | M72: =VLOOKUP($B72,Rentroll!$C$11:$X$29,18,FALSE) -> 2 | O72: =B72 -> 11 | R72: 0 | S72: 0 | T72: 0 | U72: 0 | V72: 0 | W72: 0 | X72: 0 | Y72: 0 | Z72: 0 | AA72: 0 | AB72: 0 | AC72: 0 | AD72: 0 | AE72: 0 | AF72: 0 | AG72: 0 | AH72: 0 | AI72: 0 | AJ72: 0 | AK72: 0 | AL72: 0 | AM72: 0 | AN72: 0 | AO72: 0 | AP72: 0 | AQ72: 0 | AR72: 0 | AS72: 0 | AT72: 0 | AU72: 0 | AV72: 0 | AW72: 0 | AX72: 0 | AY72: 0 | AZ72: 0 | BA72: 0 | BB72: 0 | BC72: 0 | BD72: 0 | BE72: 0 | BF72: 0 | BG72: 0 | BH72: 0 | BI72: 0 | BJ72: 0 | BK72: 0 | BL72: 0 | BM72: 0 | BN72: 0 | BO72: 0 | BP72: 0 | BQ72: 0 | BR72: 0 | BS72: 0 | BT72: 0 | BU72: 0 | BV72: 0 | BW72: 0 | BX72: 0 | BY72: 0 | BZ72: 0 | CA72: 0 | CB72: 0 | CC72: 0 | CD72: 0 | CE72: 0 | CF72: 0 | CG72: 0 | CH72: 0 | CI72: 0 | CJ72: 0 | CK72: 0 | CL72: 0 | CM72: 0 | CN72: 0 | CO72: 0 | CP72: 0 | CQ72: 0 | CR72: 0 | CS72: 0 | CT72: 0 | CU72: 0 | CV72: 0 | CW72: 0 | CX72: 0 | CY72: 0 | CZ72: 0 | DA72: 0 | DB72: 0 | DC72: 0 | DD72: 0 | DE72: 0 | DF72: 0 | DG72: 0 | DH72: 0 | DI72: 0 | DJ72: 0 | DK72: 0 | DL72: 0
B73: =Rentroll!$C$18 -> 10 | C73: =VLOOKUP($B73,Rentroll!$C$11:$X$29,3,FALSE) -> 노벰버 건설 | D73: =VLOOKUP($B73,Rentroll!$C$11:$X$29,9,FALSE) -> 45077 | E73: =VLOOKUP($B73,Rentroll!$C$11:$X$29,10,FALSE) -> 46903 | F73: =VLOOKUP($B73,Rentroll!$C$11:$X$29,11,FALSE) -> 60 | G73: =VLOOKUP($B73,Rentroll!$C$11:$X$29,13,FALSE) -> 103000 | H73: =VLOOKUP($B73,Rentroll!$C$11:$X$29,14,FALSE) -> 85833.333 | I73: =VLOOKUP($B73,Rentroll!$C$11:$X$29,15,FALSE) -> 46350 | J73: =VLOOKUP($B73,Rentroll!$C$11:$X$29,19,FALSE) -> 0.03 | K73: =VLOOKUP($B73,Rentroll!$C$11:$X$29,4,FALSE) -> 1385.09 | L73: =VLOOKUP($B73,Rentroll!$C$11:$X$29,17,FALSE) -> 0 | M73: =VLOOKUP($B73,Rentroll!$C$11:$X$29,18,FALSE) -> 2 | O73: =B73 -> 10 | R73: 0 | S73: 0 | T73: 0 | U73: 0 | V73: 0 | W73: 0 | X73: 0 | Y73: 0 | Z73: 0 | AA73: 0 | AB73: 0 | AC73: 0 | AD73: 0 | AE73: 0 | AF73: 0 | AG73: 0 | AH73: 0 | AI73: 0 | AJ73: 0 | AK73: 0 | AL73: 0 | AM73: 0 | AN73: 0 | AO73: 0 | AP73: 0 | AQ73: 0 | AR73: 0 | AS73: 0 | AT73: 0 | AU73: 0 | AV73: 0 | AW73: 0 | AX73: 0 | AY73: 0 | AZ73: 0 | BA73: 0 | BB73: 0 | BC73: 0 | BD73: 0 | BE73: 0 | BF73: 0 | BG73: 0 | BH73: 0 | BI73: 0 | BJ73: 0 | BK73: 0 | BL73: 0 | BM73: 0 | BN73: 0 | BO73: 0 | BP73: 0 | BQ73: 0 | BR73: 0 | BS73: 0 | BT73: 0 | BU73: 0 | BV73: 0 | BW73: 0 | BX73: 0 | BY73: 0 | BZ73: 0 | CA73: 0 | CB73: 0 | CC73: 0 | CD73: 0 | CE73: 0 | CF73: 0 | CG73: 0 | CH73: 0 | CI73: 0 | CJ73: 0 | CK73: 0 | CL73: 0 | CM73: 0 | CN73: 0 | CO73: 0 | CP73: 0 | CQ73: 0 | CR73: 0 | CS73: 0 | CT73: 0 | CU73: 0 | CV73: 0 | CW73: 0 | CX73: 0 | CY73: 0 | CZ73: 0 | DA73: 0 | DB73: 0 | DC73: 0 | DD73: 0 | DE73: 0 | DF73: 0 | DG73: 0 | DH73: 0 | DI73: 0 | DJ73: 0 | DK73: 0 | DL73: 0
B74: =Rentroll!$C$19 -> 9 | C74: =VLOOKUP($B74,Rentroll!$C$11:$X$29,3,FALSE) -> 노벰버 건설 | D74: =VLOOKUP($B74,Rentroll!$C$11:$X$29,9,FALSE) -> 45077 | E74: =VLOOKUP($B74,Rentroll!$C$11:$X$29,10,FALSE) -> 46903 | F74: =VLOOKUP($B74,Rentroll!$C$11:$X$29,11,FALSE) -> 60 | G74: =VLOOKUP($B74,Rentroll!$C$11:$X$29,13,FALSE) -> 103000 | H74: =VLOOKUP($B74,Rentroll!$C$11:$X$29,14,FALSE) -> 85833.333 | I74: =VLOOKUP($B74,Rentroll!$C$11:$X$29,15,FALSE) -> 46350 | J74: =VLOOKUP($B74,Rentroll!$C$11:$X$29,19,FALSE) -> 0.03 | K74: =VLOOKUP($B74,Rentroll!$C$11:$X$29,4,FALSE) -> 1385.09 | L74: =VLOOKUP($B74,Rentroll!$C$11:$X$29,17,FALSE) -> 0 | M74: =VLOOKUP($B74,Rentroll!$C$11:$X$29,18,FALSE) -> 2 | O74: =B74 -> 9 | R74: 0 | S74: 0 | T74: 0 | U74: 0 | V74: 0 | W74: 0 | X74: 0 | Y74: 0 | Z74: 0 | AA74: 0 | AB74: 0 | AC74: 0 | AD74: 0 | AE74: 0 | AF74: 0 | AG74: 0 | AH74: 0 | AI74: 0 | AJ74: 0 | AK74: 0 | AL74: 0 | AM74: 0 | AN74: 0 | AO74: 0 | AP74: 0 | AQ74: 0 | AR74: 0 | AS74: 0 | AT74: 0 | AU74: 0 | AV74: 0 | AW74: 0 | AX74: 0 | AY74: 0 | AZ74: 0 | BA74: 0 | BB74: 0 | BC74: 0 | BD74: 0 | BE74: 0 | BF74: 0 | BG74: 0 | BH74: 0 | BI74: 0 | BJ74: 0 | BK74: 0 | BL74: 0 | BM74: 0 | BN74: 0 | BO74: 0 | BP74: 0 | BQ74: 0 | BR74: 0 | BS74: 0 | BT74: 0 | BU74: 0 | BV74: 0 | BW74: 0 | BX74: 0 | BY74: 0 | BZ74: 0 | CA74: 0 | CB74: 0 | CC74: 0 | CD74: 0 | CE74: 0 | CF74: 0 | CG74: 0 | CH74: 0 | CI74: 0 | CJ74: 0 | CK74: 0 | CL74: 0 | CM74: 0 | CN74: 0 | CO74: 0 | CP74: 0 | CQ74: 0 | CR74: 0 | CS74: 0 | CT74: 0 | CU74: 0 | CV74: 0 | CW74: 0 | CX74: 0 | CY74: 0 | CZ74: 0 | DA74: 0 | DB74: 0 | DC74: 0 | DD74: 0 | DE74: 0 | DF74: 0 | DG74: 0 | DH74: 0 | DI74: 0 | DJ74: 0 | DK74: 0 | DL74: 0
B75: =Rentroll!$C$20 -> 8 | C75: =VLOOKUP($B75,Rentroll!$C$11:$X$29,3,FALSE) -> 오토 커머셜 | D75: =VLOOKUP($B75,Rentroll!$C$11:$X$29,9,FALSE) -> 44651 | E75: =VLOOKUP($B75,Rentroll!$C$11:$X$29,10,FALSE) -> 46476 | F75: =VLOOKUP($B75,Rentroll!$C$11:$X$29,11,FALSE) -> 60 | G75: =VLOOKUP($B75,Rentroll!$C$11:$X$29,13,FALSE) -> 95481 | H75: =VLOOKUP($B75,Rentroll!$C$11:$X$29,14,FALSE) -> 87524.25 | I75: =VLOOKUP($B75,Rentroll!$C$11:$X$29,15,FALSE) -> 42436 | J75: =VLOOKUP($B75,Rentroll!$C$11:$X$29,19,FALSE) -> 0.03 | K75: =VLOOKUP($B75,Rentroll!$C$11:$X$29,4,FALSE) -> 1385.09 | L75: =VLOOKUP($B75,Rentroll!$C$11:$X$29,17,FALSE) -> 0 | M75: =VLOOKUP($B75,Rentroll!$C$11:$X$29,18,FALSE) -> 1 | O75: =B75 -> 8 | R75: 0 | S75: 0 | T75: 0 | U75: 0 | V75: 0 | W75: 0 | X75: 0 | Y75: 0 | Z75: 0 | AA75: 0 | AB75: 0 | AC75: 0 | AD75: 0 | AE75: 0 | AF75: 0 | AG75: 0 | AH75: 0 | AI75: 0 | AJ75: 0 | AK75: 0 | AL75: 0 | AM75: 0 | AN75: 0 | AO75: 0 | AP75: 0 | AQ75: 0 | AR75: 0 | AS75: 0 | AT75: 0 | AU75: 0 | AV75: 0 | AW75: 0 | AX75: 0 | AY75: 0 | AZ75: 0 | BA75: 0 | BB75: 0 | BC75: 0 | BD75: 0 | BE75: 0 | BF75: 0 | BG75: 0 | BH75: 0 | BI75: 0 | BJ75: 0 | BK75: 0 | BL75: 0 | BM75: 0 | BN75: 0 | BO75: 0 | BP75: 0 | BQ75: 0 | BR75: 0 | BS75: 0 | BT75: 0 | BU75: 0 | BV75: 0 | BW75: 0 | BX75: 0 | BY75: 0 | BZ75: 0 | CA75: 0 | CB75: 0 | CC75: 0 | CD75: 0 | CE75: 0 | CF75: 0 | CG75: 0 | CH75: 0 | CI75: 0 | CJ75: 0 | CK75: 0 | CL75: 0 | CM75: 0 | CN75: 0 | CO75: 0 | CP75: 0 | CQ75: 0 | CR75: 0 | CS75: 0 | CT75: 0 | CU75: 0 | CV75: 0 | CW75: 0 | CX75: 0 | CY75: 0 | CZ75: 0 | DA75: 0 | DB75: 0 | DC75: 0 | DD75: 0 | DE75: 0 | DF75: 0 | DG75: 0 | DH75: 0 | DI75: 0 | DJ75: 0 | DK75: 0 | DL75: 0
B76: =Rentroll!$C$21 -> 7 | C76: =VLOOKUP($B76,Rentroll!$C$11:$X$29,3,FALSE) -> 오토 커머셜 | D76: =VLOOKUP($B76,Rentroll!$C$11:$X$29,9,FALSE) -> 44651 | E76: =VLOOKUP($B76,Rentroll!$C$11:$X$29,10,FALSE) -> 46476 | F76: =VLOOKUP($B76,Rentroll!$C$11:$X$29,11,FALSE) -> 60 | G76: =VLOOKUP($B76,Rentroll!$C$11:$X$29,13,FALSE) -> 95481 | H76: =VLOOKUP($B76,Rentroll!$C$11:$X$29,14,FALSE) -> 87524.25 | I76: =VLOOKUP($B76,Rentroll!$C$11:$X$29,15,FALSE) -> 42436 | J76: =VLOOKUP($B76,Rentroll!$C$11:$X$29,19,FALSE) -> 0.03 | K76: =VLOOKUP($B76,Rentroll!$C$11:$X$29,4,FALSE) -> 1385.09 | L76: =VLOOKUP($B76,Rentroll!$C$11:$X$29,17,FALSE) -> 0 | M76: =VLOOKUP($B76,Rentroll!$C$11:$X$29,18,FALSE) -> 1 | O76: =B76 -> 7 | R76: 0 | S76: 0 | T76: 0 | U76: 0 | V76: 0 | W76: 0 | X76: 0 | Y76: 0 | Z76: 0 | AA76: 0 | AB76: 0 | AC76: 0 | AD76: 0 | AE76: 0 | AF76: 0 | AG76: 0 | AH76: 0 | AI76: 0 | AJ76: 0 | AK76: 0 | AL76: 0 | AM76: 0 | AN76: 0 | AO76: 0 | AP76: 0 | AQ76: 0 | AR76: 0 | AS76: 0 | AT76: 0 | AU76: 0 | AV76: 0 | AW76: 0 | AX76: 0 | AY76: 0 | AZ76: 0 | BA76: 0 | BB76: 0 | BC76: 0 | BD76: 0 | BE76: 0 | BF76: 0 | BG76: 0 | BH76: 0 | BI76: 0 | BJ76: 0 | BK76: 0 | BL76: 0 | BM76: 0 | BN76: 0 | BO76: 0 | BP76: 0 | BQ76: 0 | BR76: 0 | BS76: 0 | BT76: 0 | BU76: 0 | BV76: 0 | BW76: 0 | BX76: 0 | BY76: 0 | BZ76: 0 | CA76: 0 | CB76: 0 | CC76: 0 | CD76: 0 | CE76: 0 | CF76: 0 | CG76: 0 | CH76: 0 | CI76: 0 | CJ76: 0 | CK76: 0 | CL76: 0 | CM76: 0 | CN76: 0 | CO76: 0 | CP76: 0 | CQ76: 0 | CR76: 0 | CS76: 0 | CT76: 0 | CU76: 0 | CV76: 0 | CW76: 0 | CX76: 0 | CY76: 0 | CZ76: 0 | DA76: 0 | DB76: 0 | DC76: 0 | DD76: 0 | DE76: 0 | DF76: 0 | DG76: 0 | DH76: 0 | DI76: 0 | DJ76: 0 | DK76: 0 | DL76: 0
B77: =Rentroll!$C$22 -> 6 | C77: =VLOOKUP($B77,Rentroll!$C$11:$X$29,3,FALSE) -> 오토 커머셜 | D77: =VLOOKUP($B77,Rentroll!$C$11:$X$29,9,FALSE) -> 44651 | E77: =VLOOKUP($B77,Rentroll!$C$11:$X$29,10,FALSE) -> 46476 | F77: =VLOOKUP($B77,Rentroll!$C$11:$X$29,11,FALSE) -> 60 | G77: =VLOOKUP($B77,Rentroll!$C$11:$X$29,13,FALSE) -> 95481 | H77: =VLOOKUP($B77,Rentroll!$C$11:$X$29,14,FALSE) -> 87524.25 | I77: =VLOOKUP($B77,Rentroll!$C$11:$X$29,15,FALSE) -> 42436 | J77: =VLOOKUP($B77,Rentroll!$C$11:$X$29,19,FALSE) -> 0.03 | K77: =VLOOKUP($B77,Rentroll!$C$11:$X$29,4,FALSE) -> 1385.09 | L77: =VLOOKUP($B77,Rentroll!$C$11:$X$29,17,FALSE) -> 0 | M77: =VLOOKUP($B77,Rentroll!$C$11:$X$29,18,FALSE) -> 1 | O77: =B77 -> 6 | R77: 0 | S77: 0 | T77: 0 | U77: 0 | V77: 0 | W77: 0 | X77: 0 | Y77: 0 | Z77: 0 | AA77: 0 | AB77: 0 | AC77: 0 | AD77: 0 | AE77: 0 | AF77: 0 | AG77: 0 | AH77: 0 | AI77: 0 | AJ77: 0 | AK77: 0 | AL77: 0 | AM77: 0 | AN77: 0 | AO77: 0 | AP77: 0 | AQ77: 0 | AR77: 0 | AS77: 0 | AT77: 0 | AU77: 0 | AV77: 0 | AW77: 0 | AX77: 0 | AY77: 0 | AZ77: 0 | BA77: 0 | BB77: 0 | BC77: 0 | BD77: 0 | BE77: 0 | BF77: 0 | BG77: 0 | BH77: 0 | BI77: 0 | BJ77: 0 | BK77: 0 | BL77: 0 | BM77: 0 | BN77: 0 | BO77: 0 | BP77: 0 | BQ77: 0 | BR77: 0 | BS77: 0 | BT77: 0 | BU77: 0 | BV77: 0 | BW77: 0 | BX77: 0 | BY77: 0 | BZ77: 0 | CA77: 0 | CB77: 0 | CC77: 0 | CD77: 0 | CE77: 0 | CF77: 0 | CG77: 0 | CH77: 0 | CI77: 0 | CJ77: 0 | CK77: 0 | CL77: 0 | CM77: 0 | CN77: 0 | CO77: 0 | CP77: 0 | CQ77: 0 | CR77: 0 | CS77: 0 | CT77: 0 | CU77: 0 | CV77: 0 | CW77: 0 | CX77: 0 | CY77: 0 | CZ77: 0 | DA77: 0 | DB77: 0 | DC77: 0 | DD77: 0 | DE77: 0 | DF77: 0 | DG77: 0 | DH77: 0 | DI77: 0 | DJ77: 0 | DK77: 0 | DL77: 0
B78: =Rentroll!$C$23 -> 5 | C78: =VLOOKUP($B78,Rentroll!$C$11:$X$29,3,FALSE) -> 공실 | F78: =VLOOKUP($B78,Rentroll!$C$11:$X$29,11,FALSE) -> 0 | G78: =VLOOKUP($B78,Rentroll!$C$11:$X$29,13,FALSE) -> 0 | H78: =VLOOKUP($B78,Rentroll!$C$11:$X$29,14,FALSE) -> 0 | I78: =VLOOKUP($B78,Rentroll!$C$11:$X$29,15,FALSE) -> 0 | J78: =VLOOKUP($B78,Rentroll!$C$11:$X$29,19,FALSE) -> 0 | K78: =VLOOKUP($B78,Rentroll!$C$11:$X$29,4,FALSE) -> 1385.09 | L78: =VLOOKUP($B78,Rentroll!$C$11:$X$29,17,FALSE) -> 0 | M78: =VLOOKUP($B78,Rentroll!$C$11:$X$29,18,FALSE) -> 0 | O78: =B78 -> 5 | R78: 0 | S78: 0 | T78: 0 | U78: 0 | V78: 0 | W78: 0 | X78: 0 | Y78: 0 | Z78: 0 | AA78: 0 | AB78: 0 | AC78: 0 | AD78: 0 | AE78: 0 | AF78: 0 | AG78: 0 | AH78: 0 | AI78: 0 | AJ78: 0 | AK78: 0 | AL78: 0 | AM78: 0 | AN78: 0 | AO78: 0 | AP78: 0 | AQ78: 0 | AR78: 0 | AS78: 0 | AT78: 0 | AU78: 0 | AV78: 0 | AW78: 0 | AX78: 0 | AY78: 0 | AZ78: 0 | BA78: 0 | BB78: 0 | BC78: 0 | BD78: 0 | BE78: 0 | BF78: 0 | BG78: 0 | BH78: 0 | BI78: 0 | BJ78: 0 | BK78: 0 | BL78: 0 | BM78: 0 | BN78: 0 | BO78: 0 | BP78: 0 | BQ78: 0 | BR78: 0 | BS78: 0 | BT78: 0 | BU78: 0 | BV78: 0 | BW78: 0 | BX78: 0 | BY78: 0 | BZ78: 0 | CA78: 0 | CB78: 0 | CC78: 0 | CD78: 0 | CE78: 0 | CF78: 0 | CG78: 0 | CH78: 0 | CI78: 0 | CJ78: 0 | CK78: 0 | CL78: 0 | CM78: 0 | CN78: 0 | CO78: 0 | CP78: 0 | CQ78: 0 | CR78: 0 | CS78: 0 | CT78: 0 | CU78: 0 | CV78: 0 | CW78: 0 | CX78: 0 | CY78: 0 | CZ78: 0 | DA78: 0 | DB78: 0 | DC78: 0 | DD78: 0 | DE78: 0 | DF78: 0 | DG78: 0 | DH78: 0 | DI78: 0 | DJ78: 0 | DK78: 0 | DL78: 0
B79: =Rentroll!$C$24 -> 4 | C79: =VLOOKUP($B79,Rentroll!$C$11:$X$29,3,FALSE) -> 공실 | F79: =VLOOKUP($B79,Rentroll!$C$11:$X$29,11,FALSE) -> 0 | G79: =VLOOKUP($B79,Rentroll!$C$11:$X$29,13,FALSE) -> 0 | H79: =VLOOKUP($B79,Rentroll!$C$11:$X$29,14,FALSE) -> 0 | I79: =VLOOKUP($B79,Rentroll!$C$11:$X$29,15,FALSE) -> 0 | J79: =VLOOKUP($B79,Rentroll!$C$11:$X$29,19,FALSE) -> 0 | K79: =VLOOKUP($B79,Rentroll!$C$11:$X$29,4,FALSE) -> 1385.09 | L79: =VLOOKUP($B79,Rentroll!$C$11:$X$29,17,FALSE) -> 0 | M79: =VLOOKUP($B79,Rentroll!$C$11:$X$29,18,FALSE) -> 0 | O79: =B79 -> 4 | R79: 0 | S79: 0 | T79: 0 | U79: 0 | V79: 0 | W79: 0 | X79: 0 | Y79: 0 | Z79: 0 | AA79: 0 | AB79: 0 | AC79: 0 | AD79: 0 | AE79: 0 | AF79: 0 | AG79: 0 | AH79: 0 | AI79: 0 | AJ79: 0 | AK79: 0 | AL79: 0 | AM79: 0 | AN79: 0 | AO79: 0 | AP79: 0 | AQ79: 0 | AR79: 0 | AS79: 0 | AT79: 0 | AU79: 0 | AV79: 0 | AW79: 0 | AX79: 0 | AY79: 0 | AZ79: 0 | BA79: 0 | BB79: 0 | BC79: 0 | BD79: 0 | BE79: 0 | BF79: 0 | BG79: 0 | BH79: 0 | BI79: 0 | BJ79: 0 | BK79: 0 | BL79: 0 | BM79: 0 | BN79: 0 | BO79: 0 | BP79: 0 | BQ79: 0 | BR79: 0 | BS79: 0 | BT79: 0 | BU79: 0 | BV79: 0 | BW79: 0 | BX79: 0 | BY79: 0 | BZ79: 0 | CA79: 0 | CB79: 0 | CC79: 0 | CD79: 0 | CE79: 0 | CF79: 0 | CG79: 0 | CH79: 0 | CI79: 0 | CJ79: 0 | CK79: 0 | CL79: 0 | CM79: 0 | CN79: 0 | CO79: 0 | CP79: 0 | CQ79: 0 | CR79: 0 | CS79: 0 | CT79: 0 | CU79: 0 | CV79: 0 | CW79: 0 | CX79: 0 | CY79: 0 | CZ79: 0 | DA79: 0 | DB79: 0 | DC79: 0 | DD79: 0 | DE79: 0 | DF79: 0 | DG79: 0 | DH79: 0 | DI79: 0 | DJ79: 0 | DK79: 0 | DL79: 0
B80: =Rentroll!$C$25 -> 3 | C80: =VLOOKUP($B80,Rentroll!$C$11:$X$29,3,FALSE) -> 공실 | F80: =VLOOKUP($B80,Rentroll!$C$11:$X$29,11,FALSE) -> 0 | G80: =VLOOKUP($B80,Rentroll!$C$11:$X$29,13,FALSE) -> 0 | H80: =VLOOKUP($B80,Rentroll!$C$11:$X$29,14,FALSE) -> 0 | I80: =VLOOKUP($B80,Rentroll!$C$11:$X$29,15,FALSE) -> 0 | J80: =VLOOKUP($B80,Rentroll!$C$11:$X$29,19,FALSE) -> 0 | K80: =VLOOKUP($B80,Rentroll!$C$11:$X$29,4,FALSE) -> 1385.09 | L80: =VLOOKUP($B80,Rentroll!$C$11:$X$29,17,FALSE) -> 0 | M80: =VLOOKUP($B80,Rentroll!$C$11:$X$29,18,FALSE) -> 0 | O80: =B80 -> 3 | R80: 0 | S80: 0 | T80: 0 | U80: 0 | V80: 0 | W80: 0 | X80: 0 | Y80: 0 | Z80: 0 | AA80: 0 | AB80: 0 | AC80: 0 | AD80: 0 | AE80: 0 | AF80: 0 | AG80: 0 | AH80: 0 | AI80: 0 | AJ80: 0 | AK80: 0 | AL80: 0 | AM80: 0 | AN80: 0 | AO80: 0 | AP80: 0 | AQ80: 0 | AR80: 0 | AS80: 0 | AT80: 0 | AU80: 0 | AV80: 0 | AW80: 0 | AX80: 0 | AY80: 0 | AZ80: 0 | BA80: 0 | BB80: 0 | BC80: 0 | BD80: 0 | BE80: 0 | BF80: 0 | BG80: 0 | BH80: 0 | BI80: 0 | BJ80: 0 | BK80: 0 | BL80: 0 | BM80: 0 | BN80: 0 | BO80: 0 | BP80: 0 | BQ80: 0 | BR80: 0 | BS80: 0 | BT80: 0 | BU80: 0 | BV80: 0 | BW80: 0 | BX80: 0 | BY80: 0 | BZ80: 0 | CA80: 0 | CB80: 0 | CC80: 0 | CD80: 0 | CE80: 0 | CF80: 0 | CG80: 0 | CH80: 0 | CI80: 0 | CJ80: 0 | CK80: 0 | CL80: 0 | CM80: 0 | CN80: 0 | CO80: 0 | CP80: 0 | CQ80: 0 | CR80: 0 | CS80: 0 | CT80: 0 | CU80: 0 | CV80: 0 | CW80: 0 | CX80: 0 | CY80: 0 | CZ80: 0 | DA80: 0 | DB80: 0 | DC80: 0 | DD80: 0 | DE80: 0 | DF80: 0 | DG80: 0 | DH80: 0 | DI80: 0 | DJ80: 0 | DK80: 0 | DL80: 0
B81: =Rentroll!$C$26 -> 2 | C81: =VLOOKUP($B81,Rentroll!$C$11:$X$29,3,FALSE) -> 공실 | F81: =VLOOKUP($B81,Rentroll!$C$11:$X$29,11,FALSE) -> 0 | G81: =VLOOKUP($B81,Rentroll!$C$11:$X$29,13,FALSE) -> 0 | H81: =VLOOKUP($B81,Rentroll!$C$11:$X$29,14,FALSE) -> 0 | I81: =VLOOKUP($B81,Rentroll!$C$11:$X$29,15,FALSE) -> 0 | J81: =VLOOKUP($B81,Rentroll!$C$11:$X$29,19,FALSE) -> 0 | K81: =VLOOKUP($B81,Rentroll!$C$11:$X$29,4,FALSE) -> 1385.09 | L81: =VLOOKUP($B81,Rentroll!$C$11:$X$29,17,FALSE) -> 0 | M81: =VLOOKUP($B81,Rentroll!$C$11:$X$29,18,FALSE) -> 0 | O81: =B81 -> 2 | R81: 0 | S81: 0 | T81: 0 | U81: 0 | V81: 0 | W81: 0 | X81: 0 | Y81: 0 | Z81: 0 | AA81: 0 | AB81: 0 | AC81: 0 | AD81: 0 | AE81: 0 | AF81: 0 | AG81: 0 | AH81: 0 | AI81: 0 | AJ81: 0 | AK81: 0 | AL81: 0 | AM81: 0 | AN81: 0 | AO81: 0 | AP81: 0 | AQ81: 0 | AR81: 0 | AS81: 0 | AT81: 0 | AU81: 0 | AV81: 0 | AW81: 0 | AX81: 0 | AY81: 0 | AZ81: 0 | BA81: 0 | BB81: 0 | BC81: 0 | BD81: 0 | BE81: 0 | BF81: 0 | BG81: 0 | BH81: 0 | BI81: 0 | BJ81: 0 | BK81: 0 | BL81: 0 | BM81: 0 | BN81: 0 | BO81: 0 | BP81: 0 | BQ81: 0 | BR81: 0 | BS81: 0 | BT81: 0 | BU81: 0 | BV81: 0 | BW81: 0 | BX81: 0 | BY81: 0 | BZ81: 0 | CA81: 0 | CB81: 0 | CC81: 0 | CD81: 0 | CE81: 0 | CF81: 0 | CG81: 0 | CH81: 0 | CI81: 0 | CJ81: 0 | CK81: 0 | CL81: 0 | CM81: 0 | CN81: 0 | CO81: 0 | CP81: 0 | CQ81: 0 | CR81: 0 | CS81: 0 | CT81: 0 | CU81: 0 | CV81: 0 | CW81: 0 | CX81: 0 | CY81: 0 | CZ81: 0 | DA81: 0 | DB81: 0 | DC81: 0 | DD81: 0 | DE81: 0 | DF81: 0 | DG81: 0 | DH81: 0 | DI81: 0 | DJ81: 0 | DK81: 0 | DL81: 0
B82: =Rentroll!$C$27 -> 1 | C82: =VLOOKUP($B82,Rentroll!$C$11:$X$29,3,FALSE) -> 파파 커피앤도넛 | D82: =VLOOKUP($B82,Rentroll!$C$11:$X$29,9,FALSE) -> 42064 | E82: =VLOOKUP($B82,Rentroll!$C$11:$X$29,10,FALSE) -> 45716 | F82: =VLOOKUP($B82,Rentroll!$C$11:$X$29,11,FALSE) -> 120 | G82: =VLOOKUP($B82,Rentroll!$C$11:$X$29,13,FALSE) -> 91334 | H82: =VLOOKUP($B82,Rentroll!$C$11:$X$29,14,FALSE) -> 83722.833 | I82: =VLOOKUP($B82,Rentroll!$C$11:$X$29,15,FALSE) -> 39143 | J82: =VLOOKUP($B82,Rentroll!$C$11:$X$29,19,FALSE) -> 0.03 | K82: =VLOOKUP($B82,Rentroll!$C$11:$X$29,4,FALSE) -> 969.56 | L82: =VLOOKUP($B82,Rentroll!$C$11:$X$29,17,FALSE) -> 0 | M82: =VLOOKUP($B82,Rentroll!$C$11:$X$29,18,FALSE) -> 1 | O82: =B82 -> 1 | R82: 0 | S82: 0 | T82: 0 | U82: 0 | V82: 0 | W82: 0 | X82: 0 | Y82: 0 | Z82: 0 | AA82: 0 | AB82: 0 | AC82: 0 | AD82: 0 | AE82: 0 | AF82: 0 | AG82: 0 | AH82: 0 | AI82: 0 | AJ82: 0 | AK82: 0 | AL82: 0 | AM82: 0 | AN82: 0 | AO82: 0 | AP82: 0 | AQ82: 0 | AR82: 0 | AS82: 0 | AT82: 0 | AU82: 0 | AV82: 0 | AW82: 0 | AX82: 0 | AY82: 0 | AZ82: 0 | BA82: 0 | BB82: 0 | BC82: 0 | BD82: 0 | BE82: 0 | BF82: 0 | BG82: 0 | BH82: 0 | BI82: 0 | BJ82: 0 | BK82: 0 | BL82: 0 | BM82: 0 | BN82: 0 | BO82: 0 | BP82: 0 | BQ82: 0 | BR82: 0 | BS82: 0 | BT82: 0 | BU82: 0 | BV82: 0 | BW82: 0 | BX82: 0 | BY82: 0 | BZ82: 0 | CA82: 0 | CB82: 0 | CC82: 0 | CD82: 0 | CE82: 0 | CF82: 0 | CG82: 0 | CH82: 0 | CI82: 0 | CJ82: 0 | CK82: 0 | CL82: 0 | CM82: 0 | CN82: 0 | CO82: 0 | CP82: 0 | CQ82: 0 | CR82: 0 | CS82: 0 | CT82: 0 | CU82: 0 | CV82: 0 | CW82: 0 | CX82: 0 | CY82: 0 | CZ82: 0 | DA82: 0 | DB82: 0 | DC82: 0 | DD82: 0 | DE82: 0 | DF82: 0 | DG82: 0 | DH82: 0 | DI82: 0 | DJ82: 0 | DK82: 0 | DL82: 0
B83: =Rentroll!$C$28 -> B101호 | C83: =VLOOKUP($B83,Rentroll!$C$11:$X$29,3,FALSE) -> 퀸즈 샌드위치 | D83: =VLOOKUP($B83,Rentroll!$C$11:$X$29,9,FALSE) -> 44926 | E83: =VLOOKUP($B83,Rentroll!$C$11:$X$29,10,FALSE) -> 46751 | F83: =VLOOKUP($B83,Rentroll!$C$11:$X$29,11,FALSE) -> 60 | G83: =VLOOKUP($B83,Rentroll!$C$11:$X$29,13,FALSE) -> 21218 | H83: =VLOOKUP($B83,Rentroll!$C$11:$X$29,14,FALSE) -> 17681.667 | I83: =VLOOKUP($B83,Rentroll!$C$11:$X$29,15,FALSE) -> 31827 | J83: =VLOOKUP($B83,Rentroll!$C$11:$X$29,19,FALSE) -> 0.03 | K83: =VLOOKUP($B83,Rentroll!$C$11:$X$29,4,FALSE) -> 969.56 | L83: =VLOOKUP($B83,Rentroll!$C$11:$X$29,17,FALSE) -> 0 | M83: =VLOOKUP($B83,Rentroll!$C$11:$X$29,18,FALSE) -> 2 | O83: =B83 -> B101호 | R83: 0 | S83: 0 | T83: 0 | U83: 0 | V83: 0 | W83: 0 | X83: 0 | Y83: 0 | Z83: 0 | AA83: 0 | AB83: 0 | AC83: 0 | AD83: 0 | AE83: 0 | AF83: 0 | AG83: 0 | AH83: 0 | AI83: 0 | AJ83: 0 | AK83: 0 | AL83: 0 | AM83: 0 | AN83: 0 | AO83: 0 | AP83: 0 | AQ83: 0 | AR83: 0 | AS83: 0 | AT83: 0 | AU83: 0 | AV83: 0 | AW83: 0 | AX83: 0 | AY83: 0 | AZ83: 0 | BA83: 0 | BB83: 0 | BC83: 0 | BD83: 0 | BE83: 0 | BF83: 0 | BG83: 0 | BH83: 0 | BI83: 0 | BJ83: 0 | BK83: 0 | BL83: 0 | BM83: 0 | BN83: 0 | BO83: 0 | BP83: 0 | BQ83: 0 | BR83: 0 | BS83: 0 | BT83: 0 | BU83: 0 | BV83: 0 | BW83: 0 | BX83: 0 | BY83: 0 | BZ83: 0 | CA83: 0 | CB83: 0 | CC83: 0 | CD83: 0 | CE83: 0 | CF83: 0 | CG83: 0 | CH83: 0 | CI83: 0 | CJ83: 0 | CK83: 0 | CL83: 0 | CM83: 0 | CN83: 0 | CO83: 0 | CP83: 0 | CQ83: 0 | CR83: 0 | CS83: 0 | CT83: 0 | CU83: 0 | CV83: 0 | CW83: 0 | CX83: 0 | CY83: 0 | CZ83: 0 | DA83: 0 | DB83: 0 | DC83: 0 | DD83: 0 | DE83: 0 | DF83: 0 | DG83: 0 | DH83: 0 | DI83: 0 | DJ83: 0 | DK83: 0 | DL83: 0
B84: =Rentroll!$C$29 -> B102호 | C84: =VLOOKUP($B84,Rentroll!$C$11:$X$29,3,FALSE) -> 로미오 문구점 | D84: =VLOOKUP($B84,Rentroll!$C$11:$X$29,9,FALSE) -> 44592 | E84: =VLOOKUP($B84,Rentroll!$C$11:$X$29,10,FALSE) -> 46417 | F84: =VLOOKUP($B84,Rentroll!$C$11:$X$29,11,FALSE) -> 60 | G84: =VLOOKUP($B84,Rentroll!$C$11:$X$29,13,FALSE) -> 31827 | H84: =VLOOKUP($B84,Rentroll!$C$11:$X$29,14,FALSE) -> 23870.25 | I84: =VLOOKUP($B84,Rentroll!$C$11:$X$29,15,FALSE) -> 31827 | J84: =VLOOKUP($B84,Rentroll!$C$11:$X$29,19,FALSE) -> 0.03 | K84: =VLOOKUP($B84,Rentroll!$C$11:$X$29,4,FALSE) -> 969.56 | L84: =VLOOKUP($B84,Rentroll!$C$11:$X$29,17,FALSE) -> 0 | M84: =VLOOKUP($B84,Rentroll!$C$11:$X$29,18,FALSE) -> 3 | O84: =B84 -> B102호 | R84: 0 | S84: 0 | T84: 0 | U84: 0 | V84: 0 | W84: 0 | X84: 0 | Y84: 0 | Z84: 0 | AA84: 0 | AB84: 0 | AC84: 0 | AD84: 0 | AE84: 0 | AF84: 0 | AG84: 0 | AH84: 0 | AI84: 0 | AJ84: 0 | AK84: 0 | AL84: 0 | AM84: 0 | AN84: 0 | AO84: 0 | AP84: 0 | AQ84: 0 | AR84: 0 | AS84: 0 | AT84: 0 | AU84: 0 | AV84: 0 | AW84: 0 | AX84: 0 | AY84: 0 | AZ84: 0 | BA84: 0 | BB84: 0 | BC84: 0 | BD84: 0 | BE84: 0 | BF84: 0 | BG84: 0 | BH84: 0 | BI84: 0 | BJ84: 0 | BK84: 0 | BL84: 0 | BM84: 0 | BN84: 0 | BO84: 0 | BP84: 0 | BQ84: 0 | BR84: 0 | BS84: 0 | BT84: 0 | BU84: 0 | BV84: 0 | BW84: 0 | BX84: 0 | BY84: 0 | BZ84: 0 | CA84: 0 | CB84: 0 | CC84: 0 | CD84: 0 | CE84: 0 | CF84: 0 | CG84: 0 | CH84: 0 | CI84: 0 | CJ84: 0 | CK84: 0 | CL84: 0 | CM84: 0 | CN84: 0 | CO84: 0 | CP84: 0 | CQ84: 0 | CR84: 0 | CS84: 0 | CT84: 0 | CU84: 0 | CV84: 0 | CW84: 0 | CX84: 0 | CY84: 0 | CZ84: 0 | DA84: 0 | DB84: 0 | DC84: 0 | DD84: 0 | DE84: 0 | DF84: 0 | DG84: 0 | DH84: 0 | DI84: 0 | DJ84: 0 | DK84: 0 | DL84: 0
B85: 층수 | C85: 임차인 | D85: 시작일 | E85: 종료일 | F85: 기간 | G85: 명목 임대료(원) | H85: 실질 임대료(원) | I85: 관리비(원) | J85: 상승률 | K85: 임대면적(㎡) | L85: Fitout | M85: Rentfree | O85: 신규 임대차
B86: =Rentroll!$C$37 -> 17 | C86: =VLOOKUP($B86,Rentroll!$C$37:$Z$60,3,FALSE) -> 리마 상사 | D86: =VLOOKUP($B86,Rentroll!$C$37:$Z$60,9,FALSE) -> 47149 | E86: =VLOOKUP($B86,Rentroll!$C$37:$Z$60,10,FALSE) -> 48975 | F86: =VLOOKUP($B86,Rentroll!$C$37:$Z$60,11,FALSE) -> 60 | G86: =VLOOKUP($B86,Rentroll!$C$37:$Z$60,13,FALSE) -> 115927.41 | H86: =VLOOKUP($B86,Rentroll!$C$37:$Z$60,14,FALSE) -> 106266.79 | I86: =VLOOKUP($B86,Rentroll!$C$37:$Z$60,15,FALSE) -> 50647.896 | J86: =VLOOKUP($B86,Rentroll!$C$37:$Z$60,19,FALSE) -> 0.03 | K86: =VLOOKUP($B86,Rentroll!$C$37:$Z$60,4,FALSE) -> 1385.09 | L86: =VLOOKUP($B86,Rentroll!$C$37:$Z$60,17,FALSE) -> 0 | M86: =VLOOKUP($B86,Rentroll!$C$37:$Z$60,18,FALSE) -> 1 | O86: =B86 -> 17 | R86: =IF($L86=0,0,(EOMONTH($D86,1)<=R$14)*(EOMONTH($D86,$L86)>=R$14)*1) -> 0 | S86: =IF($L86=0,0,(EOMONTH($D86,1)<=S$14)*(EOMONTH($D86,$L86)>=S$14)*1) -> 0 | T86: =IF($L86=0,0,(EOMONTH($D86,1)<=T$14)*(EOMONTH($D86,$L86)>=T$14)*1) -> 0 | U86: =IF($L86=0,0,(EOMONTH($D86,1)<=U$14)*(EOMONTH($D86,$L86)>=U$14)*1) -> 0 | V86: =IF($L86=0,0,(EOMONTH($D86,1)<=V$14)*(EOMONTH($D86,$L86)>=V$14)*1) -> 0 | W86: =IF($L86=0,0,(EOMONTH($D86,1)<=W$14)*(EOMONTH($D86,$L86)>=W$14)*1) -> 0 | X86: =IF($L86=0,0,(EOMONTH($D86,1)<=X$14)*(EOMONTH($D86,$L86)>=X$14)*1) -> 0 | Y86: =IF($L86=0,0,(EOMONTH($D86,1)<=Y$14)*(EOMONTH($D86,$L86)>=Y$14)*1) -> 0 | ... DL86: =IF($L86=0,0,(EOMONTH($D86,1)<=DL$14)*(EOMONTH($D86,$L86)>=DL$14)*1) -> 0
B87: =Rentroll!$C$38 -> 16 | C87: =VLOOKUP($B87,Rentroll!$C$37:$Z$60,3,FALSE) -> 리마 상사 | D87: =VLOOKUP($B87,Rentroll!$C$37:$Z$60,9,FALSE) -> 47149 | E87: =VLOOKUP($B87,Rentroll!$C$37:$Z$60,10,FALSE) -> 48975 | F87: =VLOOKUP($B87,Rentroll!$C$37:$Z$60,11,FALSE) -> 60 | G87: =VLOOKUP($B87,Rentroll!$C$37:$Z$60,13,FALSE) -> 115927.41 | H87: =VLOOKUP($B87,Rentroll!$C$37:$Z$60,14,FALSE) -> 106266.79 | I87: =VLOOKUP($B87,Rentroll!$C$37:$Z$60,15,FALSE) -> 50647.896 | J87: =VLOOKUP($B87,Rentroll!$C$37:$Z$60,19,FALSE) -> 0.03 | K87: =VLOOKUP($B87,Rentroll!$C$37:$Z$60,4,FALSE) -> 1385.09 | L87: =VLOOKUP($B87,Rentroll!$C$37:$Z$60,17,FALSE) -> 0 | M87: =VLOOKUP($B87,Rentroll!$C$37:$Z$60,18,FALSE) -> 1 | O87: =B87 -> 16 | R87: =IF($L87=0,0,(EOMONTH($D87,1)<=R$14)*(EOMONTH($D87,$L87)>=R$14)*1) -> 0 | S87: =IF($L87=0,0,(EOMONTH($D87,1)<=S$14)*(EOMONTH($D87,$L87)>=S$14)*1) -> 0 | T87: =IF($L87=0,0,(EOMONTH($D87,1)<=T$14)*(EOMONTH($D87,$L87)>=T$14)*1) -> 0 | U87: =IF($L87=0,0,(EOMONTH($D87,1)<=U$14)*(EOMONTH($D87,$L87)>=U$14)*1) -> 0 | V87: =IF($L87=0,0,(EOMONTH($D87,1)<=V$14)*(EOMONTH($D87,$L87)>=V$14)*1) -> 0 | W87: =IF($L87=0,0,(EOMONTH($D87,1)<=W$14)*(EOMONTH($D87,$L87)>=W$14)*1) -> 0 | X87: =IF($L87=0,0,(EOMONTH($D87,1)<=X$14)*(EOMONTH($D87,$L87)>=X$14)*1) -> 0 | Y87: =IF($L87=0,0,(EOMONTH($D87,1)<=Y$14)*(EOMONTH($D87,$L87)>=Y$14)*1) -> 0 | ... DL87: =IF($L87=0,0,(EOMONTH($D87,1)<=DL$14)*(EOMONTH($D87,$L87)>=DL$14)*1) -> 0
B88: =Rentroll!$C$39 -> 15 | C88: =VLOOKUP($B88,Rentroll!$C$37:$Z$60,3,FALSE) -> 111퍼센트 | D88: =VLOOKUP($B88,Rentroll!$C$37:$Z$60,9,FALSE) -> 45869 | E88: =VLOOKUP($B88,Rentroll!$C$37:$Z$60,10,FALSE) -> 47695 | F88: =VLOOKUP($B88,Rentroll!$C$37:$Z$60,11,FALSE) -> 60 | G88: =VLOOKUP($B88,Rentroll!$C$37:$Z$60,13,FALSE) -> 103000 | H88: =VLOOKUP($B88,Rentroll!$C$37:$Z$60,14,FALSE) -> 94416.667 | I88: =VLOOKUP($B88,Rentroll!$C$37:$Z$60,15,FALSE) -> 45000 | J88: =VLOOKUP($B88,Rentroll!$C$37:$Z$60,19,FALSE) -> 0.03 | K88: =VLOOKUP($B88,Rentroll!$C$37:$Z$60,4,FALSE) -> 1385.09 | L88: =VLOOKUP($B88,Rentroll!$C$37:$Z$60,17,FALSE) -> 1 | M88: =VLOOKUP($B88,Rentroll!$C$37:$Z$60,18,FALSE) -> 1 | O88: =B88 -> 15 | R88: =IF($L88=0,0,(EOMONTH($D88,1)<=R$14)*(EOMONTH($D88,$L88)>=R$14)*1) -> 0 | S88: =IF($L88=0,0,(EOMONTH($D88,1)<=S$14)*(EOMONTH($D88,$L88)>=S$14)*1) -> 0 | T88: =IF($L88=0,0,(EOMONTH($D88,1)<=T$14)*(EOMONTH($D88,$L88)>=T$14)*1) -> 0 | U88: =IF($L88=0,0,(EOMONTH($D88,1)<=U$14)*(EOMONTH($D88,$L88)>=U$14)*1) -> 0 | V88: =IF($L88=0,0,(EOMONTH($D88,1)<=V$14)*(EOMONTH($D88,$L88)>=V$14)*1) -> 0 | W88: =IF($L88=0,0,(EOMONTH($D88,1)<=W$14)*(EOMONTH($D88,$L88)>=W$14)*1) -> 0 | X88: =IF($L88=0,0,(EOMONTH($D88,1)<=X$14)*(EOMONTH($D88,$L88)>=X$14)*1) -> 0 | Y88: =IF($L88=0,0,(EOMONTH($D88,1)<=Y$14)*(EOMONTH($D88,$L88)>=Y$14)*1) -> 1 | ... DL88: =IF($L88=0,0,(EOMONTH($D88,1)<=DL$14)*(EOMONTH($D88,$L88)>=DL$14)*1) -> 0
B89: =Rentroll!$C$40 -> 14 | C89: =VLOOKUP($B89,Rentroll!$C$37:$Z$60,3,FALSE) -> 111퍼센트 | D89: =VLOOKUP($B89,Rentroll!$C$37:$Z$60,9,FALSE) -> 45869 | E89: =VLOOKUP($B89,Rentroll!$C$37:$Z$60,10,FALSE) -> 47695 | F89: =VLOOKUP($B89,Rentroll!$C$37:$Z$60,11,FALSE) -> 60 | G89: =VLOOKUP($B89,Rentroll!$C$37:$Z$60,13,FALSE) -> 103000 | H89: =VLOOKUP($B89,Rentroll!$C$37:$Z$60,14,FALSE) -> 94416.667 | I89: =VLOOKUP($B89,Rentroll!$C$37:$Z$60,15,FALSE) -> 45000 | J89: =VLOOKUP($B89,Rentroll!$C$37:$Z$60,19,FALSE) -> 0.03 | K89: =VLOOKUP($B89,Rentroll!$C$37:$Z$60,4,FALSE) -> 1385.09 | L89: =VLOOKUP($B89,Rentroll!$C$37:$Z$60,17,FALSE) -> 1 | M89: =VLOOKUP($B89,Rentroll!$C$37:$Z$60,18,FALSE) -> 1 | O89: =B89 -> 14 | R89: =IF($L89=0,0,(EOMONTH($D89,1)<=R$14)*(EOMONTH($D89,$L89)>=R$14)*1) -> 0 | S89: =IF($L89=0,0,(EOMONTH($D89,1)<=S$14)*(EOMONTH($D89,$L89)>=S$14)*1) -> 0 | T89: =IF($L89=0,0,(EOMONTH($D89,1)<=T$14)*(EOMONTH($D89,$L89)>=T$14)*1) -> 0 | U89: =IF($L89=0,0,(EOMONTH($D89,1)<=U$14)*(EOMONTH($D89,$L89)>=U$14)*1) -> 0 | V89: =IF($L89=0,0,(EOMONTH($D89,1)<=V$14)*(EOMONTH($D89,$L89)>=V$14)*1) -> 0 | W89: =IF($L89=0,0,(EOMONTH($D89,1)<=W$14)*(EOMONTH($D89,$L89)>=W$14)*1) -> 0 | X89: =IF($L89=0,0,(EOMONTH($D89,1)<=X$14)*(EOMONTH($D89,$L89)>=X$14)*1) -> 0 | Y89: =IF($L89=0,0,(EOMONTH($D89,1)<=Y$14)*(EOMONTH($D89,$L89)>=Y$14)*1) -> 1 | ... DL89: =IF($L89=0,0,(EOMONTH($D89,1)<=DL$14)*(EOMONTH($D89,$L89)>=DL$14)*1) -> 0
B90: =Rentroll!$C$41 -> 13 | C90: =VLOOKUP($B90,Rentroll!$C$37:$Z$60,3,FALSE) -> 111퍼센트 | D90: =VLOOKUP($B90,Rentroll!$C$37:$Z$60,9,FALSE) -> 45869 | E90: =VLOOKUP($B90,Rentroll!$C$37:$Z$60,10,FALSE) -> 47695 | F90: =VLOOKUP($B90,Rentroll!$C$37:$Z$60,11,FALSE) -> 60 | G90: =VLOOKUP($B90,Rentroll!$C$37:$Z$60,13,FALSE) -> 103000 | H90: =VLOOKUP($B90,Rentroll!$C$37:$Z$60,14,FALSE) -> 94416.667 | I90: =VLOOKUP($B90,Rentroll!$C$37:$Z$60,15,FALSE) -> 45000 | J90: =VLOOKUP($B90,Rentroll!$C$37:$Z$60,19,FALSE) -> 0.03 | K90: =VLOOKUP($B90,Rentroll!$C$37:$Z$60,4,FALSE) -> 1385.09 | L90: =VLOOKUP($B90,Rentroll!$C$37:$Z$60,17,FALSE) -> 1 | M90: =VLOOKUP($B90,Rentroll!$C$37:$Z$60,18,FALSE) -> 1 | O90: =B90 -> 13 | R90: =IF($L90=0,0,(EOMONTH($D90,1)<=R$14)*(EOMONTH($D90,$L90)>=R$14)*1) -> 0 | S90: =IF($L90=0,0,(EOMONTH($D90,1)<=S$14)*(EOMONTH($D90,$L90)>=S$14)*1) -> 0 | T90: =IF($L90=0,0,(EOMONTH($D90,1)<=T$14)*(EOMONTH($D90,$L90)>=T$14)*1) -> 0 | U90: =IF($L90=0,0,(EOMONTH($D90,1)<=U$14)*(EOMONTH($D90,$L90)>=U$14)*1) -> 0 | V90: =IF($L90=0,0,(EOMONTH($D90,1)<=V$14)*(EOMONTH($D90,$L90)>=V$14)*1) -> 0 | W90: =IF($L90=0,0,(EOMONTH($D90,1)<=W$14)*(EOMONTH($D90,$L90)>=W$14)*1) -> 0 | X90: =IF($L90=0,0,(EOMONTH($D90,1)<=X$14)*(EOMONTH($D90,$L90)>=X$14)*1) -> 0 | Y90: =IF($L90=0,0,(EOMONTH($D90,1)<=Y$14)*(EOMONTH($D90,$L90)>=Y$14)*1) -> 1 | ... DL90: =IF($L90=0,0,(EOMONTH($D90,1)<=DL$14)*(EOMONTH($D90,$L90)>=DL$14)*1) -> 0
B91: =Rentroll!$C$42 -> 12 | C91: =VLOOKUP($B91,Rentroll!$C$37:$Z$60,3,FALSE) -> 신라젠 | D91: =VLOOKUP($B91,Rentroll!$C$37:$Z$60,9,FALSE) -> 45869 | E91: =VLOOKUP($B91,Rentroll!$C$37:$Z$60,10,FALSE) -> 47695 | F91: =VLOOKUP($B91,Rentroll!$C$37:$Z$60,11,FALSE) -> 60 | G91: =VLOOKUP($B91,Rentroll!$C$37:$Z$60,13,FALSE) -> 103000 | H91: =VLOOKUP($B91,Rentroll!$C$37:$Z$60,14,FALSE) -> 94416.667 | I91: =VLOOKUP($B91,Rentroll!$C$37:$Z$60,15,FALSE) -> 45000 | J91: =VLOOKUP($B91,Rentroll!$C$37:$Z$60,19,FALSE) -> 0.03 | K91: =VLOOKUP($B91,Rentroll!$C$37:$Z$60,4,FALSE) -> 1385.09 | L91: =VLOOKUP($B91,Rentroll!$C$37:$Z$60,17,FALSE) -> 1 | M91: =VLOOKUP($B91,Rentroll!$C$37:$Z$60,18,FALSE) -> 1 | O91: =B91 -> 12 | R91: =IF($L91=0,0,(EOMONTH($D91,1)<=R$14)*(EOMONTH($D91,$L91)>=R$14)*1) -> 0 | S91: =IF($L91=0,0,(EOMONTH($D91,1)<=S$14)*(EOMONTH($D91,$L91)>=S$14)*1) -> 0 | T91: =IF($L91=0,0,(EOMONTH($D91,1)<=T$14)*(EOMONTH($D91,$L91)>=T$14)*1) -> 0 | U91: =IF($L91=0,0,(EOMONTH($D91,1)<=U$14)*(EOMONTH($D91,$L91)>=U$14)*1) -> 0 | V91: =IF($L91=0,0,(EOMONTH($D91,1)<=V$14)*(EOMONTH($D91,$L91)>=V$14)*1) -> 0 | W91: =IF($L91=0,0,(EOMONTH($D91,1)<=W$14)*(EOMONTH($D91,$L91)>=W$14)*1) -> 0 | X91: =IF($L91=0,0,(EOMONTH($D91,1)<=X$14)*(EOMONTH($D91,$L91)>=X$14)*1) -> 0 | Y91: =IF($L91=0,0,(EOMONTH($D91,1)<=Y$14)*(EOMONTH($D91,$L91)>=Y$14)*1) -> 1 | ... DL91: =IF($L91=0,0,(EOMONTH($D91,1)<=DL$14)*(EOMONTH($D91,$L91)>=DL$14)*1) -> 0
B92: =Rentroll!$C$43 -> 11 | C92: =VLOOKUP($B92,Rentroll!$C$37:$Z$60,3,FALSE) -> 노벰버 건설 | D92: =VLOOKUP($B92,Rentroll!$C$37:$Z$60,9,FALSE) -> 46904 | E92: =VLOOKUP($B92,Rentroll!$C$37:$Z$60,10,FALSE) -> 48730 | F92: =VLOOKUP($B92,Rentroll!$C$37:$Z$60,11,FALSE) -> 60 | G92: =VLOOKUP($B92,Rentroll!$C$37:$Z$60,13,FALSE) -> 112550.88 | H92: =VLOOKUP($B92,Rentroll!$C$37:$Z$60,14,FALSE) -> 103171.64 | I92: =VLOOKUP($B92,Rentroll!$C$37:$Z$60,15,FALSE) -> 49172.715 | J92: =VLOOKUP($B92,Rentroll!$C$37:$Z$60,19,FALSE) -> 0.03 | K92: =VLOOKUP($B92,Rentroll!$C$37:$Z$60,4,FALSE) -> 1385.09 | L92: =VLOOKUP($B92,Rentroll!$C$37:$Z$60,17,FALSE) -> 0 | M92: =VLOOKUP($B92,Rentroll!$C$37:$Z$60,18,FALSE) -> 1 | O92: =B92 -> 11 | R92: =IF($L92=0,0,(EOMONTH($D92,1)<=R$14)*(EOMONTH($D92,$L92)>=R$14)*1) -> 0 | S92: =IF($L92=0,0,(EOMONTH($D92,1)<=S$14)*(EOMONTH($D92,$L92)>=S$14)*1) -> 0 | T92: =IF($L92=0,0,(EOMONTH($D92,1)<=T$14)*(EOMONTH($D92,$L92)>=T$14)*1) -> 0 | U92: =IF($L92=0,0,(EOMONTH($D92,1)<=U$14)*(EOMONTH($D92,$L92)>=U$14)*1) -> 0 | V92: =IF($L92=0,0,(EOMONTH($D92,1)<=V$14)*(EOMONTH($D92,$L92)>=V$14)*1) -> 0 | W92: =IF($L92=0,0,(EOMONTH($D92,1)<=W$14)*(EOMONTH($D92,$L92)>=W$14)*1) -> 0 | X92: =IF($L92=0,0,(EOMONTH($D92,1)<=X$14)*(EOMONTH($D92,$L92)>=X$14)*1) -> 0 | Y92: =IF($L92=0,0,(EOMONTH($D92,1)<=Y$14)*(EOMONTH($D92,$L92)>=Y$14)*1) -> 0 | ... DL92: =IF($L92=0,0,(EOMONTH($D92,1)<=DL$14)*(EOMONTH($D92,$L92)>=DL$14)*1) -> 0
B93: =Rentroll!$C$44 -> 10 | C93: =VLOOKUP($B93,Rentroll!$C$37:$Z$60,3,FALSE) -> 노벰버 건설 | D93: =VLOOKUP($B93,Rentroll!$C$37:$Z$60,9,FALSE) -> 46904 | E93: =VLOOKUP($B93,Rentroll!$C$37:$Z$60,10,FALSE) -> 48730 | F93: =VLOOKUP($B93,Rentroll!$C$37:$Z$60,11,FALSE) -> 60 | G93: =VLOOKUP($B93,Rentroll!$C$37:$Z$60,13,FALSE) -> 112550.88 | H93: =VLOOKUP($B93,Rentroll!$C$37:$Z$60,14,FALSE) -> 103171.64 | I93: =VLOOKUP($B93,Rentroll!$C$37:$Z$60,15,FALSE) -> 49172.715 | J93: =VLOOKUP($B93,Rentroll!$C$37:$Z$60,19,FALSE) -> 0.03 | K93: =VLOOKUP($B93,Rentroll!$C$37:$Z$60,4,FALSE) -> 1385.09 | L93: =VLOOKUP($B93,Rentroll!$C$37:$Z$60,17,FALSE) -> 0 | M93: =VLOOKUP($B93,Rentroll!$C$37:$Z$60,18,FALSE) -> 1 | O93: =B93 -> 10 | R93: =IF($L93=0,0,(EOMONTH($D93,1)<=R$14)*(EOMONTH($D93,$L93)>=R$14)*1) -> 0 | S93: =IF($L93=0,0,(EOMONTH($D93,1)<=S$14)*(EOMONTH($D93,$L93)>=S$14)*1) -> 0 | T93: =IF($L93=0,0,(EOMONTH($D93,1)<=T$14)*(EOMONTH($D93,$L93)>=T$14)*1) -> 0 | U93: =IF($L93=0,0,(EOMONTH($D93,1)<=U$14)*(EOMONTH($D93,$L93)>=U$14)*1) -> 0 | V93: =IF($L93=0,0,(EOMONTH($D93,1)<=V$14)*(EOMONTH($D93,$L93)>=V$14)*1) -> 0 | W93: =IF($L93=0,0,(EOMONTH($D93,1)<=W$14)*(EOMONTH($D93,$L93)>=W$14)*1) -> 0 | X93: =IF($L93=0,0,(EOMONTH($D93,1)<=X$14)*(EOMONTH($D93,$L93)>=X$14)*1) -> 0 | Y93: =IF($L93=0,0,(EOMONTH($D93,1)<=Y$14)*(EOMONTH($D93,$L93)>=Y$14)*1) -> 0 | ... DL93: =IF($L93=0,0,(EOMONTH($D93,1)<=DL$14)*(EOMONTH($D93,$L93)>=DL$14)*1) -> 0
B94: =Rentroll!$C$45 -> 9 | C94: =VLOOKUP($B94,Rentroll!$C$37:$Z$60,3,FALSE) -> 노벰버 건설 | D94: =VLOOKUP($B94,Rentroll!$C$37:$Z$60,9,FALSE) -> 46904 | E94: =VLOOKUP($B94,Rentroll!$C$37:$Z$60,10,FALSE) -> 48730 | F94: =VLOOKUP($B94,Rentroll!$C$37:$Z$60,11,FALSE) -> 60 | G94: =VLOOKUP($B94,Rentroll!$C$37:$Z$60,13,FALSE) -> 112550.88 | H94: =VLOOKUP($B94,Rentroll!$C$37:$Z$60,14,FALSE) -> 103171.64 | I94: =VLOOKUP($B94,Rentroll!$C$37:$Z$60,15,FALSE) -> 49172.715 | J94: =VLOOKUP($B94,Rentroll!$C$37:$Z$60,19,FALSE) -> 0.03 | K94: =VLOOKUP($B94,Rentroll!$C$37:$Z$60,4,FALSE) -> 1385.09 | L94: =VLOOKUP($B94,Rentroll!$C$37:$Z$60,17,FALSE) -> 0 | M94: =VLOOKUP($B94,Rentroll!$C$37:$Z$60,18,FALSE) -> 1 | O94: =B94 -> 9 | R94: =IF($L94=0,0,(EOMONTH($D94,1)<=R$14)*(EOMONTH($D94,$L94)>=R$14)*1) -> 0 | S94: =IF($L94=0,0,(EOMONTH($D94,1)<=S$14)*(EOMONTH($D94,$L94)>=S$14)*1) -> 0 | T94: =IF($L94=0,0,(EOMONTH($D94,1)<=T$14)*(EOMONTH($D94,$L94)>=T$14)*1) -> 0 | U94: =IF($L94=0,0,(EOMONTH($D94,1)<=U$14)*(EOMONTH($D94,$L94)>=U$14)*1) -> 0 | V94: =IF($L94=0,0,(EOMONTH($D94,1)<=V$14)*(EOMONTH($D94,$L94)>=V$14)*1) -> 0 | W94: =IF($L94=0,0,(EOMONTH($D94,1)<=W$14)*(EOMONTH($D94,$L94)>=W$14)*1) -> 0 | X94: =IF($L94=0,0,(EOMONTH($D94,1)<=X$14)*(EOMONTH($D94,$L94)>=X$14)*1) -> 0 | Y94: =IF($L94=0,0,(EOMONTH($D94,1)<=Y$14)*(EOMONTH($D94,$L94)>=Y$14)*1) -> 0 | ... DL94: =IF($L94=0,0,(EOMONTH($D94,1)<=DL$14)*(EOMONTH($D94,$L94)>=DL$14)*1) -> 0
B95: =Rentroll!$C$46 -> 8 | C95: =VLOOKUP($B95,Rentroll!$C$37:$Z$60,3,FALSE) -> 오케스트로 | D95: =VLOOKUP($B95,Rentroll!$C$37:$Z$60,9,FALSE) -> 46477 | E95: =VLOOKUP($B95,Rentroll!$C$37:$Z$60,10,FALSE) -> 48304 | F95: =VLOOKUP($B95,Rentroll!$C$37:$Z$60,11,FALSE) -> 60 | G95: =VLOOKUP($B95,Rentroll!$C$37:$Z$60,13,FALSE) -> 109272.7 | H95: =VLOOKUP($B95,Rentroll!$C$37:$Z$60,14,FALSE) -> 100166.64 | I95: =VLOOKUP($B95,Rentroll!$C$37:$Z$60,15,FALSE) -> 47740.5 | J95: =VLOOKUP($B95,Rentroll!$C$37:$Z$60,19,FALSE) -> 0.03 | K95: =VLOOKUP($B95,Rentroll!$C$37:$Z$60,4,FALSE) -> 1385.09 | L95: =VLOOKUP($B95,Rentroll!$C$37:$Z$60,17,FALSE) -> 1 | M95: =VLOOKUP($B95,Rentroll!$C$37:$Z$60,18,FALSE) -> 1 | O95: =B95 -> 8 | R95: =IF($L95=0,0,(EOMONTH($D95,1)<=R$14)*(EOMONTH($D95,$L95)>=R$14)*1) -> 0 | S95: =IF($L95=0,0,(EOMONTH($D95,1)<=S$14)*(EOMONTH($D95,$L95)>=S$14)*1) -> 0 | T95: =IF($L95=0,0,(EOMONTH($D95,1)<=T$14)*(EOMONTH($D95,$L95)>=T$14)*1) -> 0 | U95: =IF($L95=0,0,(EOMONTH($D95,1)<=U$14)*(EOMONTH($D95,$L95)>=U$14)*1) -> 0 | V95: =IF($L95=0,0,(EOMONTH($D95,1)<=V$14)*(EOMONTH($D95,$L95)>=V$14)*1) -> 0 | W95: =IF($L95=0,0,(EOMONTH($D95,1)<=W$14)*(EOMONTH($D95,$L95)>=W$14)*1) -> 0 | X95: =IF($L95=0,0,(EOMONTH($D95,1)<=X$14)*(EOMONTH($D95,$L95)>=X$14)*1) -> 0 | Y95: =IF($L95=0,0,(EOMONTH($D95,1)<=Y$14)*(EOMONTH($D95,$L95)>=Y$14)*1) -> 0 | ... DL95: =IF($L95=0,0,(EOMONTH($D95,1)<=DL$14)*(EOMONTH($D95,$L95)>=DL$14)*1) -> 0
B96: =Rentroll!$C$47 -> 7 | C96: =VLOOKUP($B96,Rentroll!$C$37:$Z$60,3,FALSE) -> 오케스트로 | D96: =VLOOKUP($B96,Rentroll!$C$37:$Z$60,9,FALSE) -> 46477 | E96: =VLOOKUP($B96,Rentroll!$C$37:$Z$60,10,FALSE) -> 48304 | F96: =VLOOKUP($B96,Rentroll!$C$37:$Z$60,11,FALSE) -> 60 | G96: =VLOOKUP($B96,Rentroll!$C$37:$Z$60,13,FALSE) -> 109272.7 | H96: =VLOOKUP($B96,Rentroll!$C$37:$Z$60,14,FALSE) -> 100166.64 | I96: =VLOOKUP($B96,Rentroll!$C$37:$Z$60,15,FALSE) -> 47740.5 | J96: =VLOOKUP($B96,Rentroll!$C$37:$Z$60,19,FALSE) -> 0.03 | K96: =VLOOKUP($B96,Rentroll!$C$37:$Z$60,4,FALSE) -> 1385.09 | L96: =VLOOKUP($B96,Rentroll!$C$37:$Z$60,17,FALSE) -> 1 | M96: =VLOOKUP($B96,Rentroll!$C$37:$Z$60,18,FALSE) -> 1 | O96: =B96 -> 7 | R96: =IF($L96=0,0,(EOMONTH($D96,1)<=R$14)*(EOMONTH($D96,$L96)>=R$14)*1) -> 0 | S96: =IF($L96=0,0,(EOMONTH($D96,1)<=S$14)*(EOMONTH($D96,$L96)>=S$14)*1) -> 0 | T96: =IF($L96=0,0,(EOMONTH($D96,1)<=T$14)*(EOMONTH($D96,$L96)>=T$14)*1) -> 0 | U96: =IF($L96=0,0,(EOMONTH($D96,1)<=U$14)*(EOMONTH($D96,$L96)>=U$14)*1) -> 0 | V96: =IF($L96=0,0,(EOMONTH($D96,1)<=V$14)*(EOMONTH($D96,$L96)>=V$14)*1) -> 0 | W96: =IF($L96=0,0,(EOMONTH($D96,1)<=W$14)*(EOMONTH($D96,$L96)>=W$14)*1) -> 0 | X96: =IF($L96=0,0,(EOMONTH($D96,1)<=X$14)*(EOMONTH($D96,$L96)>=X$14)*1) -> 0 | Y96: =IF($L96=0,0,(EOMONTH($D96,1)<=Y$14)*(EOMONTH($D96,$L96)>=Y$14)*1) -> 0 | ... DL96: =IF($L96=0,0,(EOMONTH($D96,1)<=DL$14)*(EOMONTH($D96,$L96)>=DL$14)*1) -> 0
B97: =Rentroll!$C$48 -> 6 | C97: =VLOOKUP($B97,Rentroll!$C$37:$Z$60,3,FALSE) -> 오케스트로 | D97: =VLOOKUP($B97,Rentroll!$C$37:$Z$60,9,FALSE) -> 46477 | E97: =VLOOKUP($B97,Rentroll!$C$37:$Z$60,10,FALSE) -> 48304 | F97: =VLOOKUP($B97,Rentroll!$C$37:$Z$60,11,FALSE) -> 60 | G97: =VLOOKUP($B97,Rentroll!$C$37:$Z$60,13,FALSE) -> 109272.7 | H97: =VLOOKUP($B97,Rentroll!$C$37:$Z$60,14,FALSE) -> 100166.64 | I97: =VLOOKUP($B97,Rentroll!$C$37:$Z$60,15,FALSE) -> 47740.5 | J97: =VLOOKUP($B97,Rentroll!$C$37:$Z$60,19,FALSE) -> 0.03 | K97: =VLOOKUP($B97,Rentroll!$C$37:$Z$60,4,FALSE) -> 1385.09 | L97: =VLOOKUP($B97,Rentroll!$C$37:$Z$60,17,FALSE) -> 1 | M97: =VLOOKUP($B97,Rentroll!$C$37:$Z$60,18,FALSE) -> 1 | O97: =B97 -> 6 | R97: =IF($L97=0,0,(EOMONTH($D97,1)<=R$14)*(EOMONTH($D97,$L97)>=R$14)*1) -> 0 | S97: =IF($L97=0,0,(EOMONTH($D97,1)<=S$14)*(EOMONTH($D97,$L97)>=S$14)*1) -> 0 | T97: =IF($L97=0,0,(EOMONTH($D97,1)<=T$14)*(EOMONTH($D97,$L97)>=T$14)*1) -> 0 | U97: =IF($L97=0,0,(EOMONTH($D97,1)<=U$14)*(EOMONTH($D97,$L97)>=U$14)*1) -> 0 | V97: =IF($L97=0,0,(EOMONTH($D97,1)<=V$14)*(EOMONTH($D97,$L97)>=V$14)*1) -> 0 | W97: =IF($L97=0,0,(EOMONTH($D97,1)<=W$14)*(EOMONTH($D97,$L97)>=W$14)*1) -> 0 | X97: =IF($L97=0,0,(EOMONTH($D97,1)<=X$14)*(EOMONTH($D97,$L97)>=X$14)*1) -> 0 | Y97: =IF($L97=0,0,(EOMONTH($D97,1)<=Y$14)*(EOMONTH($D97,$L97)>=Y$14)*1) -> 0 | ... DL97: =IF($L97=0,0,(EOMONTH($D97,1)<=DL$14)*(EOMONTH($D97,$L97)>=DL$14)*1) -> 0
B98: =Rentroll!$C$49 -> 5 | C98: =VLOOKUP($B98,Rentroll!$C$37:$Z$60,3,FALSE) -> 타이거로켓 | D98: =VLOOKUP($B98,Rentroll!$C$37:$Z$60,9,FALSE) -> 45688 | E98: =VLOOKUP($B98,Rentroll!$C$37:$Z$60,10,FALSE) -> 47514 | F98: =VLOOKUP($B98,Rentroll!$C$37:$Z$60,11,FALSE) -> 60 | G98: =VLOOKUP($B98,Rentroll!$C$37:$Z$60,13,FALSE) -> 103000 | H98: =VLOOKUP($B98,Rentroll!$C$37:$Z$60,14,FALSE) -> 90125 | I98: =VLOOKUP($B98,Rentroll!$C$37:$Z$60,15,FALSE) -> 45000 | J98: =VLOOKUP($B98,Rentroll!$C$37:$Z$60,19,FALSE) -> 0.03 | K98: =VLOOKUP($B98,Rentroll!$C$37:$Z$60,4,FALSE) -> 1385.09 | L98: =VLOOKUP($B98,Rentroll!$C$37:$Z$60,17,FALSE) -> 1 | M98: =VLOOKUP($B98,Rentroll!$C$37:$Z$60,18,FALSE) -> 1.5 | O98: =B98 -> 5 | R98: =IF($L98=0,0,(EOMONTH($D98,1)<=R$14)*(EOMONTH($D98,$L98)>=R$14)*1) -> 0 | S98: =IF($L98=0,0,(EOMONTH($D98,1)<=S$14)*(EOMONTH($D98,$L98)>=S$14)*1) -> 1 | T98: =IF($L98=0,0,(EOMONTH($D98,1)<=T$14)*(EOMONTH($D98,$L98)>=T$14)*1) -> 0 | U98: =IF($L98=0,0,(EOMONTH($D98,1)<=U$14)*(EOMONTH($D98,$L98)>=U$14)*1) -> 0 | V98: =IF($L98=0,0,(EOMONTH($D98,1)<=V$14)*(EOMONTH($D98,$L98)>=V$14)*1) -> 0 | W98: =IF($L98=0,0,(EOMONTH($D98,1)<=W$14)*(EOMONTH($D98,$L98)>=W$14)*1) -> 0 | X98: =IF($L98=0,0,(EOMONTH($D98,1)<=X$14)*(EOMONTH($D98,$L98)>=X$14)*1) -> 0 | Y98: =IF($L98=0,0,(EOMONTH($D98,1)<=Y$14)*(EOMONTH($D98,$L98)>=Y$14)*1) -> 0 | ... DL98: =IF($L98=0,0,(EOMONTH($D98,1)<=DL$14)*(EOMONTH($D98,$L98)>=DL$14)*1) -> 0
B99: =Rentroll!$C$50 -> 4 | C99: =VLOOKUP($B99,Rentroll!$C$37:$Z$60,3,FALSE) -> 타이거로켓 | D99: =VLOOKUP($B99,Rentroll!$C$37:$Z$60,9,FALSE) -> 45688 | E99: =VLOOKUP($B99,Rentroll!$C$37:$Z$60,10,FALSE) -> 47514 | F99: =VLOOKUP($B99,Rentroll!$C$37:$Z$60,11,FALSE) -> 60 | G99: =VLOOKUP($B99,Rentroll!$C$37:$Z$60,13,FALSE) -> 103000 | H99: =VLOOKUP($B99,Rentroll!$C$37:$Z$60,14,FALSE) -> 90125 | I99: =VLOOKUP($B99,Rentroll!$C$37:$Z$60,15,FALSE) -> 45000 | J99: =VLOOKUP($B99,Rentroll!$C$37:$Z$60,19,FALSE) -> 0.03 | K99: =VLOOKUP($B99,Rentroll!$C$37:$Z$60,4,FALSE) -> 1385.09 | L99: =VLOOKUP($B99,Rentroll!$C$37:$Z$60,17,FALSE) -> 1 | M99: =VLOOKUP($B99,Rentroll!$C$37:$Z$60,18,FALSE) -> 1.5 | O99: =B99 -> 4 | R99: =IF($L99=0,0,(EOMONTH($D99,1)<=R$14)*(EOMONTH($D99,$L99)>=R$14)*1) -> 0 | S99: =IF($L99=0,0,(EOMONTH($D99,1)<=S$14)*(EOMONTH($D99,$L99)>=S$14)*1) -> 1 | T99: =IF($L99=0,0,(EOMONTH($D99,1)<=T$14)*(EOMONTH($D99,$L99)>=T$14)*1) -> 0 | U99: =IF($L99=0,0,(EOMONTH($D99,1)<=U$14)*(EOMONTH($D99,$L99)>=U$14)*1) -> 0 | V99: =IF($L99=0,0,(EOMONTH($D99,1)<=V$14)*(EOMONTH($D99,$L99)>=V$14)*1) -> 0 | W99: =IF($L99=0,0,(EOMONTH($D99,1)<=W$14)*(EOMONTH($D99,$L99)>=W$14)*1) -> 0 | X99: =IF($L99=0,0,(EOMONTH($D99,1)<=X$14)*(EOMONTH($D99,$L99)>=X$14)*1) -> 0 | Y99: =IF($L99=0,0,(EOMONTH($D99,1)<=Y$14)*(EOMONTH($D99,$L99)>=Y$14)*1) -> 0 | ... DL99: =IF($L99=0,0,(EOMONTH($D99,1)<=DL$14)*(EOMONTH($D99,$L99)>=DL$14)*1) -> 0
B100: =Rentroll!$C$51 -> 3 | C100: =VLOOKUP($B100,Rentroll!$C$37:$Z$60,3,FALSE) -> 타이거로켓 | D100: =VLOOKUP($B100,Rentroll!$C$37:$Z$60,9,FALSE) -> 45688 | E100: =VLOOKUP($B100,Rentroll!$C$37:$Z$60,10,FALSE) -> 47514 | F100: =VLOOKUP($B100,Rentroll!$C$37:$Z$60,11,FALSE) -> 60 | G100: =VLOOKUP($B100,Rentroll!$C$37:$Z$60,13,FALSE) -> 103000 | H100: =VLOOKUP($B100,Rentroll!$C$37:$Z$60,14,FALSE) -> 90125 | I100: =VLOOKUP($B100,Rentroll!$C$37:$Z$60,15,FALSE) -> 45000 | J100: =VLOOKUP($B100,Rentroll!$C$37:$Z$60,19,FALSE) -> 0.03 | K100: =VLOOKUP($B100,Rentroll!$C$37:$Z$60,4,FALSE) -> 1385.09 | L100: =VLOOKUP($B100,Rentroll!$C$37:$Z$60,17,FALSE) -> 1 | M100: =VLOOKUP($B100,Rentroll!$C$37:$Z$60,18,FALSE) -> 1.5 | O100: =B100 -> 3 | R100: =IF($L100=0,0,(EOMONTH($D100,1)<=R$14)*(EOMONTH($D100,$L100)>=R$14)*1) -> 0 | S100: =IF($L100=0,0,(EOMONTH($D100,1)<=S$14)*(EOMONTH($D100,$L100)>=S$14)*1) -> 1 | T100: =IF($L100=0,0,(EOMONTH($D100,1)<=T$14)*(EOMONTH($D100,$L100)>=T$14)*1) -> 0 | U100: =IF($L100=0,0,(EOMONTH($D100,1)<=U$14)*(EOMONTH($D100,$L100)>=U$14)*1) -> 0 | V100: =IF($L100=0,0,(EOMONTH($D100,1)<=V$14)*(EOMONTH($D100,$L100)>=V$14)*1) -> 0 | W100: =IF($L100=0,0,(EOMONTH($D100,1)<=W$14)*(EOMONTH($D100,$L100)>=W$14)*1) -> 0 | X100: =IF($L100=0,0,(EOMONTH($D100,1)<=X$14)*(EOMONTH($D100,$L100)>=X$14)*1) -> 0 | Y100: =IF($L100=0,0,(EOMONTH($D100,1)<=Y$14)*(EOMONTH($D100,$L100)>=Y$14)*1) -> 0 | ... DL100: =IF($L100=0,0,(EOMONTH($D100,1)<=DL$14)*(EOMONTH($D100,$L100)>=DL$14)*1) -> 0
B101: =Rentroll!$C$52 -> 201호 | C101: =VLOOKUP($B101,Rentroll!$C$37:$Z$60,3,FALSE) -> RMW CARNE | D101: =VLOOKUP($B101,Rentroll!$C$37:$Z$60,9,FALSE) -> 45747 | E101: =VLOOKUP($B101,Rentroll!$C$37:$Z$60,10,FALSE) -> 47573 | F101: =VLOOKUP($B101,Rentroll!$C$37:$Z$60,11,FALSE) -> 60 | G101: =VLOOKUP($B101,Rentroll!$C$37:$Z$60,13,FALSE) -> 130000 | H101: =VLOOKUP($B101,Rentroll!$C$37:$Z$60,14,FALSE) -> 130000 | I101: =VLOOKUP($B101,Rentroll!$C$37:$Z$60,15,FALSE) -> 45000 | J101: =VLOOKUP($B101,Rentroll!$C$37:$Z$60,19,FALSE) -> 0.03 | K101: =VLOOKUP($B101,Rentroll!$C$37:$Z$60,4,FALSE) -> 346.2725 | L101: =VLOOKUP($B101,Rentroll!$C$37:$Z$60,17,FALSE) -> 2 | M101: =VLOOKUP($B101,Rentroll!$C$37:$Z$60,18,FALSE) -> 0 | O101: =B101 -> 201호 | R101: =IF($L101=0,0,(EOMONTH($D101,1)<=R$14)*(EOMONTH($D101,$L101)>=R$14)*1) -> 0 | S101: =IF($L101=0,0,(EOMONTH($D101,1)<=S$14)*(EOMONTH($D101,$L101)>=S$14)*1) -> 0 | T101: =IF($L101=0,0,(EOMONTH($D101,1)<=T$14)*(EOMONTH($D101,$L101)>=T$14)*1) -> 0 | U101: =IF($L101=0,0,(EOMONTH($D101,1)<=U$14)*(EOMONTH($D101,$L101)>=U$14)*1) -> 1 | V101: =IF($L101=0,0,(EOMONTH($D101,1)<=V$14)*(EOMONTH($D101,$L101)>=V$14)*1) -> 1 | W101: =IF($L101=0,0,(EOMONTH($D101,1)<=W$14)*(EOMONTH($D101,$L101)>=W$14)*1) -> 0 | X101: =IF($L101=0,0,(EOMONTH($D101,1)<=X$14)*(EOMONTH($D101,$L101)>=X$14)*1) -> 0 | Y101: =IF($L101=0,0,(EOMONTH($D101,1)<=Y$14)*(EOMONTH($D101,$L101)>=Y$14)*1) -> 0 | ... DL101: =IF($L101=0,0,(EOMONTH($D101,1)<=DL$14)*(EOMONTH($D101,$L101)>=DL$14)*1) -> 0
B102: =Rentroll!$C$53 -> 202호 | C102: =VLOOKUP($B102,Rentroll!$C$37:$Z$60,3,FALSE) -> 키이로 | D102: =VLOOKUP($B102,Rentroll!$C$37:$Z$60,9,FALSE) -> 45747 | E102: =VLOOKUP($B102,Rentroll!$C$37:$Z$60,10,FALSE) -> 47573 | F102: =VLOOKUP($B102,Rentroll!$C$37:$Z$60,11,FALSE) -> 60 | G102: =VLOOKUP($B102,Rentroll!$C$37:$Z$60,13,FALSE) -> 130000 | H102: =VLOOKUP($B102,Rentroll!$C$37:$Z$60,14,FALSE) -> 130000 | I102: =VLOOKUP($B102,Rentroll!$C$37:$Z$60,15,FALSE) -> 45000 | J102: =VLOOKUP($B102,Rentroll!$C$37:$Z$60,19,FALSE) -> 0.03 | K102: =VLOOKUP($B102,Rentroll!$C$37:$Z$60,4,FALSE) -> 346.2725 | L102: =VLOOKUP($B102,Rentroll!$C$37:$Z$60,17,FALSE) -> 2 | M102: =VLOOKUP($B102,Rentroll!$C$37:$Z$60,18,FALSE) -> 0 | O102: =B102 -> 202호 | R102: =IF($L102=0,0,(EOMONTH($D102,1)<=R$14)*(EOMONTH($D102,$L102)>=R$14)*1) -> 0 | S102: =IF($L102=0,0,(EOMONTH($D102,1)<=S$14)*(EOMONTH($D102,$L102)>=S$14)*1) -> 0 | T102: =IF($L102=0,0,(EOMONTH($D102,1)<=T$14)*(EOMONTH($D102,$L102)>=T$14)*1) -> 0 | U102: =IF($L102=0,0,(EOMONTH($D102,1)<=U$14)*(EOMONTH($D102,$L102)>=U$14)*1) -> 1 | V102: =IF($L102=0,0,(EOMONTH($D102,1)<=V$14)*(EOMONTH($D102,$L102)>=V$14)*1) -> 1 | W102: =IF($L102=0,0,(EOMONTH($D102,1)<=W$14)*(EOMONTH($D102,$L102)>=W$14)*1) -> 0 | X102: =IF($L102=0,0,(EOMONTH($D102,1)<=X$14)*(EOMONTH($D102,$L102)>=X$14)*1) -> 0 | Y102: =IF($L102=0,0,(EOMONTH($D102,1)<=Y$14)*(EOMONTH($D102,$L102)>=Y$14)*1) -> 0 | ... DL102: =IF($L102=0,0,(EOMONTH($D102,1)<=DL$14)*(EOMONTH($D102,$L102)>=DL$14)*1) -> 0
B103: =Rentroll!$C$54 -> 203호 | C103: =VLOOKUP($B103,Rentroll!$C$37:$Z$60,3,FALSE) -> 주 052 | D103: =VLOOKUP($B103,Rentroll!$C$37:$Z$60,9,FALSE) -> 45747 | E103: =VLOOKUP($B103,Rentroll!$C$37:$Z$60,10,FALSE) -> 47573 | F103: =VLOOKUP($B103,Rentroll!$C$37:$Z$60,11,FALSE) -> 60 | G103: =VLOOKUP($B103,Rentroll!$C$37:$Z$60,13,FALSE) -> 130000 | H103: =VLOOKUP($B103,Rentroll!$C$37:$Z$60,14,FALSE) -> 130000 | I103: =VLOOKUP($B103,Rentroll!$C$37:$Z$60,15,FALSE) -> 45000 | J103: =VLOOKUP($B103,Rentroll!$C$37:$Z$60,19,FALSE) -> 0.03 | K103: =VLOOKUP($B103,Rentroll!$C$37:$Z$60,4,FALSE) -> 346.2725 | L103: =VLOOKUP($B103,Rentroll!$C$37:$Z$60,17,FALSE) -> 2 | M103: =VLOOKUP($B103,Rentroll!$C$37:$Z$60,18,FALSE) -> 0 | O103: =B103 -> 203호 | R103: =IF($L103=0,0,(EOMONTH($D103,1)<=R$14)*(EOMONTH($D103,$L103)>=R$14)*1) -> 0 | S103: =IF($L103=0,0,(EOMONTH($D103,1)<=S$14)*(EOMONTH($D103,$L103)>=S$14)*1) -> 0 | T103: =IF($L103=0,0,(EOMONTH($D103,1)<=T$14)*(EOMONTH($D103,$L103)>=T$14)*1) -> 0 | U103: =IF($L103=0,0,(EOMONTH($D103,1)<=U$14)*(EOMONTH($D103,$L103)>=U$14)*1) -> 1 | V103: =IF($L103=0,0,(EOMONTH($D103,1)<=V$14)*(EOMONTH($D103,$L103)>=V$14)*1) -> 1 | W103: =IF($L103=0,0,(EOMONTH($D103,1)<=W$14)*(EOMONTH($D103,$L103)>=W$14)*1) -> 0 | X103: =IF($L103=0,0,(EOMONTH($D103,1)<=X$14)*(EOMONTH($D103,$L103)>=X$14)*1) -> 0 | Y103: =IF($L103=0,0,(EOMONTH($D103,1)<=Y$14)*(EOMONTH($D103,$L103)>=Y$14)*1) -> 0 | ... DL103: =IF($L103=0,0,(EOMONTH($D103,1)<=DL$14)*(EOMONTH($D103,$L103)>=DL$14)*1) -> 0
...

Sheet 운영수입
B2: Team LAVEL | T2: 변수입력 | U2: 합계1 | V2: 제목
B3: KBC타워 재무모델 | T3: 적정성확인 | U3: 합계2 | V3: 표제목
T4: 오류확인 | U4: 합계3 | V4: 작성자참고
A6: 단위: 백만원
A7: 운영수입
S8: 구분 | T8: 1 | U8: 2 | V8: 3 | W8: 4 | X8: 5 | Y8: 6 | Z8: 7 | AA8: 8 | AB8: 9 | AC8: 10 | AD8: 11 | AE8: 12 | AF8: 13 | AG8: 14 | AH8: 15 | AI8: 16
S9: 시작월 | T9: =start -> 45716 | U9: =EOMONTH(T10,1) -> 45900 | V9: =EOMONTH(U10,1) -> 46081 | W9: =EOMONTH(V10,1) -> 46265 | X9: =EOMONTH(W10,1) -> 46446 | Y9: =EOMONTH(X10,1) -> 46630 | Z9: =EOMONTH(Y10,1) -> 46812 | AA9: =EOMONTH(Z10,1) -> 46996 | AB9: =EOMONTH(AA10,1) -> 47177 | ... AI9: =EOMONTH(AH10,1) -> 48457
S10: 종료월 | T10: =EOMONTH(T9,period-1) -> 45869 | U10: =EOMONTH(U9,period-1) -> 46053 | V10: =EOMONTH(V9,period-1) -> 46234 | W10: =EOMONTH(W9,period-1) -> 46418 | X10: =EOMONTH(X9,period-1) -> 46599 | Y10: =EOMONTH(Y9,period-1) -> 46783 | Z10: =EOMONTH(Z9,period-1) -> 46965 | AA10: =EOMONTH(AA9,period-1) -> 47149 | ... AI10: =EOMONTH(AI9,period-1) -> 48610
P11: 운영기간Index | S11: =(S14>=[0]!start)*(S14<=[0]!exit)*1 -> 0 | T11: =(T14>=[0]!start)*(T14<=[0]!exit)*1 -> 1 | U11: =(U14>=[0]!start)*(U14<=[0]!exit)*1 -> 1 | V11: =(V14>=[0]!start)*(V14<=[0]!exit)*1 -> 1 | W11: =(W14>=[0]!start)*(W14<=[0]!exit)*1 -> 1 | X11: =(X14>=[0]!start)*(X14<=[0]!exit)*1 -> 1 | Y11: =(Y14>=[0]!start)*(Y14<=[0]!exit)*1 -> 1 | Z11: =(Z14>=[0]!start)*(Z14<=[0]!exit)*1 -> 1 | ... DM11: =(DM14>=[0]!start)*(DM14<=[0]!exit)*1 -> 0
P12: 누적운영기간Index | S12: =SUM($S$11:S11)*S11 -> 0 | T12: =SUM($S$11:T11)*T11 -> 1 | U12: =SUM($S$11:U11)*U11 -> 2 | V12: =SUM($S$11:V11)*V11 -> 3 | W12: =SUM($S$11:W11)*W11 -> 4 | X12: =SUM($S$11:X11)*X11 -> 5 | Y12: =SUM($S$11:Y11)*Y11 -> 6 | Z12: =SUM($S$11:Z11)*Z11 -> 7 | ... DM12: =SUM($S$11:DM11)*DM11 -> 0
P13: 12개월Index | S13: =(MOD(S12,12)=1)*1 -> 0 | T13: =(MOD(T12,12)=1)*1 -> 1 | U13: =(MOD(U12,12)=1)*1 -> 0 | V13: =(MOD(V12,12)=1)*1 -> 0 | W13: =(MOD(W12,12)=1)*1 -> 0 | X13: =(MOD(X12,12)=1)*1 -> 0 | Y13: =(MOD(Y12,12)=1)*1 -> 0 | Z13: =(MOD(Z12,12)=1)*1 -> 0 | ... DM13: =(MOD(DM12,12)=1)*1 -> 0
P14: Date | S14: =acq -> 45688 | T14: =EOMONTH(S14,1) -> 45716 | U14: =EOMONTH(T14,1) -> 45747 | V14: =EOMONTH(U14,1) -> 45777 | W14: =EOMONTH(V14,1) -> 45808 | X14: =EOMONTH(W14,1) -> 45838 | Y14: =EOMONTH(X14,1) -> 45869 | Z14: =EOMONTH(Y14,1) -> 45900 | AA14: =EOMONTH(Z14,1) -> 45930 | ... DM14: =EOMONTH(DL14,1) -> 48669
P15: 회계기간 | S15: =SUMIFS($T$8:$AI$8,$T$9:$AI$9,"<="&S$14,$T$10:$AI$10,">="&S$14) -> 0 | T15: =SUMIFS($T$8:$AI$8,$T$9:$AI$9,"<="&T$14,$T$10:$AI$10,">="&T$14) -> 1 | U15: =SUMIFS($T$8:$AI$8,$T$9:$AI$9,"<="&U$14,$T$10:$AI$10,">="&U$14) -> 1 | V15: =SUMIFS($T$8:$AI$8,$T$9:$AI$9,"<="&V$14,$T$10:$AI$10,">="&V$14) -> 1 | W15: =SUMIFS($T$8:$AI$8,$T$9:$AI$9,"<="&W$14,$T$10:$AI$10,">="&W$14) -> 1 | X15: =SUMIFS($T$8:$AI$8,$T$9:$AI$9,"<="&X$14,$T$10:$AI$10,">="&X$14) -> 1 | Y15: =SUMIFS($T$8:$AI$8,$T$9:$AI$9,"<="&Y$14,$T$10:$AI$10,">="&Y$14) -> 1 | Z15: =SUMIFS($T$8:$AI$8,$T$9:$AI$9,"<="&Z$14,$T$10:$AI$10,">="&Z$14) -> 2 | ... DM15: =SUMIFS($T$8:$AI$8,$T$9:$AI$9,"<="&DM$14,$T$10:$AI$10,">="&DM$14) -> 0
P16: 운영년차 | S16: =SUM($S$13:S13)*S11 -> 0 | T16: =SUM($S$13:T13)*T11 -> 1 | U16: =SUM($S$13:U13)*U11 -> 1 | V16: =SUM($S$13:V13)*V11 -> 1 | W16: =SUM($S$13:W13)*W11 -> 1 | X16: =SUM($S$13:X13)*X11 -> 1 | Y16: =SUM($S$13:Y13)*Y11 -> 1 | Z16: =SUM($S$13:Z13)*Z11 -> 1 | ... DM16: =SUM($S$13:DM13)*DM11 -> 0
B18: 임대료 {현(위) 및 신규(아래) 임대차 계약} | O18: 실질 임대료 수익 | Q18: =SUM(S18:DM18) -> 42367.537 | S18: =S19+S39 -> 0 | T18: =T19+T39 -> 430.67443 | U18: =U19+U39 -> 519.40355 | V18: =V19+V39 -> 522.704 | W18: =W19+W39 -> 536.32117 | X18: =X19+X39 -> 580.40936 | Y18: =Y19+Y39 -> 580.40936 | Z18: =Z19+Z39 -> 511.22439 | ... DM18: =DM19+DM39 -> 0
B19: 층수 | C19: 임차인 | D19: 시작일 | E19: 종료일 | F19: 기간 | G19: 명목 임대료(원) | H19: 실질 임대료(원) | I19: 관리비(원) | J19: 상승률 | K19: 임대면적(㎡) | L19: Fitout | M19: Rentfree | O19: 기존 임대차 | Q19: =SUM(S19:DM19) -> 11750.282 | S19: =SUM(S20:S38) -> 0 | T19: =SUM(T20:T38) -> 430.67443 | U19: =SUM(U20:U38) -> 406.1192 | V19: =SUM(V20:V38) -> 409.41966 | W19: =SUM(W20:W38) -> 409.41966 | X19: =SUM(X20:X38) -> 412.65635 | Y19: =SUM(Y20:Y38) -> 412.65635 | Z19: =SUM(Z20:Z38) -> 299.47759 | ... DM19: =SUM(DM20:DM38) -> 0
B20: =Rentroll!$C$11 -> 17 | C20: =VLOOKUP($B20,Rentroll!$C$11:$X$29,3,FALSE) -> 리마 상사 | D20: =VLOOKUP($B20,Rentroll!$C$11:$X$29,9,FALSE) -> 45322 | E20: =VLOOKUP($B20,Rentroll!$C$11:$X$29,10,FALSE) -> 47148 | F20: =VLOOKUP($B20,Rentroll!$C$11:$X$29,11,FALSE) -> 60 | G20: =VLOOKUP($B20,Rentroll!$C$11:$X$29,13,FALSE) -> 100000 | H20: =VLOOKUP($B20,Rentroll!$C$11:$X$29,14,FALSE) -> 75000 | I20: =VLOOKUP($B20,Rentroll!$C$11:$X$29,15,FALSE) -> 45000 | J20: =VLOOKUP($B20,Rentroll!$C$11:$X$29,19,FALSE) -> 0.03 | K20: =VLOOKUP($B20,Rentroll!$C$11:$X$29,4,FALSE) -> 1385.09 | L20: =VLOOKUP($B20,Rentroll!$C$11:$X$29,17,FALSE) -> 0 | M20: =VLOOKUP($B20,Rentroll!$C$11:$X$29,18,FALSE) -> 3 | O20: =B20 -> 17 | Q20: =SUM(S20:DM20) -> 1577.6071 | S20: =IF(Index!R66=1,0,$H20*$K20*py*Index!R19*Index!R160/unit) -> 0 | T20: =IF(Index!S66=1,0,$H20*$K20*py*Index!S19*Index!S160/unit) -> 31.424229 | U20: =IF(Index!T66=1,0,$H20*$K20*py*Index!T19*Index!T160/unit) -> 31.424229 | V20: =IF(Index!U66=1,0,$H20*$K20*py*Index!U19*Index!U160/unit) -> 31.424229 | W20: =IF(Index!V66=1,0,$H20*$K20*py*Index!V19*Index!V160/unit) -> 31.424229 | X20: =IF(Index!W66=1,0,$H20*$K20*py*Index!W19*Index!W160/unit) -> 31.424229 | Y20: =IF(Index!X66=1,0,$H20*$K20*py*Index!X19*Index!X160/unit) -> 31.424229 | Z20: =IF(Index!Y66=1,0,$H20*$K20*py*Index!Y19*Index!Y160/unit) -> 31.424229 | ... DM20: =IF(Index!DL66=1,0,$H20*$K20*py*Index!DL19*Index!DL160/unit) -> 0
